Workbook

Sheet Participants-Parties
A1: Opened - Day | B1: Opened - Time | C1: Party | D1: Job | E1: Status | F1: Priority | G1: Situation | H1: Type
A2: Satuday | B2: 0.54166667 | C2: Clairia | D2: Keeper | E2: Hopefully fixed | F2: Low | G2: Keeper tweaked an ankle while walking. Sounds minor, but should have a medical check-in at lunch. -Scaz Kristi - JulieL checked her out and she's fine. "It hurt for a sec; it's fine now." | H2: Medical
A3: Friday | B3: 0.78125 | C3: P'Loa | E3: Hopefully fixed | F3: High | G3: participant suddenly feeling light-headed, sweaty; Steve found Abigail. Julie Leviter checking in on him. Maisie's husband is being sent to hospiatal. Ab called 911 Maise (compantion) may be going with him. Jodi 6:50 Maise is going with her husband ... Tennile is talkin to Joyce about being doloron companion for evening jodi 7:15 | H3: Medical
A4: Friday | B4: 0.77083333 | C4: Uri-Kesh | D4: Traveler | E4: Hopefully fixed | F4: Low | G4: Linda walked a participant from urikesh through the basement staff area with eyes closed. Linda said she had been feeling overwhelmed. Talked to Bill later and participant had gone stragiht into combat workshops. He didn't know how that went. - jodi fri 6:50 Chris - checked in with Bill; he is "not concerned at the moment". They're getting ready to leave the tavern now 8:30pm Kristi - Raja (the traveler) approached Linda (as Valentina) and says she's doing fine now. Let's check in with Bill in the morning but if she's still good, we can call this hopefully fixed. I downgraded this to Low. (10:30pm) Kristi - Bill is not worried. Closing this (8:45am)
A5: Friday | B5: 0.8125 | C5: Doloron | D5: Other | E5: Hopefully fixed | F5: Low | G5: joyce will be companion for doloron friday night. She is delivering her contact info to her party and then will meet up with doloron. She is willing to keep going as companion past today if needed and says her schedule is pretty clear. (trial coordinator for claria sunday) jodi 7:40 joyce says that since son does not have a guardian ... worth it to get a medical power attorney
A6: Friday | B6: 0.91666667 | C6: P'Loa | D6: Keeper | E6: Hopefully fixed | F6: Low | G6: Kristi - Maisie mentioned that Orlando (real name) was nervous about attending but was feeling comfortable because he's with Matt. Matt isn't coming back so we're just making sure Orlando is having fun and not getting too anxious. (10pm) Kristi - JenP had an early encounter with Orlando and he was given coffee and is in good spirits (7:30am)
A7: Satuday | B7: 0.3125 | C7: Sythwan | D7: Seeker | E7: Hopefully fixed | F7: Low | G7: Kristi - We have a participant in Clairia (Kai) who's flying out of Logan at 8pm on Sunday. Would Caro (Seeker) be willing to drive her on Sunday? If not, we have other options but Caro is the best. Give answer to MattM after we know. (7:30am) Kristi - Lori is going to ask Caro. I told her a No now is better than a Yes that changes later. (9:15am) Kristi - DaveN says Lori says Caro says Yes. Yay! Telling MattM (9:18am)
A8: Friday | B8: 0.95833333 | C8: Noctara | D8: Other | E8: Hopefully fixed | F8: Low | G8: Melissa (recorded by Reichert)Provided party with 5 towels from the comfort comittee
A9: Satuday | B9: 0.33333333 | C9: Doloron | D9: Other | E9: Hopefully fixed | F9: High | G9: Chris -- Need to ask Joyce for her input on handing out party path items today. War Band is ready to take over for her, want to confirm that she is OK with this
A10: Satuday | B10: 0.375 | C10: Keer | D10: Seeker | E10: Hopefully fixed | F10: Low | G10: Ari a bit tired, might need a nap later, we'll see (CR)
A11: Satuday | B11: 0.375 | C11: Waylon | D11: Maker | E11: Hopefully fixed | F11: Low | G11: CR: Companion syas Tarik (Maker ) and SLedge (Keeper) would be good to pair with magic items, will help them engage a bite more | H11: Opportunity!
A12: Satuday | B12: 0.375 | C12: Clairia | D12: Maker | E12: Hopefully fixed | F12: Low | G12: Tasar? is tired this morning (blue hair) (group in general has a bit of morning grumbling). There is a 3:3 split between moving slow and getting going.(CR)
A13: Satuday | B13: 0.375 | C13: Elsewhich | D13: Other | E13: Hopefully fixed | F13: Low | G13: Would be good to pair magic items across internal lines (per companion brief) (CR) | H13: Opportunity!
A14: Satuday | B14: 0.52083333 | C14: Uri-Kesh | D14: Seeker | E14: Hopefully fixed | F14: High | G14: Seeker from Uri-Kesh is asking to go home. Spoke with CR on the tavern porch. He's clear on his reasons and we think getting him away from the rest of the party ASAP is the right move. He came alone and has his own car. Sending him out as of lunch. -BS 12:30 CR: Gray is gone
A15: Satuday | B15: 0.66666667 | C15: Sythwan | D15: Other | E15: Hopefully fixed | F15: High | G15: Kristi - Not a problem; just please give Lori the Sunday morning keeper vision! Thank you! :) | H15: Opportunity!
A16: Satuday | B16: 0.54166667 | C16: Uri-Kesh | D16: Traveler | E16: Hopefully fixed | F16: Low | G16: Needs a lunch time check in to verify that she is on track
A17: Satuday | B17: 0.35416667 | C17: Noctara | D17: Other | E17: Hopefully fixed | F17: Low | G17: CR: Via companion, they are really into Banshee lore, Pendant of Fortune d'Oro would be a big win for them RD: Told Margot before she went out. We'll try. j: they did get the pendant ..recognized immediately and were very excited. | H17: Opportunity!
A18: Satuday | B18: 0.375 | C18: Keer | D18: Ranger | E18: Hopefully fixed | F18: Low | G18: Kristi - BobM reports that Nietz (Martin) is holding himself apart. Not worried about it yet but worth keeping an eye on. (He was supposed to be here with his daughter but she had to cancel last minute. Also note that Martin lost a son to an overdose a couple years back so please just watch this as grief/Rites plot ramps up. - this is just Kristi talking, not BobM) (9am) CR-Companion reports that this is improving but should remain monitored)
A19: Satuday | B19: 0.375 | C19: Clairia | D19: Traveler | E19: Monitoring | F19: Low | G19: Obscura is terrified to be here, need to bring her into things with some attention, suggested hitting som eupbeat sites this AM, like peacocks (CR) Traveler requested first a cane (given by MMiles at 12:00) and then a knee brace and wrap (given by companion at 12:20). We should have one the medical staff check in at lunch with her. -BS, 12:20SAT 1:15 (CR) Julie L checked in with Natalie, she is coping but may need accomodation at 8[pm meeting. Kristi - JulieL talked to her again. She doesn't want to let her group down. She doesn't know the others in the group (besides her boyfriend and friend) and is feeling worried about letting them down. The pain is her baseline; she's dealing with it. Julie is reinforcing that it's okay to take naps or breaks or to speak up. Julie was also telling her that the story is going to get scarier; that's not her, it's just how the story is. (1:45pm) Scaz: Julie checked on her again at 4pm. Thinks she's doing ok. Jodi: gave her and other clarian resting in front of the tavern charge information. They were looking to get back with with group, had been planning on investigating the morg for danny charge (but it was a ghost theater). A bit timid but engaged. | H19: Medical
A20: Satuday | B20: 0.54166667 | C20: Glendeep | D20: Other | E20: Monitoring | F20: Low | G20: CR: Opportunity for magic: They've been giving out SHell bracelets, would be cool to work this in or ackbnowledge | H20: Opportunity!
A21: Satuday | B21: 0.54166667 | C21: Glendeep | D21: Traveler | E21: Hopefully fixed | F21: Low | G21: CR: Has a past ankle injury, fine for now but Brian is keeping a compression bandage on him in case he needs it later JL is talking to this participant Fine as of dinner SAT - scaz
A22: Satuday | B22: 0.58333333 | C22: Doloron | D22: Caster | E22: Hopefully fixed | F22: Low | G22: Caster is a little fixated on rules and doing it "right". Is putting a lot of pressure on himself that he only gets to do this once and doesn't want to screw it up. I encouraged him to take breaks, focus on being in a story, to understand that sometimes the dice go cold and sometimes dice are cocked and you need to just decide what makes a good story and go with it. He understood this intellectually but let's see if he can embody it. Companion says things are resolved - Scaz, dinner Sat
A23: Satuday | B23: 0.625 | C23: Clairia | D23: Other | E23: Hopefully fixed | F23: Low | G23: Clairia is splitting up. Some are napping. One is going to rest their knee at the tavern. Rest are going. Someone needs to do the 4pm "Sky turns black" at the tavern. Rob (4pm) - Julie talked to the people and they said their health is fine. I think they are a little checked out but they may just be quiet. I told them the sky turned black.
A24: Satuday | B24: 0.70833333 | C24: Uri-Kesh | D24: Other | E24: Fixing | F24: Low | G24: Party disregarded Poppy's admonishment to stay out of the Court of Mirrors. She repeatedly told them not to enter, increasing severity. They ultimately entered and shut the door behind them without really acknowledging her. Should Poppy address them directly at dinner that this was disrespectful/otherwise?- laura's thought is that they are disregarding 'side characters as people'... not personally as an staff person but in the adventure. Abigail & Jodi Companion thinks that they were trying to disregard the gold-faced characters because of all the changes. Haven't seen this problem anywhere else. Suggests that we send Poppy to them at dinner to add on some guilt. -scaz
A25: Satuday | B25: 0.77083333 | C25: Sythwan | D25: Other | E25: Hopefully fixed | F25: Low | G25: Sythwan would like an early soulspeaking if possible | H25: Opportunity!
A26: Satuday | B26: 0.77083333 | C26: Clairia | D26: Other | E26: Hopefully fixed | F26: Low | G26: Might have dropped a book. Might have dropped a rope
A27: Satuday | B27: 0.77083333 | C27: Elsewhich | D27: Other | E27: Hopefully fixed | F27: Low | G27: Might have dropped a rope. Kristi - they don't need it again (Sun 7am)
A28: Satuday | B28: 0.85416667 | C28: Doloron | D28: Traveler | E28: Monitoring | F28: Low | G28: Kristi - is there really not an entry on the Doloron traveler yet? Weird. Anyway, he's noping out of the Saturday night activities, including being driven to the crypt. "I've pushed myself way too hard." Yeah, no shit, dude. But he's sitting in the tavern and seems okay with that. Keeping an eye on but hopefully okay. (8:40pm)
A29: Sunday | B29: 0.375 | C29: Glendeep | D29: Seeker | E29: Hopefully fixed | F29: Low | G29: CR: Note for future: Seeker was disappointed by the Wolven battle, felt like a meat shield and not a hero | H29: Opportunity!

Sheet StaffCamp
A1: Opened - Day | B1: Opened - Time | C1: Staff | D1: Status | E1: Priority | F1: Situation | G1: Type
A2: Satuday | B2: 0.66666667 | C2: Peggy O'Connell | D2: Hopefully fixed | E2: Low | F2: Peggy is at the Air-BNB icing her knee. Will be back for 8pm duty. -scaz | J2: Bill Sabram
A3: Satuday | B3: 0.35416667 | C3: Chris Reichert | D3: Hopefully fixed | E3: Low | F3: CR: Note to future, do wqe need to put towels on the participant packing list? | G3: Opportunity! | J3: Anna Kelly
A4: Satuday | B4: 0.33333333 | C4: Chris Reichert | D4: Hopefully fixed | E4: Low | F4: Chris: Obtain more toilet paper from camp, need to talk to Heather, texted her at 8:10am Says she will be here before lunch time CR: Toilet paper surplus place in the single use bathroom, more industrial paper towel rolls are in the downstairs supply closet | J4: Alison Morris
A5: Satuday | B5: 0.39583333 | C5: camp | D5: Hopefully fixed | E5: Low | F5: Kristi: Chelsea reports (via Rowan) that the Hillcrest bathroom has a leaky toilet (which we think is just how it is) and a jammed paper towel dispenser and is low on toilet paper. Sending GregRo up to hopefully address at least 2 of these (9:45am) CR: 11:07, Out of Order signs placed on the toilets, more TP is available in the EM bathroom | J5: Ariel Jaffee
A6: Set Up | B6: 0.54166667 | C6: Kelsey Schultz | D6: Monitoring | E6: Low | F6: Kelsey has had a lot going on this year and feels a bit fragile/unfocused. Might need extra attention and/or care. -RD | J6: Aaron Size
A7: Set Up | B7: 0.75 | C7: Diana Galanakis | D7: Monitoring | E7: Low | F7: Reminder that Diana is pregnant and this is not public knowledge but she might get tired, etc. etc.. - RD | J7: Abigail Vargus
A8: Set Up | B8: 0.375 | C8: Kayla Schlenz | D8: Monitoring | E8: Low | F8: Kayla hurt her knee this week so might have limited mobility - RD | J8: Alex Sheehan
A9: Satuday | B9: 0.35416667 | C9: Michelle Nathan | D9: Monitoring | E9: Low | F9: Michelle is physically and mentally at low ebb. She will eat breakfast downstairs, get a ride to the Valerius house, and would like someone else to take her madlibs ander duty so that she can be Iolanthe.-AMV Chris (9:27): Tenille is taking over the Madlib Ander | J9: Ana Quintana
A10: Satuday | B10: 0.5 | C10: Jim Vincent | D10: Fixing | E10: High | F10: CR: Jim injured his ankle on a porch trip. Gave ice pack and Tylenol, needs medical follow up. CR: Dana treated at 12:30pm, confirmed ice and elevation, needs follow up in a few hours CR (2:30): Flag for Julie L to examine | J10: Ben Warren
A11: Satuday | B11: 0.75 | C11: Katherine Greene | D11: Fixing | E11: High | F11: Katherine was approached by a staff in an ander mask to address her conversation about combat in last year's event. She is very upset. Scaz is talking to her.-AMV Much of this seems to revolve around conversation with Tricia. Katherine's still very upset, but is moving forward with her role for the alt timeline. We will likely need to have a sit-down with Katherine and Tricia later. -scaz J: Tricia saw Katherine and Scaz talking and has been eyeing the table after getting back from her monster shift, but not engaging with us. Scaz and Ab briefed Reichert and he is going to talk to Tricia to say that we are aware that something went on and we can talk through it later and hear her side (after tonights festivities). 7:40 | J11: Bob Coury
A12: Satuday | B12: 0.66666667 | C12: Peggy O'Connell | D12: Hopefully fixed | E12: Low | F12: peg went back to hotel to ice her knee. She will be back for evening activies J: she is back | J12: Blake Geno
A13: Satuday | B13: 0.79166667 | C13: Nils Klinkenberg | D13: Monitoring | E13: Low | F13: A cane broke in ghost theater. Is it also his? Check. - Rob Kristi - the broken cane that's on the EM desk is Edwin Davies' and Otherworld's. The sunday vision references the cane but I think we can fix it enough if Nils needs to clue hammer the party tomorrow (8:30) | J13: Bob Marriott
J14: Bri Taborn
J15: Brian Neff
J16: Brian Scassellati
J17: Britt Rothauser
J18: Cecilia Lindgren
J19: Charlotte Wilson
J20: Chelsea Hadlock
J21: Chris Reichert
J22: Christine Huebbe
J23: Christine Reeves
J24: Cliff Young
J25: Cris Shuldiner
... J114: Zak Terry
D129: Hopefully fixed | F129: asdfadsf
A134: Satuday | B134: 0.58333333 | C134: Jeff Yaus | D134: Hopefully fixed | E134: Low | F134: Jeff was serving lunch to Carmina/Michelle, who was in character in front of many participants. He responded to her imperious nature by whispering to her that she should "tone it down at lunch." Michelle (already struggling with being mean) found this hurtful although she said venting about it was enough. I find it boundary-crossing-AMV ... 4pm: talked to Jeff, he believed he was asking for space to serve participants, will clarify w Michelle, apologized and thanked me.-AMV | J134: Betsy Rosenblatt

Sheet Dashboard
B1: Saturday | F1: Sunday
B2: Breakfast | C2: Vision? | D2: Lunch | E2: Dinner | F2: Breakfast | G2: Vision? | H2: Party Path | I2: Cup of Insight? | J2: Got Riddle? | K2: Combats | L2: Open Issues | M2: Got Riddle Item?
A3: Arden | B3: TRUE | C3: TRUE | D3: TRUE | E3: TRUE | F3: TRUE | G3: TRUE | H3: ='All Party Summary'!B2 -> 8/8 | I3: ='All Party Summary'!C2 -> Yes! | J3: ='All Party Summary'!D2 -> Yes! | K3: ='All Party Summary'!F2 -> 9 | L3: =COUNTIFS('Participants-Parties'!$C:$C, A3,'Participants-Parties'!$E:$E, "<>Hopefully Fixed") -> 0 | M3: TRUE | P3: Saturday Breakfast Questions - Vibe check and vision confirmation
A4: Clairia | B4: TRUE | C4: TRUE | D4: TRUE | E4: TRUE | F4: TRUE | G4: TRUE | H4: ='All Party Summary'!B3 -> 8/8 | I4: ='All Party Summary'!C3 -> Yes! | J4: ='All Party Summary'!D3 -> Yes! | K4: ='All Party Summary'!F3 -> 5 | L4: =COUNTIFS('Participants-Parties'!$C:$C, A4,'Participants-Parties'!$E:$E, "<>Hopefully Fixed") -> 1 | M4: FALSE | O4: 1 | P4: How are you doing?
A5: Doloron | B5: TRUE | C5: TRUE | D5: TRUE | E5: TRUE | F5: TRUE | G5: TRUE | H5: ='All Party Summary'!B4 -> 7/8 | I5: ='All Party Summary'!C4 -> Yes! | J5: ='All Party Summary'!D4 -> Yes! | K5: ='All Party Summary'!F4 -> 7 | L5: =COUNTIFS('Participants-Parties'!$C:$C, A5,'Participants-Parties'!$E:$E, "<>Hopefully Fixed") -> 1 | M5: FALSE | O5: 2 | P5: How did everybody sleep?
A6: Elsewhich | B6: TRUE | C6: TRUE | D6: TRUE | E6: TRUE | F6: TRUE | G6: TRUE | H6: ='All Party Summary'!B5 -> 8/8 | I6: ='All Party Summary'!C5 -> Yes! | J6: ='All Party Summary'!D5 -> Yes! | K6: ='All Party Summary'!F5 -> 7 | L6: =COUNTIFS('Participants-Parties'!$C:$C, A6,'Participants-Parties'!$E:$E, "<>Hopefully Fixed") -> 0 | M6: TRUE | O6: 3 | P6: How’s everybody feeling this morning?
A7: Glendeep | B7: TRUE | C7: TRUE | D7: TRUE | E7: TRUE | F7: TRUE | G7: TRUE | H7: ='All Party Summary'!B6 -> 7/8 | I7: ='All Party Summary'!C6 -> Yes! | J7: ='All Party Summary'!D6 -> Yes! | K7: ='All Party Summary'!F6 -> 8 | L7: =COUNTIFS('Participants-Parties'!$C:$C, A7,'Participants-Parties'!$E:$E, "<>Hopefully Fixed") -> 1 | M7: TRUE | O7: 4 | P7: Was the Keeper given their vision? Did they share it? Did anyone have thoughts about it?
A8: Keer | B8: TRUE | C8: TRUE | D8: TRUE | E8: TRUE | F8: TRUE | G8: TRUE | H8: ='All Party Summary'!B7 -> 8/8 | I8: ='All Party Summary'!C7 -> Yes! | J8: ='All Party Summary'!D7 -> Yes! | K8: ='All Party Summary'!F7 -> 9 | L8: =COUNTIFS('Participants-Parties'!$C:$C, A8,'Participants-Parties'!$E:$E, "<>Hopefully Fixed") -> 0 | M8: TRUE | O8: 5 | P8: Do they remember they have the list of things to find today?
A9: Noctara | B9: TRUE | C9: TRUE | D9: TRUE | E9: TRUE | F9: TRUE | G9: TRUE | H9: ='All Party Summary'!B8 -> 8/8 | I9: ='All Party Summary'!C8 -> Yes! | J9: ='All Party Summary'!D8 -> Yes! | K9: ='All Party Summary'!F8 -> 8 | L9: =COUNTIFS('Participants-Parties'!$C:$C, A9,'Participants-Parties'!$E:$E, "<>Hopefully Fixed") -> 0 | M9: TRUE | O9: 6 | P9: Are there any challenges among people in the group?
A10: P'loa | B10: TRUE | C10: TRUE | D10: TRUE | E10: TRUE | F10: TRUE | G10: TRUE | H10: ='All Party Summary'!B9 -> 8/8 | I10: ='All Party Summary'!C9 -> Yes! | J10: ='All Party Summary'!D9 -> Yes! | K10: ='All Party Summary'!F9 -> 8 | L10: =COUNTIFS('Participants-Parties'!$C:$C, A10,'Participants-Parties'!$E:$E, "<>Hopefully Fixed") -> 0 | M10: TRUE | O10: 7 | P10: Anyone we should be keeping an eye on?
A11: Sythwan | B11: TRUE | C11: TRUE | D11: TRUE | E11: TRUE | F11: TRUE | G11: TRUE | H11: ='All Party Summary'!B10 -> 8/8 | I11: ='All Party Summary'!C10 -> Yes! | J11: ='All Party Summary'!D10 -> Yes! | K11: ='All Party Summary'!F10 -> 10 | L11: =COUNTIFS('Participants-Parties'!$C:$C, A11,'Participants-Parties'!$E:$E, "<>Hopefully Fixed") -> 0 | M11: TRUE | O11: 8 | P11: If party has open issues [COLUMN L], check on them. Update status [Participants tab] if warranted
A12: Uri-Kesh | B12: TRUE | C12: TRUE | D12: TRUE | E12: TRUE | F12: TRUE | G12: TRUE | H12: ='All Party Summary'!B11 -> 8/8 | I12: ='All Party Summary'!C11 -> Yes! | J12: ='All Party Summary'!D11 -> Yes! | K12: ='All Party Summary'!F11 -> 5 | L12: =COUNTIFS('Participants-Parties'!$C:$C, A12,'Participants-Parties'!$E:$E, "<>Hopefully Fixed") -> 1 | M12: TRUE | O12: 9 | P12: Anything else we should know?
A13: Waylon | B13: TRUE | C13: TRUE | D13: TRUE | E13: TRUE | F13: TRUE | G13: TRUE | H13: ='All Party Summary'!B12 -> 8/8 | I13: ='All Party Summary'!C12 -> Yes! | J13: ='All Party Summary'!D12 -> Yes! | K13: ='All Party Summary'!F12 -> 14 | L13: =COUNTIFS('Participants-Parties'!$C:$C, A13,'Participants-Parties'!$E:$E, "<>Hopefully Fixed") -> 0 | M13: FALSE
P14: Saturday Lunch Questions - How's their adventure beginning? Any warning signs?
O15: 1 | P15: It looks like they have/haven't done Cup of Insight yet. [COLUMN I] Is that right?
O16: 2 | P16: It looks like they have/haven't gotten their riddle yet. [COLUMN J] Is that right?
O17: 3 | P17: Have they found their riddle item? [IF SO, CHECK COLUMN M]
O18: 4 | P18: How are they feeling about combat?
O19: 5 | P19: If party has open issues [COLUMN L], check on them. Update status [Participants tab] if warranted
O20: 6 | P20: How is everybody feeling?
O21: 7 | P21: How are people getting along?
O22: 8 | P22: Have they encountered challenges impacting their spirits?
O23: 9 | P23: Does anyone need a personal check in with an EM?
O24: 10 | P24: What can we do to make their experience magical/wonderful?
P26: Saturday Dinner Questions - Roadblocks to finishing? For Saturday night activities?
O27: 1 | P27: Have they found their riddle item? [IF SO, CHECK COLUMN M]
O28: 2 | P28: It looks like they have some/most/all of their party path items. [COLUMN H]. Is that right?
O29: 3 | P29: If party has open issues [COLUMN L], check on them. Update status [Participants tab] if warranted
O30: 4 | P30: Does anyone need a special accommodation for the Saturday night activities? [If so, tell Conductor]
P32: Sunday Breakfast Questions - Clue hammers and the final push
O33: 1 | P33: How are you doing?
O34: 2 | P34: How did everybody sleep?
O35: 3 | P35: How’s everybody feeling this morning?
O36: 4 | P36: Was the Keeper given their vision? Did they share it? Did anyone have thoughts about it?
O37: 5 | P37: It looks like they do/don't have all party path items. [COLUMN H] If they don't, make a plan
O38: 6 | P38: Do they remember when their penultimate meeting is? If not, remind them.
O39: 7 | P39: What if anything are they thinking about their charge?
O40: 8 | P40: Give them the Forcefield Wolven invitation. They can give to party at their discretion.
O41: 9 | P41: Is there anything we can do at the last minute to complete their adventure?

Sheet Combat Log
B3: Chitter 1 | C3: Chitter 2 | D3: Chitter 3 | E3: Skeever 4 | F3: Skeever 5 | G3: Skeever 6 | H3: Skeever 7 | I3: Skeever 8 | J3: Skeever 9 | K3: Skeever 10 | L3: Skeever 11 | M3: Worlog 1 | N3: Worlog 2
A4: Arden
A5: Clairia
A6: Doloron
A7: Elsewhich
A8: Glendeep
A9: Keer
A10: Noctara
A11: P'loa
A12: Sythwan
A13: Uri-Kesh
A14: Waylon
B16: Wolven 1 | C16: Wolven 2 | D16: Wolven 3 | E16: Wolven 4 | F16: Wolven 5 | G16: Wolven 6 | H16: Wolven 7 | I16: Wolven 8 | J16: Wolven 9 | K16: Wolven 10 | L16: Wolven 11 | M16: Wolven 12 | N16: Bachelorette 1 | O16: Bachelorette 2 | Q16: TOTALS
A17: Arden | Q17: Arden | R17: =counta(B4:N4)+counta(B17:O17) -> 0
A18: Clairia | Q18: Clairia | R18: =counta(B5:N5)+counta(B18:O18) -> 0
A19: Doloron | Q19: Doloron | R19: =counta(B6:N6)+counta(B19:O19) -> 0
A20: Elsewhich | Q20: Elsewhich | R20: =counta(B7:N7)+counta(B20:O20) -> 0
A21: Glendeep | Q21: Glendeep | R21: =counta(B8:N8)+counta(B21:O21) -> 0
A22: Keer | Q22: Keer | R22: =counta(B9:N9)+counta(B22:O22) -> 0
A23: Noctara | Q23: Noctara | R23: =counta(B10:N10)+counta(B23:O23) -> 0
A24: P'loa | Q24: P'loa | R24: =counta(B11:N11)+counta(B24:O24) -> 0
A25: Sythwan | Q25: Sythwan | R25: =counta(B12:N12)+counta(B25:O25) -> 0
A26: Uri-Kesh | Q26: Uri-Kesh | R26: =counta(B13:N13)+counta(B26:O26) -> 0
A27: Waylon | Q27: Waylon | R27: =counta(B14:N14)+counta(B27:O27) -> 0

Sheet All Party Summary
B1: Party Path Items | C1: Cup of Insight? | D1: Received Riddle? | E1: Found Riddle Item? | F1: Combats
A2: Arden | B2: =concatenate((countif('Arden_Party Sheet'!A13:A20,"Yes!")),"/8") -> 8/8 | C2: =If('Arden_Party Sheet'!$A$13="Yes!","Yes!","No") -> Yes! | D2: =If('Arden_Party Sheet'!$A$19="Yes!","Yes!","No") -> Yes! | E2: =If(Dashboard!$M3=TRUE,"Yes!","No") -> Yes! | F2: =Combat_Import!V4 -> 9
A3: Clairia | B3: =concatenate((countif('Clairia_Party Sheet'!A13:A20,"Yes!")),"/8") -> 8/8 | C3: =If('Clairia_Party Sheet'!$A$14="Yes!","Yes!","No") -> Yes! | D3: =If('Clairia_Party Sheet'!$A$19="Yes!","Yes!","No") -> Yes! | E3: =If(Dashboard!$M4=TRUE,"Yes!","No") -> No | F3: =Combat_Import!V5 -> 5
A4: Dolorón | B4: =concatenate((countif('Doloron_Party Sheet'!A13:A20,"Yes!")),"/8") -> 7/8 | C4: =If('Doloron_Party Sheet'!$A$16="Yes!","Yes!","No") -> Yes! | D4: =If('Doloron_Party Sheet'!$A$14="Yes!","Yes!","No") -> Yes! | E4: =If(Dashboard!$M5=TRUE,"Yes!","No") -> No | F4: =Combat_Import!V6 -> 7
A5: Elsewhich | B5: =concatenate((countif('Elsewhich_Party Sheet'!A13:A20,"Yes!")),"/8") -> 8/8 | C5: =If('Elsewhich_Party Sheet'!$A$12="Yes!","Yes!","No") -> Yes! | D5: =If('Elsewhich_Party Sheet'!$A$19="Yes!","Yes!","No") -> Yes! | E5: =If(Dashboard!$M6=TRUE,"Yes!","No") -> Yes! | F5: =Combat_Import!V7 -> 7
A6: Glendeep | B6: =concatenate((countif('Glendeep_Party Sheet'!A$13:A$20,"Yes!")),"/8") -> 7/8 | C6: =If('Glendeep_Party Sheet'!$A$12="Yes!","Yes!","No") -> Yes! | D6: =If('Glendeep_Party Sheet'!$A$19="Yes!","Yes!","No") -> Yes! | E6: =If(Dashboard!$M7=TRUE,"Yes!","No") -> Yes! | F6: =Combat_Import!V8 -> 8
A7: Keer | B7: =concatenate((countif('Keer_Party Sheet'!A$13:A$20,"Yes!")),"/8") -> 8/8 | C7: =If('Keer_Party Sheet'!$A$16="Yes!","Yes!","No") -> Yes! | D7: =If('Keer_Party Sheet'!$A$20="Yes!","Yes!","No") -> Yes! | E7: =If(Dashboard!$M8=TRUE,"Yes!","No") -> Yes! | F7: =Combat_Import!V9 -> 9
A8: Noctara | B8: =concatenate((countif('Noctara_Party Sheet'!A$13:A$20,"Yes!")),"/8") -> 8/8 | C8: =If('Noctara_Party Sheet'!$A$15="Yes!","Yes!","No") -> Yes! | D8: =If('Noctara_Party Sheet'!$A$15="Yes!","Yes!","No") -> Yes! | E8: =If(Dashboard!$M9=TRUE,"Yes!","No") -> Yes! | F8: =Combat_Import!V10 -> 8
A9: P'loa | B9: =concatenate((countif('Ploa_Party Sheet'!A$13:A$20,"Yes!")),"/8") -> 8/8 | C9: =If('Ploa_Party Sheet'!$A$16="Yes!","Yes!","No") -> Yes! | D9: =If('Ploa_Party Sheet'!$A$20="Yes!","Yes!","No") -> Yes! | E9: =If(Dashboard!$M10=TRUE,"Yes!","No") -> Yes! | F9: =Combat_Import!V11 -> 8
A10: Sythwan | B10: =concatenate((countif('Sythwan_Party Sheet'!A$13:A$20,"Yes!")),"/8") -> 8/8 | C10: =If('Sythwan_Party Sheet'!$A$16="Yes!","Yes!","No") -> Yes! | D10: =If('Sythwan_Party Sheet'!$A$18="Yes!","Yes!","No") -> Yes! | E10: =If(Dashboard!$M11=TRUE,"Yes!","No") -> Yes! | F10: =Combat_Import!V12 -> 10
A11: Uri-Kesh | B11: =concatenate((countif('UriKesh_Party Sheet'!A$13:A$20,"Yes!")),"/8") -> 8/8 | C11: =If('UriKesh_Party Sheet'!$A$16="Yes!","Yes!","No") -> Yes! | D11: =If('UriKesh_Party Sheet'!$A$14="Yes!","Yes!","No") -> Yes! | E11: =If(Dashboard!$M12=TRUE,"Yes!","No") -> Yes! | F11: =Combat_Import!V13 -> 5
A12: Waylon | B12: =concatenate((countif('Waylon_Party Sheet'!A$13:A$20,"Yes!")),"/8") -> 8/8 | C12: =If('Waylon_Party Sheet'!$A$16="Yes!","Yes!","No") -> Yes! | D12: =If('Waylon_Party Sheet'!$A$16="Yes!","Yes!","No") -> Yes! | E12: =If(Dashboard!$M13=TRUE,"Yes!","No") -> No | F12: =Combat_Import!V14 -> 14
F13: =Combat_Import!O15

Sheet Arden_Party Sheet
A1: ARDEN
A2: Investigating the charge against: Bracken
A3: Companion: Ari (Susan Gerow)
A4: Keeper’s Saturday morning dream: The vision shows the citrine shards and leads the party to Valentina.
A5: Riddle: "laughing girl" fire riddle, fire circle in Winterhill Clearing
A6: Keeper’s Sunday morning dream: This vision shows the Order of the Black Lantern and suggests that it is a club of a different sort than the party (and Bracken) might have originally thought.
A8: Complete? | B8: Staff | C8: Time | D8: Items to give | F8: Complete? | G8: Staff | H8: Info to Give | I8: Bloc Requirements
A9: =if(Arden_Import!B5=true,"Yes!","No") -> Yes! | B9: Aria Morgan | C9: Contact | D9: -- | F9: =if(Arden_Import!B24=true,"Yes!","No") -> Yes! | G9: Angelica Sprink | H9: assigns charge | I9: Need | J9: =COUNTif(F9,"Yes!") -> 1
A10: =if(Arden_Import!B6=true,"Yes!","No") -> Yes! | B10: Ursula Smirch | C10: 2nd Friday | D10: -- | F10: =if(Arden_Import!B25=true,"Yes!","No") -> Yes! | G10: Geneva Sprink | H10: Bracken has been telling Angelica about monsters and that she might get attacked, and suggesting she make a plan to defend herself. (life skills: defense) | I10: Need 5 | J10: =COUNTif(F10:F17,"Yes!") -> 6
A11: =if(Arden_Import!B7=true,"Yes!","No") -> No | B11: Nix Valerius | C11: 3rd Friday | D11: -- | F11: =if(Arden_Import!B26=true,"Yes!","No") -> Yes! | G11: Bartleby Sprink | H11: Bracken has been telling Angelica about how food is made, or how to wash dishes. (life skills: food prep)
A12: =if(Arden_Import!B8=true,"Yes!","No") -> Yes! | B12: Isaiah Cooke | C12: 4th Friday | D12: list of items | F12: =if(Arden_Import!B27=true,"Yes!","No") -> No | G12: Lenora Graves | H12: Bracken has been telling Angelica about monsters and that she might get attacked. (life skills: defense)
A13: =if(Arden_Import!B9=true,"Yes!","No") -> Yes! | B13: Kiko Truthspeaker | C13: 1st Saturday | D13: locus root | F13: =if(Arden_Import!B28=true,"Yes!","No") -> No | G13: Kyson Wayseeker | H13: Angelica never learned basic survival skills, but “a friend” is now teaching her.
A14: =if(Arden_Import!B10=true,"Yes!","No") -> Yes! | B14: Buzzkill | C14: 11am-6pm | D14: none until tomorrow | F14: =if(Arden_Import!B29=true,"Yes!","No") -> Yes! | G14: Samuelson | H14: Angelica has been more independent recently, such as finding out how much her meal costs. (life skills: paying for meals)
A15: =if(Arden_Import!B11=true,"Yes!","No") -> Yes! | B15: Pascal Valerius | C15: 8am-1pm | D15: star of direction | F15: =if(Arden_Import!B30=true,"Yes!","No") -> Yes! | G15: Pansy Golden | H15: Angelica used to be helpless, but recently she seems more self-sufficient (life skills: helping clean).
A16: =if(Arden_Import!B12=true,"Yes!","No") -> Yes! | B16: Karmin Smirch | C16: 9-11am, 1-4pm, 6-8pm | D16: riverglass jewelbox | F16: =if(Arden_Import!B31=true,"Yes!","No") -> Yes! | G16: Kulinos | H16: Angelica used to be helpless, but recently she seems more knowledgeable (life skills: rhubarb leaves are toxic).
A17: =if(Arden_Import!B13=true,"Yes!","No") -> Yes! | B17: Valentina | C17: 10am-4pm | D17: citrine shards | F17: =if(Arden_Import!B32=true,"Yes!","No") -> Yes! | G17: Aleeya Witchborn | H17: Angelica used to be helpless with directions, but Bracken has been teaching her (life skills: understanding directions).
A18: =if(Arden_Import!B14=true,"Yes!","No") -> Yes! | B18: Charlie Peacock | C18: 1-6pm | D18: cowry shell | F18: =if(Arden_Import!B33=true,"Yes!","No") -> Yes! | G18: Karla Smirch | H18: Bracken has given away his belongings to those poorer than himself. | I18: Need | J18: =COUNTif(F18,"Yes!") -> 1
A19: =if(Arden_Import!B15=true,"Yes!","No") -> Yes! | B19: Moxie | C19: 10am-5pm | D19: riddle to argentum heart | F19: =if(Arden_Import!B34=true,"Yes!","No") -> No | G19: Dusty Peacock | H19: Bracken has been hanging around Angelica. But he seems nice and hard to believe he’s harassing her.
A20: =if(Arden_Import!B16=true,"Yes!","No") -> Yes! | B20: Obsidian | C20: 8am-12noon, 2-4pm | D20: spiritstone | F20: =if(Arden_Import!B35=true,"Yes!","No") -> Yes! | G20: Phineas Smirch | H20: Bracken is a thug and a menace. Born bad. | I20: Need 2 | J20: =COUNTif(F20:F22,"Yes!") -> 2
A21: =if(Arden_Import!B17=true,"Yes!","No") -> Yes! | B21: Ghost Theater | C21: 4-8pm | D21: limelight | F21: =if(Arden_Import!B36=true,"Yes!","No") -> No | G21: Equinoxious | H21: Bracken had a rough childhood. He’s learned many survival skills, including questionable ones like lock-picking. May be trouble.
A22: =if(Arden_Import!B18=true,"Yes!","No") -> No | B22: Buzzkill | C22: 9:45am Sunday | D22: chaos pendant | F22: =if(Arden_Import!B37=true,"Yes!","No") -> Yes! | G22: Isaiah Cooke | H22: Bracken had a rough childhood. He’s been seen walking near the wildlands. May be trouble.
A23: =if(Arden_Import!B19=true,"Yes!","No") -> No | B23: Morgoth & Henchmen | C23: 10am Sunday | D23: Sconce of the Wood | F23: =if(Arden_Import!B38=true,"Yes!","No") -> Yes! | G23: Crabtree | H23: Crown of St. Mora, which was stolen several years ago, was anonymously left at the Valerius house a couple weeks ago. | I23: Need 1 | J23: =COUNTif(F23:F24,"Yes!") -> 2
A24: =If(Dashboard!$M3=TRUE,"Yes!","No") -> Yes! | B24: riddle item found? | C24: -- | D24: -- | F24: =if(Arden_Import!B39=true,"Yes!","No") -> Yes! | G24: Aesthetika | H24: Crown of St. Mora, which was stolen several years ago, was anonymously left at the Valerius house a couple weeks ago.
F25: =if(Arden_Import!B40=true,"Yes!","No") -> Yes! | G25: Santiago Valerius | H25: Bracken is the person who left the Crown of St. Mora at the Valerius house. But why did he have it? | I25: Need | J25: =COUNTif(F25,"Yes!") -> 1
A26: COMMENTS | F26: =if(Arden_Import!B41=true,"Yes!","No") -> Yes! | G26: Dimitri | H26: Rumor that Smirches had the Crown of St. Mora, although no idea why they had it or would return it. | I26: Need 1 | J26: =COUNTif(F26:F27,"Yes!") -> 1
A27: =IFERROR(__xludf.DUMMYFUNCTION("IFERROR( FILTER( FLATTEN({Arden_Import!C5:C20; Arden_Import!C24:C52; Arden_Import!A55:A79}), FLATTEN({Arden_Import!C5:C20; Arden_Import!C24:C52; Arden_Import!A55:A79}) <> """" ), """" )"),"Spoke with Birdie, Starling, & Willow- discussed Memory Lapse from last night, theater burning, and Golden Page/Nemaiah. Party was ""hesitant to trust others"" but they opened up after some conversation. Introduced to Ursula. DG") -> Spoke with Birdie, Starling, & Willow- discussed Memory Lapse from last night, theater burning, and Golden Page/Nemaiah. Party was "hesitant to trust others" but they opened up after some conversation. Introduced to Ursula. DG | F27: =if(Arden_Import!B42=true,"Yes!","No") -> No | G27: Fenwick Michaels | H27: Rumor that a merchant family in WE had the Crown of St. Mora. No idea how/why it was returned.
A28: =IFERROR(__xludf.DUMMYFUNCTION("""COMPUTED_VALUE"""),"Gave them the list Friday night (sorry, put in the wrong cell)") -> Gave them the list Friday night (sorry, put in the wrong cell) | F28: =if(Arden_Import!B43=true,"Yes!","No") -> Yes! | G28: Bracken | H28: Barring truth magic, he’s not sure what the party is talking about and/or Left the Crown
A29: =IFERROR(__xludf.DUMMYFUNCTION("""COMPUTED_VALUE"""),"Traveler had not shared the list with the group, got her to share lore, and some of the list, but fewer people heard that. 10:30.") -> Traveler had not shared the list with the group, got her to share lore, and some of the list, but fewer people heard that. 10:30. | F29: =if(Arden_Import!B44=true,"Yes!","No") -> Yes! | G29: Pearl Bryce | H29: Bracken asked if dragons were real. They’re not. | I29: Need 1 | J29: =COUNTif(F29:F30,"Yes!") -> 2
A30: =IFERROR(__xludf.DUMMYFUNCTION("""COMPUTED_VALUE"""),"Did challenge with them, will give on Sunday at the coordinator's leisure (AS)") -> Did challenge with them, will give on Sunday at the coordinator's leisure (AS) | F30: =if(Arden_Import!B45=true,"Yes!","No") -> Yes! | G30: Kora Peacekeeper | H30: Bracken asked if dragons were real. They’re not.
A31: =IFERROR(__xludf.DUMMYFUNCTION("""COMPUTED_VALUE"""),"Finished the jingle challenge with them at 4pm on Saturday. I'm sure nothing horrible happened right as I walked away. -DaveKamin") -> Finished the jingle challenge with them at 4pm on Saturday. I'm sure nothing horrible happened right as I walked away. -DaveKamin | F31: =if(Arden_Import!B46=true,"Yes!","No") -> Yes! | G31: Tinker Bill | H31: Tinker Bill found “Ever Vigilant * Ever Fabulous” coasters propping up a table; Solomon & Bonnie said they’re not theirs. The party should keep some! | I31: Need | J31: =COUNTif(F31,"Yes!") -> 1
A32: =IFERROR(__xludf.DUMMYFUNCTION("""COMPUTED_VALUE"""),"Switched to pitch pipe challenge and did it in front of tavern after their ghost theater in Charlie's absence. -JF") -> Switched to pitch pipe challenge and did it in front of tavern after their ghost theater in Charlie's absence. -JF | F32: =if(Arden_Import!B47=true,"Yes!","No") -> Yes! | G32: Kyli Talespinner | H32: Bracken dropped a piece of black paper. She’s hoping the party can help figure it out. The paper lists quests, with the final one partially ripped away. | I32: Need | J32: =COUNTif(F32,"Yes!") -> 1
A33: =IFERROR(__xludf.DUMMYFUNCTION("""COMPUTED_VALUE"""),"Found them at 6pm. Petulantly threw the stupid riddle at them. -LN") -> Found them at 6pm. Petulantly threw the stupid riddle at them. -LN | F33: =if(Dashboard!G3=true,"Yes!","No") -> Yes! | G33: Keeper’s Sunday Vision | H33: Shows the Order of the Black Lantern and suggests that it is a club of a different sort than the party (and Bracken) might have originally thought. | I33: Need | J33: =COUNTif(F33,"Yes!") -> 1
A34: =IFERROR(__xludf.DUMMYFUNCTION("""COMPUTED_VALUE"""),"Did a bit of a ""who cares speedrun"" but had a good experience. -Dave Nadig") -> Did a bit of a "who cares speedrun" but had a good experience. -Dave Nadig | F34: =if(Arden_Import!B49=true,"Yes!","No") -> No | G34: Angelica Sprink | H34: Angelica was attacked by wolven, but Bracken’s training let her fend them off. | I34: Need | J34: =COUNTif(F34,"Yes!") -> 0
A35: =IFERROR(__xludf.DUMMYFUNCTION("""COMPUTED_VALUE"""),"Met them in preperation to assign charge LD, assigned charge with a side of tears and teenage angst.") -> Met them in preperation to assign charge LD, assigned charge with a side of tears and teenage angst. | F35: =if(Arden_Import!B50=true,"Yes!","No") -> No | G35: Bracken | H35: Bracken reveals details about the order and quests. | I35: Need | J35: =COUNTif(F35,"Yes!") -> 0
A36: =IFERROR(__xludf.DUMMYFUNCTION("""COMPUTED_VALUE"""),"Did not directly approach but sat next to them at lunch and was told they already fully understood charge from overhearing Angelica and Geneva fight and not to clue hammer any more ") -> Did not directly approach but sat next to them at lunch and was told they already fully understood charge from overhearing Angelica and Geneva fight and not to clue hammer any more | F36: =if(Arden_Import!B51=true,"Yes!","No") -> No | G36: Karmin Smirch | H36: Has a new set of clothing that is Bracken’s size. The party will help him acquire it. | I36: Need | J36: =COUNTif(F36,"Yes!") -> 0
A37: =IFERROR(__xludf.DUMMYFUNCTION("""COMPUTED_VALUE"""),"Was told they already had info they needed, not to clue hammer them") -> Was told they already had info they needed, not to clue hammer them | F37: =if(Arden_Import!B52=true,"Yes!","No") -> No | G37: Adina Valerius | H37: Bracken is attempting to join a secretive order of knights. Since one of his missions requires that he rescue a damsel in distress, Bracken has interpreted this to mean he should teach the helpless Angelica Sprink the life skills she was lacking, and this, as well as the other quests he is in the process of completing, explain his potentially questionable behavior. Although Bracken doesn’t yet know how special and unusual this particular order is, he’ll ultimately be deemed worthy of entry into this secretive and fabulous Knight Club. | I37: Need | J37: =COUNTif(F37,"Yes!") -> 0
A38: =IFERROR(__xludf.DUMMYFUNCTION("""COMPUTED_VALUE"""),"Talked to woman in light green shirt. Two others listened.") -> Talked to woman in light green shirt. Two others listened.
A39: =IFERROR(__xludf.DUMMYFUNCTION("""COMPUTED_VALUE"""),"Sat night during apple crisp. They asked about a Black Lamp secret society, I said I didn't know anything about that.") -> Sat night during apple crisp. They asked about a Black Lamp secret society, I said I didn't know anything about that.
A40: =IFERROR(__xludf.DUMMYFUNCTION("""COMPUTED_VALUE"""),"Slipped the info in as a natural aside at breakfast to two participants on the periphery just after they spoke with Samuelson about Angelica, and before Bartleby came over to them. Very interested. ") -> Slipped the info in as a natural aside at breakfast to two participants on the periphery just after they spoke with Samuelson about Angelica, and before Bartleby came over to them. Very interested.
A41: =IFERROR(__xludf.DUMMYFUNCTION("""COMPUTED_VALUE"""),"3 of the party members were very focused on the info and then tried to teach Karla the magic of giving to help her better understand Bracken") -> 3 of the party members were very focused on the info and then tried to teach Karla the magic of giving to help her better understand Bracken
A42: =IFERROR(__xludf.DUMMYFUNCTION("""COMPUTED_VALUE"""),"Got asked about Bracken after ritual") -> Got asked about Bracken after ritual
A43: =IFERROR(__xludf.DUMMYFUNCTION("""COMPUTED_VALUE"""),"Gave them the location spell listing and they wrote all the ppl on it. They crushed the illiterate challenge. Invested in all parts of Otherworld already. Seemed like a great crew. Update, gave them charge info at 12:15") -> Gave them the location spell listing and they wrote all the ppl on it. They crushed the illiterate challenge. Invested in all parts of Otherworld already. Seemed like a great crew. Update, gave them charge info at 12:15
A44: =IFERROR(__xludf.DUMMYFUNCTION("""COMPUTED_VALUE"""),"Gave clue info re: St Mora crown & SWV's return to Mistal; they were interested & wrote a few things down; Saturday late morning - MO") -> Gave clue info re: St Mora crown & SWV's return to Mistal; they were interested & wrote a few things down; Saturday late morning - MO
A45: =IFERROR(__xludf.DUMMYFUNCTION("""COMPUTED_VALUE"""),"I told one woman who seemed to be listening intently. (before lunch) -TO'") -> I told one woman who seemed to be listening intently. (before lunch) -TO'
A46: =IFERROR(__xludf.DUMMYFUNCTION("""COMPUTED_VALUE"""),"Gave the charge information to the Traveler. She asked proactively after the Crown and has been tracking Bracken and Angelica") -> Gave the charge information to the Traveler. She asked proactively after the Crown and has been tracking Bracken and Angelica
A47: =IFERROR(__xludf.DUMMYFUNCTION("""COMPUTED_VALUE"""),"Seemed to know about St. Mora and be putting together with other clues. RCY. ") -> Seemed to know about St. Mora and be putting together with other clues. RCY.
A48: =IFERROR(__xludf.DUMMYFUNCTION("""COMPUTED_VALUE"""),"At least a few seem to be hard committed to helping Angelica and involved, but as far as I can tell no real knowledge of the charge or what it might mean --RS") -> At least a few seem to be hard committed to helping Angelica and involved, but as far as I can tell no real knowledge of the charge or what it might mean --RS
A49: =IFERROR(__xludf.DUMMYFUNCTION("""COMPUTED_VALUE"""),"Told 2 memebers about the dragon seemed interested right after lunch -TB") -> Told 2 memebers about the dragon seemed interested right after lunch -TB
A50: =IFERROR(__xludf.DUMMYFUNCTION("""COMPUTED_VALUE"""),"Two paying attention, no initial recognition of Brackens name, seemed to know at the end of the interaction. CL 10:30am") -> Two paying attention, no initial recognition of Brackens name, seemed to know at the end of the interaction. CL 10:30am
A51: =IFERROR(__xludf.DUMMYFUNCTION("""COMPUTED_VALUE"""),"Coasters delivered. Made sure seveal heard my little speech. They did look to try and see the printing..") -> Coasters delivered. Made sure seveal heard my little speech. They did look to try and see the printing..
A52: =IFERROR(__xludf.DUMMYFUNCTION("""COMPUTED_VALUE"""),"Gave paper in Tavern before they went to Soul Speaking. Party is very interested in helping Bracken and started trying to read the black paper under a flashlight almost right away. MG") -> Gave paper in Tavern before they went to Soul Speaking. Party is very interested in helping Bracken and started trying to read the black paper under a flashlight almost right away. MG
A53: =IFERROR(__xludf.DUMMYFUNCTION("""COMPUTED_VALUE"""),"party photo taken -Mirin") -> party photo taken -Mirin
A54: =IFERROR(__xludf.DUMMYFUNCTION("""COMPUTED_VALUE"""),"1 almost died battling skeevers, keeper used heal all hits pray") -> 1 almost died battling skeevers, keeper used heal all hits pray
A55: =IFERROR(__xludf.DUMMYFUNCTION("""COMPUTED_VALUE"""),"Told Arden about Golden Letter for Samuelson. -Mike S.") -> Told Arden about Golden Letter for Samuelson. -Mike S.
A56: =IFERROR(__xludf.DUMMYFUNCTION("""COMPUTED_VALUE"""),"They mentioned they hadn't found a chest yet and wanted to, I gave them some advice on where to find them. - ZT") -> They mentioned they hadn't found a chest yet and wanted to, I gave them some advice on where to find them. - ZT
A57: =IFERROR(__xludf.DUMMYFUNCTION("""COMPUTED_VALUE"""),"Kim told me (Ariel) that Arden found the basket of Wolven slaying (but Lance says it wont be a problem)") -> Kim told me (Ariel) that Arden found the basket of Wolven slaying (but Lance says it wont be a problem)
A58: =IFERROR(__xludf.DUMMYFUNCTION("""COMPUTED_VALUE"""),"The woman with the short blond hair is collecting leaves and other examples of the local fauna to bring back to Arden for study. She gave me (Baroness Adina) a leaf from Arden to remind me of my home. She is awesome!") -> The woman with the short blond hair is collecting leaves and other examples of the local fauna to bring back to Arden for study. She gave me (Baroness Adina) a leaf from Arden to remind me of my home. She is awesome!
A59: =IFERROR(__xludf.DUMMYFUNCTION("""COMPUTED_VALUE"""),"very good fighters, good coordination ") -> very good fighters, good coordination
A60: =IFERROR(__xludf.DUMMYFUNCTION("""COMPUTED_VALUE"""),"Maker is a really strong individual fighter; overall group combat is strong - Neal D. 1pm Sat") -> Maker is a really strong individual fighter; overall group combat is strong - Neal D. 1pm Sat
A61: =IFERROR(__xludf.DUMMYFUNCTION("""COMPUTED_VALUE"""),"Backing off trial drama, companion told Rowan who told me (Lane) that they are completly trial locked in and not to item focused. 1:44 pm") -> Backing off trial drama, companion told Rowan who told me (Lane) that they are completly trial locked in and not to item focused. 1:44 pm
A62: =IFERROR(__xludf.DUMMYFUNCTION("""COMPUTED_VALUE"""),"Have golden page info re: Obsidian-Abigail") -> Have golden page info re: Obsidian-Abigail

Sheet Combat_Import
A1: =IFERROR(__xludf.DUMMYFUNCTION("IMPORTRANGE(""https://docs.google.com/spreadsheets/d/1PPFix0KE5FV0_ekB8X93l4fBTTlhI3_4FnP7klgfg_Y/edit?gid=0#gid=0"", ""Combat!a1:z30"")"),"") | B1: =IFERROR(__xludf.DUMMYFUNCTION("""COMPUTED_VALUE"""),"Arden") -> Arden | C1: =IFERROR(__xludf.DUMMYFUNCTION("""COMPUTED_VALUE"""),"Clairia") -> Clairia | D1: =IFERROR(__xludf.DUMMYFUNCTION("""COMPUTED_VALUE"""),"Doloron") -> Doloron | E1: =IFERROR(__xludf.DUMMYFUNCTION("""COMPUTED_VALUE"""),"Elsewhich") -> Elsewhich | F1: =IFERROR(__xludf.DUMMYFUNCTION("""COMPUTED_VALUE"""),"Glendeep") -> Glendeep | G1: =IFERROR(__xludf.DUMMYFUNCTION("""COMPUTED_VALUE"""),"Keer") -> Keer | H1: =IFERROR(__xludf.DUMMYFUNCTION("""COMPUTED_VALUE"""),"Noctara") -> Noctara | I1: =IFERROR(__xludf.DUMMYFUNCTION("""COMPUTED_VALUE"""),"P'loa") -> P'loa | J1: =IFERROR(__xludf.DUMMYFUNCTION("""COMPUTED_VALUE"""),"Sythwan") -> Sythwan | K1: =IFERROR(__xludf.DUMMYFUNCTION("""COMPUTED_VALUE"""),"Uri-Kesh") -> Uri-Kesh | L1: =IFERROR(__xludf.DUMMYFUNCTION("""COMPUTED_VALUE"""),"Waylon") -> Waylon | M1: =IFERROR(__xludf.DUMMYFUNCTION("""COMPUTED_VALUE"""),"Notes") -> Notes
A2: =IFERROR(__xludf.DUMMYFUNCTION("""COMPUTED_VALUE"""),"Chitter 1") -> Chitter 1 | B2: =IFERROR(__xludf.DUMMYFUNCTION("""COMPUTED_VALUE"""),TRUE) -> TRUE | C2: =IFERROR(__xludf.DUMMYFUNCTION("""COMPUTED_VALUE"""),TRUE) -> TRUE | D2: =IFERROR(__xludf.DUMMYFUNCTION("""COMPUTED_VALUE"""),TRUE) -> TRUE | E2: =IFERROR(__xludf.DUMMYFUNCTION("""COMPUTED_VALUE"""),FALSE) -> FALSE | F2: =IFERROR(__xludf.DUMMYFUNCTION("""COMPUTED_VALUE"""),TRUE) -> TRUE | G2: =IFERROR(__xludf.DUMMYFUNCTION("""COMPUTED_VALUE"""),TRUE) -> TRUE | H2: =IFERROR(__xludf.DUMMYFUNCTION("""COMPUTED_VALUE"""),FALSE) -> FALSE | I2: =IFERROR(__xludf.DUMMYFUNCTION("""COMPUTED_VALUE"""),FALSE) -> FALSE | J2: =IFERROR(__xludf.DUMMYFUNCTION("""COMPUTED_VALUE"""),FALSE) -> FALSE | K2: =IFERROR(__xludf.DUMMYFUNCTION("""COMPUTED_VALUE"""),FALSE) -> FALSE | L2: =IFERROR(__xludf.DUMMYFUNCTION("""COMPUTED_VALUE"""),FALSE) -> FALSE | M2: =IFERROR(__xludf.DUMMYFUNCTION("""COMPUTED_VALUE"""),"Arden, Doloron, and Keer hit the chitters as a single group and got one bag between them. Elsewhich met us right after Claria and did not have pre-breakfast combat. All rangers were right on the soothing chitters function. (GR - 7AM)") -> Arden, Doloron, and Keer hit the chitters as a single group and got one bag between them. Elsewhich met us right after Claria and did not have pre-breakfast combat. All rangers were right on the soothing chitters function. (GR - 7AM)
A3: =IFERROR(__xludf.DUMMYFUNCTION("""COMPUTED_VALUE"""),"Chitter 2") -> Chitter 2 | B3: =IFERROR(__xludf.DUMMYFUNCTION("""COMPUTED_VALUE"""),FALSE) -> FALSE | C3: =IFERROR(__xludf.DUMMYFUNCTION("""COMPUTED_VALUE"""),FALSE) -> FALSE | D3: =IFERROR(__xludf.DUMMYFUNCTION("""COMPUTED_VALUE"""),FALSE) -> FALSE | E3: =IFERROR(__xludf.DUMMYFUNCTION("""COMPUTED_VALUE"""),FALSE) -> FALSE | F3: =IFERROR(__xludf.DUMMYFUNCTION("""COMPUTED_VALUE"""),FALSE) -> FALSE | G3: =IFERROR(__xludf.DUMMYFUNCTION("""COMPUTED_VALUE"""),FALSE) -> FALSE | H3: =IFERROR(__xludf.DUMMYFUNCTION("""COMPUTED_VALUE"""),FALSE) -> FALSE | I3: =IFERROR(__xludf.DUMMYFUNCTION("""COMPUTED_VALUE"""),FALSE) -> FALSE | ... L3: =IFERROR(__xludf.DUMMYFUNCTION("""COMPUTED_VALUE"""),FALSE) -> FALSE | U3: =IFERROR(__xludf.DUMMYFUNCTION("""COMPUTED_VALUE"""),"TOTALS") -> TOTALS
A4: =IFERROR(__xludf.DUMMYFUNCTION("""COMPUTED_VALUE"""),"Chitter 3") -> Chitter 3 | B4: =IFERROR(__xludf.DUMMYFUNCTION("""COMPUTED_VALUE"""),FALSE) -> FALSE | C4: =IFERROR(__xludf.DUMMYFUNCTION("""COMPUTED_VALUE"""),TRUE) -> TRUE | D4: =IFERROR(__xludf.DUMMYFUNCTION("""COMPUTED_VALUE"""),FALSE) -> FALSE | E4: =IFERROR(__xludf.DUMMYFUNCTION("""COMPUTED_VALUE"""),FALSE) -> FALSE | F4: =IFERROR(__xludf.DUMMYFUNCTION("""COMPUTED_VALUE"""),FALSE) -> FALSE | G4: =IFERROR(__xludf.DUMMYFUNCTION("""COMPUTED_VALUE"""),FALSE) -> FALSE | H4: =IFERROR(__xludf.DUMMYFUNCTION("""COMPUTED_VALUE"""),TRUE) -> TRUE | I4: =IFERROR(__xludf.DUMMYFUNCTION("""COMPUTED_VALUE"""),FALSE) -> FALSE | J4: =IFERROR(__xludf.DUMMYFUNCTION("""COMPUTED_VALUE"""),TRUE) -> TRUE | K4: =IFERROR(__xludf.DUMMYFUNCTION("""COMPUTED_VALUE"""),TRUE) -> TRUE | L4: =IFERROR(__xludf.DUMMYFUNCTION("""COMPUTED_VALUE"""),FALSE) -> FALSE | M4: =IFERROR(__xludf.DUMMYFUNCTION("""COMPUTED_VALUE"""),"Fought Sythwan twice. They used soothing once and move in shadows once. Uri-Kesh and Clairia fought chitters together.") -> Fought Sythwan twice. They used soothing once and move in shadows once. Uri-Kesh and Clairia fought chitters together. | U4: =IFERROR(__xludf.DUMMYFUNCTION("""COMPUTED_VALUE"""),"Arden") -> Arden | V4: =IFERROR(__xludf.DUMMYFUNCTION("""COMPUTED_VALUE"""),9.0) -> 9
A5: =IFERROR(__xludf.DUMMYFUNCTION("""COMPUTED_VALUE"""),"Skeever 4") -> Skeever 4 | B5: =IFERROR(__xludf.DUMMYFUNCTION("""COMPUTED_VALUE"""),FALSE) -> FALSE | C5: =IFERROR(__xludf.DUMMYFUNCTION("""COMPUTED_VALUE"""),FALSE) -> FALSE | D5: =IFERROR(__xludf.DUMMYFUNCTION("""COMPUTED_VALUE"""),FALSE) -> FALSE | E5: =IFERROR(__xludf.DUMMYFUNCTION("""COMPUTED_VALUE"""),FALSE) -> FALSE | F5: =IFERROR(__xludf.DUMMYFUNCTION("""COMPUTED_VALUE"""),FALSE) -> FALSE | G5: =IFERROR(__xludf.DUMMYFUNCTION("""COMPUTED_VALUE"""),FALSE) -> FALSE | H5: =IFERROR(__xludf.DUMMYFUNCTION("""COMPUTED_VALUE"""),FALSE) -> FALSE | I5: =IFERROR(__xludf.DUMMYFUNCTION("""COMPUTED_VALUE"""),FALSE) -> FALSE | J5: =IFERROR(__xludf.DUMMYFUNCTION("""COMPUTED_VALUE"""),TRUE) -> TRUE | K5: =IFERROR(__xludf.DUMMYFUNCTION("""COMPUTED_VALUE"""),FALSE) -> FALSE | L5: =IFERROR(__xludf.DUMMYFUNCTION("""COMPUTED_VALUE"""),TRUE) -> TRUE | M5: =IFERROR(__xludf.DUMMYFUNCTION("""COMPUTED_VALUE"""),"Pre-breakfast encountered Waylon and Sythwan together - gave them 1 pouch. Then encountered Sythwan after breakfast - they used Swampfoot") -> Pre-breakfast encountered Waylon and Sythwan together - gave them 1 pouch. Then encountered Sythwan after breakfast - they used Swampfoot | U5: =IFERROR(__xludf.DUMMYFUNCTION("""COMPUTED_VALUE"""),"Clairia") -> Clairia | V5: =IFERROR(__xludf.DUMMYFUNCTION("""COMPUTED_VALUE"""),5.0) -> 5
A6: =IFERROR(__xludf.DUMMYFUNCTION("""COMPUTED_VALUE"""),"Skeever 5") -> Skeever 5 | B6: =IFERROR(__xludf.DUMMYFUNCTION("""COMPUTED_VALUE"""),FALSE) -> FALSE | C6: =IFERROR(__xludf.DUMMYFUNCTION("""COMPUTED_VALUE"""),FALSE) -> FALSE | D6: =IFERROR(__xludf.DUMMYFUNCTION("""COMPUTED_VALUE"""),FALSE) -> FALSE | E6: =IFERROR(__xludf.DUMMYFUNCTION("""COMPUTED_VALUE"""),TRUE) -> TRUE | F6: =IFERROR(__xludf.DUMMYFUNCTION("""COMPUTED_VALUE"""),FALSE) -> FALSE | G6: =IFERROR(__xludf.DUMMYFUNCTION("""COMPUTED_VALUE"""),TRUE) -> TRUE | H6: =IFERROR(__xludf.DUMMYFUNCTION("""COMPUTED_VALUE"""),TRUE) -> TRUE | I6: =IFERROR(__xludf.DUMMYFUNCTION("""COMPUTED_VALUE"""),FALSE) -> FALSE | J6: =IFERROR(__xludf.DUMMYFUNCTION("""COMPUTED_VALUE"""),FALSE) -> FALSE | K6: =IFERROR(__xludf.DUMMYFUNCTION("""COMPUTED_VALUE"""),FALSE) -> FALSE | L6: =IFERROR(__xludf.DUMMYFUNCTION("""COMPUTED_VALUE"""),TRUE) -> TRUE | M6: =IFERROR(__xludf.DUMMYFUNCTION("""COMPUTED_VALUE"""),"Noctara has stookesters' (they cast Turn Coat); then teamed up with Skeever 7 to get G, W & E (U avoided us)") -> Noctara has stookesters' (they cast Turn Coat); then teamed up with Skeever 7 to get G, W & E (U avoided us) | U6: =IFERROR(__xludf.DUMMYFUNCTION("""COMPUTED_VALUE"""),"Doloron") -> Doloron | V6: =IFERROR(__xludf.DUMMYFUNCTION("""COMPUTED_VALUE"""),7.0) -> 7
A7: =IFERROR(__xludf.DUMMYFUNCTION("""COMPUTED_VALUE"""),"Skeever 6") -> Skeever 6 | B7: =IFERROR(__xludf.DUMMYFUNCTION("""COMPUTED_VALUE"""),FALSE) -> FALSE | C7: =IFERROR(__xludf.DUMMYFUNCTION("""COMPUTED_VALUE"""),FALSE) -> FALSE | D7: =IFERROR(__xludf.DUMMYFUNCTION("""COMPUTED_VALUE"""),FALSE) -> FALSE | E7: =IFERROR(__xludf.DUMMYFUNCTION("""COMPUTED_VALUE"""),FALSE) -> FALSE | F7: =IFERROR(__xludf.DUMMYFUNCTION("""COMPUTED_VALUE"""),FALSE) -> FALSE | G7: =IFERROR(__xludf.DUMMYFUNCTION("""COMPUTED_VALUE"""),FALSE) -> FALSE | H7: =IFERROR(__xludf.DUMMYFUNCTION("""COMPUTED_VALUE"""),FALSE) -> FALSE | I7: =IFERROR(__xludf.DUMMYFUNCTION("""COMPUTED_VALUE"""),FALSE) -> FALSE | ... L7: =IFERROR(__xludf.DUMMYFUNCTION("""COMPUTED_VALUE"""),FALSE) -> FALSE | U7: =IFERROR(__xludf.DUMMYFUNCTION("""COMPUTED_VALUE"""),"Elsewhich") -> Elsewhich | V7: =IFERROR(__xludf.DUMMYFUNCTION("""COMPUTED_VALUE"""),7.0) -> 7
A8: =IFERROR(__xludf.DUMMYFUNCTION("""COMPUTED_VALUE"""),"Skeever 7") -> Skeever 7 | B8: =IFERROR(__xludf.DUMMYFUNCTION("""COMPUTED_VALUE"""),FALSE) -> FALSE | C8: =IFERROR(__xludf.DUMMYFUNCTION("""COMPUTED_VALUE"""),FALSE) -> FALSE | D8: =IFERROR(__xludf.DUMMYFUNCTION("""COMPUTED_VALUE"""),FALSE) -> FALSE | E8: =IFERROR(__xludf.DUMMYFUNCTION("""COMPUTED_VALUE"""),TRUE) -> TRUE | F8: =IFERROR(__xludf.DUMMYFUNCTION("""COMPUTED_VALUE"""),FALSE) -> FALSE | G8: =IFERROR(__xludf.DUMMYFUNCTION("""COMPUTED_VALUE"""),TRUE) -> TRUE | H8: =IFERROR(__xludf.DUMMYFUNCTION("""COMPUTED_VALUE"""),TRUE) -> TRUE | I8: =IFERROR(__xludf.DUMMYFUNCTION("""COMPUTED_VALUE"""),TRUE) -> TRUE | J8: =IFERROR(__xludf.DUMMYFUNCTION("""COMPUTED_VALUE"""),FALSE) -> FALSE | K8: =IFERROR(__xludf.DUMMYFUNCTION("""COMPUTED_VALUE"""),FALSE) -> FALSE | L8: =IFERROR(__xludf.DUMMYFUNCTION("""COMPUTED_VALUE"""),TRUE) -> TRUE | M8: =IFERROR(__xludf.DUMMYFUNCTION("""COMPUTED_VALUE"""),"Everything was with skeever 5 except P'loa, who cast whirlwind on us.") -> Everything was with skeever 5 except P'loa, who cast whirlwind on us. | U8: =IFERROR(__xludf.DUMMYFUNCTION("""COMPUTED_VALUE"""),"Glendeep") -> Glendeep | V8: =IFERROR(__xludf.DUMMYFUNCTION("""COMPUTED_VALUE"""),8.0) -> 8
A9: =IFERROR(__xludf.DUMMYFUNCTION("""COMPUTED_VALUE"""),"Skeever 8") -> Skeever 8 | B9: =IFERROR(__xludf.DUMMYFUNCTION("""COMPUTED_VALUE"""),FALSE) -> FALSE | C9: =IFERROR(__xludf.DUMMYFUNCTION("""COMPUTED_VALUE"""),FALSE) -> FALSE | D9: =IFERROR(__xludf.DUMMYFUNCTION("""COMPUTED_VALUE"""),FALSE) -> FALSE | E9: =IFERROR(__xludf.DUMMYFUNCTION("""COMPUTED_VALUE"""),TRUE) -> TRUE | F9: =IFERROR(__xludf.DUMMYFUNCTION("""COMPUTED_VALUE"""),FALSE) -> FALSE | G9: =IFERROR(__xludf.DUMMYFUNCTION("""COMPUTED_VALUE"""),TRUE) -> TRUE | H9: =IFERROR(__xludf.DUMMYFUNCTION("""COMPUTED_VALUE"""),FALSE) -> FALSE | I9: =IFERROR(__xludf.DUMMYFUNCTION("""COMPUTED_VALUE"""),FALSE) -> FALSE | J9: =IFERROR(__xludf.DUMMYFUNCTION("""COMPUTED_VALUE"""),TRUE) -> TRUE | K9: =IFERROR(__xludf.DUMMYFUNCTION("""COMPUTED_VALUE"""),FALSE) -> FALSE | L9: =IFERROR(__xludf.DUMMYFUNCTION("""COMPUTED_VALUE"""),TRUE) -> TRUE | M9: =IFERROR(__xludf.DUMMYFUNCTION("""COMPUTED_VALUE"""),"Sythwan used gravitational pull; seemed inclined to leave us alone (having looted the third member). They also hit Cursed Skeever right after us, I think, so they may be (a) rich or (b) damaged. -LN, noon") -> Sythwan used gravitational pull; seemed inclined to leave us alone (having looted the third member). They also hit Cursed Skeever right after us, I think, so they may be (a) rich or (b) damaged. -LN, noon | U9: =IFERROR(__xludf.DUMMYFUNCTION("""COMPUTED_VALUE"""),"Keer") -> Keer | V9: =IFERROR(__xludf.DUMMYFUNCTION("""COMPUTED_VALUE"""),9.0) -> 9
A10: =IFERROR(__xludf.DUMMYFUNCTION("""COMPUTED_VALUE"""),"Skeever 9") -> Skeever 9 | B10: =IFERROR(__xludf.DUMMYFUNCTION("""COMPUTED_VALUE"""),TRUE) -> TRUE | C10: =IFERROR(__xludf.DUMMYFUNCTION("""COMPUTED_VALUE"""),FALSE) -> FALSE | D10: =IFERROR(__xludf.DUMMYFUNCTION("""COMPUTED_VALUE"""),TRUE) -> TRUE | E10: =IFERROR(__xludf.DUMMYFUNCTION("""COMPUTED_VALUE"""),FALSE) -> FALSE | F10: =IFERROR(__xludf.DUMMYFUNCTION("""COMPUTED_VALUE"""),TRUE) -> TRUE | G10: =IFERROR(__xludf.DUMMYFUNCTION("""COMPUTED_VALUE"""),FALSE) -> FALSE | H10: =IFERROR(__xludf.DUMMYFUNCTION("""COMPUTED_VALUE"""),FALSE) -> FALSE | I10: =IFERROR(__xludf.DUMMYFUNCTION("""COMPUTED_VALUE"""),TRUE) -> TRUE | J10: =IFERROR(__xludf.DUMMYFUNCTION("""COMPUTED_VALUE"""),FALSE) -> FALSE | K10: =IFERROR(__xludf.DUMMYFUNCTION("""COMPUTED_VALUE"""),FALSE) -> FALSE | L10: =IFERROR(__xludf.DUMMYFUNCTION("""COMPUTED_VALUE"""),TRUE) -> TRUE | M10: =IFERROR(__xludf.DUMMYFUNCTION("""COMPUTED_VALUE"""),"p'loa and waylon used death,arden rootfoot, doloron wirlwind,glendeep gravitational pull,teleport other, frost bite. A number of hits from cursed skeever dealt out to all parties (and usually some healing needed). Arden has at least one or two very tactic"&"ally impressive fighters. Would love if cursed wolven was able to hit P'loa again, the keeper really struggled and I would love for them to get a second chance to possibly step up more.") -> p'loa and waylon used death,arden rootfoot, doloron wirlwind,glendeep gravitational pull,teleport other, frost bite. A number of hits from cursed skeever dealt out to all parties (and usually some healing needed). Arden has at least one or two very tactically impressive fighters. Would love if cursed wolven was able to hit P'loa again, the keeper really struggled and I would love for them to get a second chance to possibly step up more. | U10: =IFERROR(__xludf.DUMMYFUNCTION("""COMPUTED_VALUE"""),"Noctara") -> Noctara | V10: =IFERROR(__xludf.DUMMYFUNCTION("""COMPUTED_VALUE"""),8.0) -> 8
A11: =IFERROR(__xludf.DUMMYFUNCTION("""COMPUTED_VALUE"""),"Skeever 10") -> Skeever 10 | B11: =IFERROR(__xludf.DUMMYFUNCTION("""COMPUTED_VALUE"""),FALSE) -> FALSE | C11: =IFERROR(__xludf.DUMMYFUNCTION("""COMPUTED_VALUE"""),FALSE) -> FALSE | D11: =IFERROR(__xludf.DUMMYFUNCTION("""COMPUTED_VALUE"""),TRUE) -> TRUE | E11: =IFERROR(__xludf.DUMMYFUNCTION("""COMPUTED_VALUE"""),FALSE) -> FALSE | F11: =IFERROR(__xludf.DUMMYFUNCTION("""COMPUTED_VALUE"""),FALSE) -> FALSE | G11: =IFERROR(__xludf.DUMMYFUNCTION("""COMPUTED_VALUE"""),FALSE) -> FALSE | H11: =IFERROR(__xludf.DUMMYFUNCTION("""COMPUTED_VALUE"""),FALSE) -> FALSE | I11: =IFERROR(__xludf.DUMMYFUNCTION("""COMPUTED_VALUE"""),FALSE) -> FALSE | J11: =IFERROR(__xludf.DUMMYFUNCTION("""COMPUTED_VALUE"""),TRUE) -> TRUE | K11: =IFERROR(__xludf.DUMMYFUNCTION("""COMPUTED_VALUE"""),TRUE) -> TRUE | L11: =IFERROR(__xludf.DUMMYFUNCTION("""COMPUTED_VALUE"""),FALSE) -> FALSE | M11: =IFERROR(__xludf.DUMMYFUNCTION("""COMPUTED_VALUE"""),"Sythwan used frost spell, UriKesh used two spells and thanked us for the fight, Doloron used sleep spell and thanked us") -> Sythwan used frost spell, UriKesh used two spells and thanked us for the fight, Doloron used sleep spell and thanked us | U11: =IFERROR(__xludf.DUMMYFUNCTION("""COMPUTED_VALUE"""),"P'loa") -> P'loa | V11: =IFERROR(__xludf.DUMMYFUNCTION("""COMPUTED_VALUE"""),8.0) -> 8
A12: =IFERROR(__xludf.DUMMYFUNCTION("""COMPUTED_VALUE"""),"Skeever 11") -> Skeever 11 | B12: =IFERROR(__xludf.DUMMYFUNCTION("""COMPUTED_VALUE"""),FALSE) -> FALSE | C12: =IFERROR(__xludf.DUMMYFUNCTION("""COMPUTED_VALUE"""),TRUE) -> TRUE | D12: =IFERROR(__xludf.DUMMYFUNCTION("""COMPUTED_VALUE"""),FALSE) -> FALSE | E12: =IFERROR(__xludf.DUMMYFUNCTION("""COMPUTED_VALUE"""),TRUE) -> TRUE | F12: =IFERROR(__xludf.DUMMYFUNCTION("""COMPUTED_VALUE"""),TRUE) -> TRUE | G12: =IFERROR(__xludf.DUMMYFUNCTION("""COMPUTED_VALUE"""),TRUE) -> TRUE | H12: =IFERROR(__xludf.DUMMYFUNCTION("""COMPUTED_VALUE"""),FALSE) -> FALSE | I12: =IFERROR(__xludf.DUMMYFUNCTION("""COMPUTED_VALUE"""),FALSE) -> FALSE | J12: =IFERROR(__xludf.DUMMYFUNCTION("""COMPUTED_VALUE"""),FALSE) -> FALSE | K12: =IFERROR(__xludf.DUMMYFUNCTION("""COMPUTED_VALUE"""),FALSE) -> FALSE | L12: =IFERROR(__xludf.DUMMYFUNCTION("""COMPUTED_VALUE"""),FALSE) -> FALSE | U12: =IFERROR(__xludf.DUMMYFUNCTION("""COMPUTED_VALUE"""),"Sythwan") -> Sythwan | V12: =IFERROR(__xludf.DUMMYFUNCTION("""COMPUTED_VALUE"""),10.0) -> 10
A13: =IFERROR(__xludf.DUMMYFUNCTION("""COMPUTED_VALUE"""),"Worlog 1") -> Worlog 1 | B13: =IFERROR(__xludf.DUMMYFUNCTION("""COMPUTED_VALUE"""),TRUE) -> TRUE | C13: =IFERROR(__xludf.DUMMYFUNCTION("""COMPUTED_VALUE"""),FALSE) -> FALSE | D13: =IFERROR(__xludf.DUMMYFUNCTION("""COMPUTED_VALUE"""),TRUE) -> TRUE | E13: =IFERROR(__xludf.DUMMYFUNCTION("""COMPUTED_VALUE"""),FALSE) -> FALSE | F13: =IFERROR(__xludf.DUMMYFUNCTION("""COMPUTED_VALUE"""),TRUE) -> TRUE | G13: =IFERROR(__xludf.DUMMYFUNCTION("""COMPUTED_VALUE"""),TRUE) -> TRUE | H13: =IFERROR(__xludf.DUMMYFUNCTION("""COMPUTED_VALUE"""),FALSE) -> FALSE | I13: =IFERROR(__xludf.DUMMYFUNCTION("""COMPUTED_VALUE"""),TRUE) -> TRUE | J13: =IFERROR(__xludf.DUMMYFUNCTION("""COMPUTED_VALUE"""),TRUE) -> TRUE | K13: =IFERROR(__xludf.DUMMYFUNCTION("""COMPUTED_VALUE"""),TRUE) -> TRUE | L13: =IFERROR(__xludf.DUMMYFUNCTION("""COMPUTED_VALUE"""),TRUE) -> TRUE | U13: =IFERROR(__xludf.DUMMYFUNCTION("""COMPUTED_VALUE"""),"Uri-Kesh") -> Uri-Kesh | V13: =IFERROR(__xludf.DUMMYFUNCTION("""COMPUTED_VALUE"""),5.0) -> 5
A14: =IFERROR(__xludf.DUMMYFUNCTION("""COMPUTED_VALUE"""),"Worlog 2") -> Worlog 2 | B14: =IFERROR(__xludf.DUMMYFUNCTION("""COMPUTED_VALUE"""),TRUE) -> TRUE | C14: =IFERROR(__xludf.DUMMYFUNCTION("""COMPUTED_VALUE"""),FALSE) -> FALSE | D14: =IFERROR(__xludf.DUMMYFUNCTION("""COMPUTED_VALUE"""),FALSE) -> FALSE | E14: =IFERROR(__xludf.DUMMYFUNCTION("""COMPUTED_VALUE"""),FALSE) -> FALSE | F14: =IFERROR(__xludf.DUMMYFUNCTION("""COMPUTED_VALUE"""),FALSE) -> FALSE | G14: =IFERROR(__xludf.DUMMYFUNCTION("""COMPUTED_VALUE"""),FALSE) -> FALSE | H14: =IFERROR(__xludf.DUMMYFUNCTION("""COMPUTED_VALUE"""),TRUE) -> TRUE | I14: =IFERROR(__xludf.DUMMYFUNCTION("""COMPUTED_VALUE"""),FALSE) -> FALSE | J14: =IFERROR(__xludf.DUMMYFUNCTION("""COMPUTED_VALUE"""),FALSE) -> FALSE | K14: =IFERROR(__xludf.DUMMYFUNCTION("""COMPUTED_VALUE"""),FALSE) -> FALSE | L14: =IFERROR(__xludf.DUMMYFUNCTION("""COMPUTED_VALUE"""),TRUE) -> TRUE | M14: =IFERROR(__xludf.DUMMYFUNCTION("""COMPUTED_VALUE"""),"Waylon and Noctara were amped, ""That was so fun!"" on exit. Arden Walked Through Shadows and looked proud.") -> Waylon and Noctara were amped, "That was so fun!" on exit. Arden Walked Through Shadows and looked proud. | U14: =IFERROR(__xludf.DUMMYFUNCTION("""COMPUTED_VALUE"""),"Waylon") -> Waylon | V14: =IFERROR(__xludf.DUMMYFUNCTION("""COMPUTED_VALUE"""),14.0) -> 14
A15: =IFERROR(__xludf.DUMMYFUNCTION("""COMPUTED_VALUE"""),"Wolven 1") -> Wolven 1 | B15: =IFERROR(__xludf.DUMMYFUNCTION("""COMPUTED_VALUE"""),FALSE) -> FALSE | C15: =IFERROR(__xludf.DUMMYFUNCTION("""COMPUTED_VALUE"""),FALSE) -> FALSE | D15: =IFERROR(__xludf.DUMMYFUNCTION("""COMPUTED_VALUE"""),TRUE) -> TRUE | E15: =IFERROR(__xludf.DUMMYFUNCTION("""COMPUTED_VALUE"""),TRUE) -> TRUE | F15: =IFERROR(__xludf.DUMMYFUNCTION("""COMPUTED_VALUE"""),FALSE) -> FALSE | G15: =IFERROR(__xludf.DUMMYFUNCTION("""COMPUTED_VALUE"""),FALSE) -> FALSE | H15: =IFERROR(__xludf.DUMMYFUNCTION("""COMPUTED_VALUE"""),FALSE) -> FALSE | I15: =IFERROR(__xludf.DUMMYFUNCTION("""COMPUTED_VALUE"""),FALSE) -> FALSE | J15: =IFERROR(__xludf.DUMMYFUNCTION("""COMPUTED_VALUE"""),FALSE) -> FALSE | K15: =IFERROR(__xludf.DUMMYFUNCTION("""COMPUTED_VALUE"""),TRUE) -> TRUE | L15: =IFERROR(__xludf.DUMMYFUNCTION("""COMPUTED_VALUE"""),FALSE) -> FALSE | M15: =IFERROR(__xludf.DUMMYFUNCTION("""COMPUTED_VALUE"""),"Uri-Kesh has Aloras and wants to sell it, they used an item to heal someone. Doloron caster is salty. we killed 2 of them, they cast paralyze and teleport self. Elsewhich had to use a couple keeper spells. -AMG") -> Uri-Kesh has Aloras and wants to sell it, they used an item to heal someone. Doloron caster is salty. we killed 2 of them, they cast paralyze and teleport self. Elsewhich had to use a couple keeper spells. -AMG
A16: =IFERROR(__xludf.DUMMYFUNCTION("""COMPUTED_VALUE"""),"Wolven 2") -> Wolven 2 | B16: =IFERROR(__xludf.DUMMYFUNCTION("""COMPUTED_VALUE"""),FALSE) -> FALSE | C16: =IFERROR(__xludf.DUMMYFUNCTION("""COMPUTED_VALUE"""),FALSE) -> FALSE | D16: =IFERROR(__xludf.DUMMYFUNCTION("""COMPUTED_VALUE"""),FALSE) -> FALSE | E16: =IFERROR(__xludf.DUMMYFUNCTION("""COMPUTED_VALUE"""),FALSE) -> FALSE | F16: =IFERROR(__xludf.DUMMYFUNCTION("""COMPUTED_VALUE"""),FALSE) -> FALSE | G16: =IFERROR(__xludf.DUMMYFUNCTION("""COMPUTED_VALUE"""),FALSE) -> FALSE | H16: =IFERROR(__xludf.DUMMYFUNCTION("""COMPUTED_VALUE"""),TRUE) -> TRUE | I16: =IFERROR(__xludf.DUMMYFUNCTION("""COMPUTED_VALUE"""),TRUE) -> TRUE | J16: =IFERROR(__xludf.DUMMYFUNCTION("""COMPUTED_VALUE"""),FALSE) -> FALSE | K16: =IFERROR(__xludf.DUMMYFUNCTION("""COMPUTED_VALUE"""),FALSE) -> FALSE | L16: =IFERROR(__xludf.DUMMYFUNCTION("""COMPUTED_VALUE"""),FALSE) -> FALSE | M16: =IFERROR(__xludf.DUMMYFUNCTION("""COMPUTED_VALUE"""),"both confident in combat") -> both confident in combat
A17: =IFERROR(__xludf.DUMMYFUNCTION("""COMPUTED_VALUE"""),"Wolven 3") -> Wolven 3 | B17: =IFERROR(__xludf.DUMMYFUNCTION("""COMPUTED_VALUE"""),FALSE) -> FALSE | C17: =IFERROR(__xludf.DUMMYFUNCTION("""COMPUTED_VALUE"""),FALSE) -> FALSE | D17: =IFERROR(__xludf.DUMMYFUNCTION("""COMPUTED_VALUE"""),FALSE) -> FALSE | E17: =IFERROR(__xludf.DUMMYFUNCTION("""COMPUTED_VALUE"""),FALSE) -> FALSE | F17: =IFERROR(__xludf.DUMMYFUNCTION("""COMPUTED_VALUE"""),FALSE) -> FALSE | G17: =IFERROR(__xludf.DUMMYFUNCTION("""COMPUTED_VALUE"""),FALSE) -> FALSE | H17: =IFERROR(__xludf.DUMMYFUNCTION("""COMPUTED_VALUE"""),TRUE) -> TRUE | I17: =IFERROR(__xludf.DUMMYFUNCTION("""COMPUTED_VALUE"""),FALSE) -> FALSE | J17: =IFERROR(__xludf.DUMMYFUNCTION("""COMPUTED_VALUE"""),FALSE) -> FALSE | K17: =IFERROR(__xludf.DUMMYFUNCTION("""COMPUTED_VALUE"""),FALSE) -> FALSE | L17: =IFERROR(__xludf.DUMMYFUNCTION("""COMPUTED_VALUE"""),TRUE) -> TRUE | M17: =IFERROR(__xludf.DUMMYFUNCTION("""COMPUTED_VALUE"""),"Noctara has Tick Tick Boom — Kim 3pm") -> Noctara has Tick Tick Boom — Kim 3pm
A18: =IFERROR(__xludf.DUMMYFUNCTION("""COMPUTED_VALUE"""),"Wolven 4") -> Wolven 4 | B18: =IFERROR(__xludf.DUMMYFUNCTION("""COMPUTED_VALUE"""),FALSE) -> FALSE | C18: =IFERROR(__xludf.DUMMYFUNCTION("""COMPUTED_VALUE"""),FALSE) -> FALSE | D18: =IFERROR(__xludf.DUMMYFUNCTION("""COMPUTED_VALUE"""),FALSE) -> FALSE | E18: =IFERROR(__xludf.DUMMYFUNCTION("""COMPUTED_VALUE"""),FALSE) -> FALSE | F18: =IFERROR(__xludf.DUMMYFUNCTION("""COMPUTED_VALUE"""),FALSE) -> FALSE | G18: =IFERROR(__xludf.DUMMYFUNCTION("""COMPUTED_VALUE"""),FALSE) -> FALSE | H18: =IFERROR(__xludf.DUMMYFUNCTION("""COMPUTED_VALUE"""),FALSE) -> FALSE | I18: =IFERROR(__xludf.DUMMYFUNCTION("""COMPUTED_VALUE"""),TRUE) -> TRUE | J18: =IFERROR(__xludf.DUMMYFUNCTION("""COMPUTED_VALUE"""),TRUE) -> TRUE | K18: =IFERROR(__xludf.DUMMYFUNCTION("""COMPUTED_VALUE"""),FALSE) -> FALSE | L18: =IFERROR(__xludf.DUMMYFUNCTION("""COMPUTED_VALUE"""),FALSE) -> FALSE | M18: =IFERROR(__xludf.DUMMYFUNCTION("""COMPUTED_VALUE"""),"Elsewhich: took a lot of free hits, plus death spell and entangle spell, one arm wound and one heal one Sythwan: joined in halfway through tried to do his little damage as possible. P'loa: used teleport, walk in shadows, line of fire, heal all prayer and "&"potion of life used. Good planning and poise.") -> Elsewhich: took a lot of free hits, plus death spell and entangle spell, one arm wound and one heal one Sythwan: joined in halfway through tried to do his little damage as possible. P'loa: used teleport, walk in shadows, line of fire, heal all prayer and potion of life used. Good planning and poise.
A19: =IFERROR(__xludf.DUMMYFUNCTION("""COMPUTED_VALUE"""),"Wolven 5") -> Wolven 5 | B19: =IFERROR(__xludf.DUMMYFUNCTION("""COMPUTED_VALUE"""),FALSE) -> FALSE | C19: =IFERROR(__xludf.DUMMYFUNCTION("""COMPUTED_VALUE"""),FALSE) -> FALSE | D19: =IFERROR(__xludf.DUMMYFUNCTION("""COMPUTED_VALUE"""),FALSE) -> FALSE | E19: =IFERROR(__xludf.DUMMYFUNCTION("""COMPUTED_VALUE"""),FALSE) -> FALSE | F19: =IFERROR(__xludf.DUMMYFUNCTION("""COMPUTED_VALUE"""),FALSE) -> FALSE | G19: =IFERROR(__xludf.DUMMYFUNCTION("""COMPUTED_VALUE"""),FALSE) -> FALSE | H19: =IFERROR(__xludf.DUMMYFUNCTION("""COMPUTED_VALUE"""),FALSE) -> FALSE | I19: =IFERROR(__xludf.DUMMYFUNCTION("""COMPUTED_VALUE"""),FALSE) -> FALSE | ... K19: =IFERROR(__xludf.DUMMYFUNCTION("""COMPUTED_VALUE"""),FALSE) -> FALSE | L19: =IFERROR(__xludf.DUMMYFUNCTION("""COMPUTED_VALUE"""),TRUE) -> TRUE | M19: =IFERROR(__xludf.DUMMYFUNCTION("""COMPUTED_VALUE"""),"Clairia (3 person party, did not send out cursed Wolven), Waylon, Elsewhich, and Keer got individual battles. Then we had a 3-party Uberbattle with Waylon, Noctara, and Glendeep. Lots of hits and wounds, some deaths, some spells used, no extreme damage. "&"Keer used Death + another spell on CW. Waylon used wand that affects all non-humans on the Wolven. Womp womp. --HA ") -> Clairia (3 person party, did not send out cursed Wolven), Waylon, Elsewhich, and Keer got individual battles. Then we had a 3-party Uberbattle with Waylon, Noctara, and Glendeep. Lots of hits and wounds, some deaths, some spells used, no extreme damage. Keer used Death + another spell on CW. Waylon used wand that affects all non-humans on the Wolven. Womp womp. --HA
A20: =IFERROR(__xludf.DUMMYFUNCTION("""COMPUTED_VALUE"""),"Wolven 6") -> Wolven 6 | B20: =IFERROR(__xludf.DUMMYFUNCTION("""COMPUTED_VALUE"""),FALSE) -> FALSE | C20: =IFERROR(__xludf.DUMMYFUNCTION("""COMPUTED_VALUE"""),FALSE) -> FALSE | D20: =IFERROR(__xludf.DUMMYFUNCTION("""COMPUTED_VALUE"""),FALSE) -> FALSE | E20: =IFERROR(__xludf.DUMMYFUNCTION("""COMPUTED_VALUE"""),FALSE) -> FALSE | F20: =IFERROR(__xludf.DUMMYFUNCTION("""COMPUTED_VALUE"""),FALSE) -> FALSE | G20: =IFERROR(__xludf.DUMMYFUNCTION("""COMPUTED_VALUE"""),FALSE) -> FALSE | H20: =IFERROR(__xludf.DUMMYFUNCTION("""COMPUTED_VALUE"""),FALSE) -> FALSE | I20: =IFERROR(__xludf.DUMMYFUNCTION("""COMPUTED_VALUE"""),FALSE) -> FALSE | ... L20: =IFERROR(__xludf.DUMMYFUNCTION("""COMPUTED_VALUE"""),FALSE) -> FALSE
A21: =IFERROR(__xludf.DUMMYFUNCTION("""COMPUTED_VALUE"""),"Wolven 7") -> Wolven 7 | B21: =IFERROR(__xludf.DUMMYFUNCTION("""COMPUTED_VALUE"""),TRUE) -> TRUE | C21: =IFERROR(__xludf.DUMMYFUNCTION("""COMPUTED_VALUE"""),FALSE) -> FALSE | D21: =IFERROR(__xludf.DUMMYFUNCTION("""COMPUTED_VALUE"""),TRUE) -> TRUE | E21: =IFERROR(__xludf.DUMMYFUNCTION("""COMPUTED_VALUE"""),FALSE) -> FALSE | F21: =IFERROR(__xludf.DUMMYFUNCTION("""COMPUTED_VALUE"""),FALSE) -> FALSE | G21: =IFERROR(__xludf.DUMMYFUNCTION("""COMPUTED_VALUE"""),FALSE) -> FALSE | H21: =IFERROR(__xludf.DUMMYFUNCTION("""COMPUTED_VALUE"""),FALSE) -> FALSE | I21: =IFERROR(__xludf.DUMMYFUNCTION("""COMPUTED_VALUE"""),FALSE) -> FALSE | J21: =IFERROR(__xludf.DUMMYFUNCTION("""COMPUTED_VALUE"""),TRUE) -> TRUE | K21: =IFERROR(__xludf.DUMMYFUNCTION("""COMPUTED_VALUE"""),FALSE) -> FALSE | L21: =IFERROR(__xludf.DUMMYFUNCTION("""COMPUTED_VALUE"""),TRUE) -> TRUE | M21: =IFERROR(__xludf.DUMMYFUNCTION("""COMPUTED_VALUE"""),"Doloron did single combat (losing a leg); Arden lost a bunch of free hits and one arm; Sythway used a wolven wand and got ander mad libs (jump to eifel tower yelling zoinks); Waylon used 3 keeper spells including life -- basically out of free hits and kee"&"per spells but all were standing when they left. Notes on Ander mad libs -- so fun and funny! Sythwan: 2 wolven holding hands (from a party spell) had to jump to the Eiffel Tower yelling ""Zoinks!"" Waylon: 1 wolven had to be violently thrifty for the ne"&"xt 5 minutes when they see anything orange") -> Doloron did single combat (losing a leg); Arden lost a bunch of free hits and one arm; Sythway used a wolven wand and got ander mad libs (jump to eifel tower yelling zoinks); Waylon used 3 keeper spells including life -- basically out of free hits and keeper spells but all were standing when they left. Notes on Ander mad libs -- so fun and funny! Sythwan: 2 wolven holding hands (from a party spell) had to jump to the Eiffel Tower yelling "Zoinks!" Waylon: 1 wolven had to be violently thrifty for the next 5 minutes when they see anything orange
A22: =IFERROR(__xludf.DUMMYFUNCTION("""COMPUTED_VALUE"""),"Wolven 8") -> Wolven 8 | B22: =IFERROR(__xludf.DUMMYFUNCTION("""COMPUTED_VALUE"""),TRUE) -> TRUE | C22: =IFERROR(__xludf.DUMMYFUNCTION("""COMPUTED_VALUE"""),FALSE) -> FALSE | D22: =IFERROR(__xludf.DUMMYFUNCTION("""COMPUTED_VALUE"""),FALSE) -> FALSE | E22: =IFERROR(__xludf.DUMMYFUNCTION("""COMPUTED_VALUE"""),FALSE) -> FALSE | F22: =IFERROR(__xludf.DUMMYFUNCTION("""COMPUTED_VALUE"""),TRUE) -> TRUE | G22: =IFERROR(__xludf.DUMMYFUNCTION("""COMPUTED_VALUE"""),FALSE) -> FALSE | H22: =IFERROR(__xludf.DUMMYFUNCTION("""COMPUTED_VALUE"""),TRUE) -> TRUE | I22: =IFERROR(__xludf.DUMMYFUNCTION("""COMPUTED_VALUE"""),TRUE) -> TRUE | J22: =IFERROR(__xludf.DUMMYFUNCTION("""COMPUTED_VALUE"""),TRUE) -> TRUE | K22: =IFERROR(__xludf.DUMMYFUNCTION("""COMPUTED_VALUE"""),TRUE) -> TRUE | L22: =IFERROR(__xludf.DUMMYFUNCTION("""COMPUTED_VALUE"""),TRUE) -> TRUE | M22: =IFERROR(__xludf.DUMMYFUNCTION("""COMPUTED_VALUE"""),"2 of us got separated and ran into Arden who used Basket of Wolven Slaying. We then ran into Uri Kesh who used Combat Focus. Finally we met up with the rest of our group and ran into Noctara who used Hidden Path. On way back to basement we ran into both W"&"aylon and Sythwan and both parties used Hidden Path to elude us. Glendeep used a ""Ranger Full Party Decloak"" maneuver on Hatchet & Co. They hidden path-ed right into our midst and then hacked us apart. And then they killed Hatchet with a Death spell!") -> 2 of us got separated and ran into Arden who used Basket of Wolven Slaying. We then ran into Uri Kesh who used Combat Focus. Finally we met up with the rest of our group and ran into Noctara who used Hidden Path. On way back to basement we ran into both Waylon and Sythwan and both parties used Hidden Path to elude us. Glendeep used a "Ranger Full Party Decloak" maneuver on Hatchet & Co. They hidden path-ed right into our midst and then hacked us apart. And then they killed Hatchet with a Death spell!
A23: =IFERROR(__xludf.DUMMYFUNCTION("""COMPUTED_VALUE"""),"Wolven 9") -> Wolven 9 | B23: =IFERROR(__xludf.DUMMYFUNCTION("""COMPUTED_VALUE"""),FALSE) -> FALSE | C23: =IFERROR(__xludf.DUMMYFUNCTION("""COMPUTED_VALUE"""),TRUE) -> TRUE | D23: =IFERROR(__xludf.DUMMYFUNCTION("""COMPUTED_VALUE"""),FALSE) -> FALSE | E23: =IFERROR(__xludf.DUMMYFUNCTION("""COMPUTED_VALUE"""),TRUE) -> TRUE | F23: =IFERROR(__xludf.DUMMYFUNCTION("""COMPUTED_VALUE"""),TRUE) -> TRUE | G23: =IFERROR(__xludf.DUMMYFUNCTION("""COMPUTED_VALUE"""),FALSE) -> FALSE | H23: =IFERROR(__xludf.DUMMYFUNCTION("""COMPUTED_VALUE"""),FALSE) -> FALSE | I23: =IFERROR(__xludf.DUMMYFUNCTION("""COMPUTED_VALUE"""),TRUE) -> TRUE | J23: =IFERROR(__xludf.DUMMYFUNCTION("""COMPUTED_VALUE"""),FALSE) -> FALSE | K23: =IFERROR(__xludf.DUMMYFUNCTION("""COMPUTED_VALUE"""),FALSE) -> FALSE | L23: =IFERROR(__xludf.DUMMYFUNCTION("""COMPUTED_VALUE"""),FALSE) -> FALSE | M23: =IFERROR(__xludf.DUMMYFUNCTION("""COMPUTED_VALUE"""),"Uri-Kesh passed with secret path, Gleendeep fought with moderate wounding, Clairia barely fought with minor injury, Elsewhich called 1-1 combat and killed Rowan (got scared after Fury killed her own herald for failing to make them kneel), P'loa tried to c"&"all secret path but Fury cast smash the patriarchy and eventually died while every wolven and p'loan fought on their knees = one P'loan dead") -> Uri-Kesh passed with secret path, Gleendeep fought with moderate wounding, Clairia barely fought with minor injury, Elsewhich called 1-1 combat and killed Rowan (got scared after Fury killed her own herald for failing to make them kneel), P'loa tried to call secret path but Fury cast smash the patriarchy and eventually died while every wolven and p'loan fought on their knees = one P'loan dead
A24: =IFERROR(__xludf.DUMMYFUNCTION("""COMPUTED_VALUE"""),"Wolven 10") -> Wolven 10 | B24: =IFERROR(__xludf.DUMMYFUNCTION("""COMPUTED_VALUE"""),FALSE) -> FALSE | C24: =IFERROR(__xludf.DUMMYFUNCTION("""COMPUTED_VALUE"""),FALSE) -> FALSE | D24: =IFERROR(__xludf.DUMMYFUNCTION("""COMPUTED_VALUE"""),FALSE) -> FALSE | E24: =IFERROR(__xludf.DUMMYFUNCTION("""COMPUTED_VALUE"""),FALSE) -> FALSE | F24: =IFERROR(__xludf.DUMMYFUNCTION("""COMPUTED_VALUE"""),FALSE) -> FALSE | G24: =IFERROR(__xludf.DUMMYFUNCTION("""COMPUTED_VALUE"""),TRUE) -> TRUE | H24: =IFERROR(__xludf.DUMMYFUNCTION("""COMPUTED_VALUE"""),TRUE) -> TRUE | I24: =IFERROR(__xludf.DUMMYFUNCTION("""COMPUTED_VALUE"""),FALSE) -> FALSE | J24: =IFERROR(__xludf.DUMMYFUNCTION("""COMPUTED_VALUE"""),FALSE) -> FALSE | K24: =IFERROR(__xludf.DUMMYFUNCTION("""COMPUTED_VALUE"""),FALSE) -> FALSE | L24: =IFERROR(__xludf.DUMMYFUNCTION("""COMPUTED_VALUE"""),TRUE) -> TRUE | M24: =IFERROR(__xludf.DUMMYFUNCTION("""COMPUTED_VALUE"""),"Noctara got Fortuna D'Oro. They knew what it was right away and were very excited. ") -> Noctara got Fortuna D'Oro. They knew what it was right away and were very excited.
A25: =IFERROR(__xludf.DUMMYFUNCTION("""COMPUTED_VALUE"""),"Wolven 11") -> Wolven 11 | B25: =IFERROR(__xludf.DUMMYFUNCTION("""COMPUTED_VALUE"""),FALSE) -> FALSE | C25: =IFERROR(__xludf.DUMMYFUNCTION("""COMPUTED_VALUE"""),FALSE) -> FALSE | D25: =IFERROR(__xludf.DUMMYFUNCTION("""COMPUTED_VALUE"""),TRUE) -> TRUE | E25: =IFERROR(__xludf.DUMMYFUNCTION("""COMPUTED_VALUE"""),FALSE) -> FALSE | F25: =IFERROR(__xludf.DUMMYFUNCTION("""COMPUTED_VALUE"""),FALSE) -> FALSE | G25: =IFERROR(__xludf.DUMMYFUNCTION("""COMPUTED_VALUE"""),FALSE) -> FALSE | H25: =IFERROR(__xludf.DUMMYFUNCTION("""COMPUTED_VALUE"""),FALSE) -> FALSE | I25: =IFERROR(__xludf.DUMMYFUNCTION("""COMPUTED_VALUE"""),FALSE) -> FALSE | J25: =IFERROR(__xludf.DUMMYFUNCTION("""COMPUTED_VALUE"""),FALSE) -> FALSE | K25: =IFERROR(__xludf.DUMMYFUNCTION("""COMPUTED_VALUE"""),FALSE) -> FALSE | L25: =IFERROR(__xludf.DUMMYFUNCTION("""COMPUTED_VALUE"""),FALSE) -> FALSE
A26: =IFERROR(__xludf.DUMMYFUNCTION("""COMPUTED_VALUE"""),"Wolven 12") -> Wolven 12 | B26: =IFERROR(__xludf.DUMMYFUNCTION("""COMPUTED_VALUE"""),TRUE) -> TRUE | C26: =IFERROR(__xludf.DUMMYFUNCTION("""COMPUTED_VALUE"""),FALSE) -> FALSE | D26: =IFERROR(__xludf.DUMMYFUNCTION("""COMPUTED_VALUE"""),FALSE) -> FALSE | E26: =IFERROR(__xludf.DUMMYFUNCTION("""COMPUTED_VALUE"""),FALSE) -> FALSE | F26: =IFERROR(__xludf.DUMMYFUNCTION("""COMPUTED_VALUE"""),TRUE) -> TRUE | G26: =IFERROR(__xludf.DUMMYFUNCTION("""COMPUTED_VALUE"""),FALSE) -> FALSE | H26: =IFERROR(__xludf.DUMMYFUNCTION("""COMPUTED_VALUE"""),FALSE) -> FALSE | I26: =IFERROR(__xludf.DUMMYFUNCTION("""COMPUTED_VALUE"""),FALSE) -> FALSE | J26: =IFERROR(__xludf.DUMMYFUNCTION("""COMPUTED_VALUE"""),FALSE) -> FALSE | K26: =IFERROR(__xludf.DUMMYFUNCTION("""COMPUTED_VALUE"""),FALSE) -> FALSE | L26: =IFERROR(__xludf.DUMMYFUNCTION("""COMPUTED_VALUE"""),FALSE) -> FALSE | M26: =IFERROR(__xludf.DUMMYFUNCTION("""COMPUTED_VALUE"""),"Single combat between seeker from Glendeep and Anderson.") -> Single combat between seeker from Glendeep and Anderson.
A27: =IFERROR(__xludf.DUMMYFUNCTION("""COMPUTED_VALUE"""),"Bachelorette 1") -> Bachelorette 1 | B27: =IFERROR(__xludf.DUMMYFUNCTION("""COMPUTED_VALUE"""),TRUE) -> TRUE | C27: =IFERROR(__xludf.DUMMYFUNCTION("""COMPUTED_VALUE"""),TRUE) -> TRUE | D27: =IFERROR(__xludf.DUMMYFUNCTION("""COMPUTED_VALUE"""),FALSE) -> FALSE | E27: =IFERROR(__xludf.DUMMYFUNCTION("""COMPUTED_VALUE"""),FALSE) -> FALSE | F27: =IFERROR(__xludf.DUMMYFUNCTION("""COMPUTED_VALUE"""),TRUE) -> TRUE | G27: =IFERROR(__xludf.DUMMYFUNCTION("""COMPUTED_VALUE"""),TRUE) -> TRUE | H27: =IFERROR(__xludf.DUMMYFUNCTION("""COMPUTED_VALUE"""),FALSE) -> FALSE | I27: =IFERROR(__xludf.DUMMYFUNCTION("""COMPUTED_VALUE"""),TRUE) -> TRUE | J27: =IFERROR(__xludf.DUMMYFUNCTION("""COMPUTED_VALUE"""),TRUE) -> TRUE | K27: =IFERROR(__xludf.DUMMYFUNCTION("""COMPUTED_VALUE"""),FALSE) -> FALSE | L27: =IFERROR(__xludf.DUMMYFUNCTION("""COMPUTED_VALUE"""),TRUE) -> TRUE | M27: =IFERROR(__xludf.DUMMYFUNCTION("""COMPUTED_VALUE"""),"Great single combat with seeker from Arden. Party was super supportive of cheering her on even with self doubt (I'm too short to really hit her!)") -> Great single combat with seeker from Arden. Party was super supportive of cheering her on even with self doubt (I'm too short to really hit her!)
A28: =IFERROR(__xludf.DUMMYFUNCTION("""COMPUTED_VALUE"""),"Bachelorette 2") -> Bachelorette 2 | B28: =IFERROR(__xludf.DUMMYFUNCTION("""COMPUTED_VALUE"""),TRUE) -> TRUE | C28: =IFERROR(__xludf.DUMMYFUNCTION("""COMPUTED_VALUE"""),FALSE) -> FALSE | D28: =IFERROR(__xludf.DUMMYFUNCTION("""COMPUTED_VALUE"""),FALSE) -> FALSE | E28: =IFERROR(__xludf.DUMMYFUNCTION("""COMPUTED_VALUE"""),TRUE) -> TRUE | F28: =IFERROR(__xludf.DUMMYFUNCTION("""COMPUTED_VALUE"""),FALSE) -> FALSE | G28: =IFERROR(__xludf.DUMMYFUNCTION("""COMPUTED_VALUE"""),TRUE) -> TRUE | H28: =IFERROR(__xludf.DUMMYFUNCTION("""COMPUTED_VALUE"""),FALSE) -> FALSE | I28: =IFERROR(__xludf.DUMMYFUNCTION("""COMPUTED_VALUE"""),FALSE) -> FALSE | J28: =IFERROR(__xludf.DUMMYFUNCTION("""COMPUTED_VALUE"""),TRUE) -> TRUE | K28: =IFERROR(__xludf.DUMMYFUNCTION("""COMPUTED_VALUE"""),FALSE) -> FALSE | L28: =IFERROR(__xludf.DUMMYFUNCTION("""COMPUTED_VALUE"""),TRUE) -> TRUE | M28: =IFERROR(__xludf.DUMMYFUNCTION("""COMPUTED_VALUE"""),"Waylon - used Single Combat, then passed us again with Sythwan, used Root Foot, only hit two. Keer and Arden were non-combat (Keer used Secret Path and snuck past us ""sleeping"" and Arden watched us dance/attack each other. All parties were very friendly"&" toward us and seemed in good spirits throughout and after fight. - ESD") -> Waylon - used Single Combat, then passed us again with Sythwan, used Root Foot, only hit two. Keer and Arden were non-combat (Keer used Secret Path and snuck past us "sleeping" and Arden watched us dance/attack each other. All parties were very friendly toward us and seemed in good spirits throughout and after fight. - ESD
A29: =IFERROR(__xludf.DUMMYFUNCTION("""COMPUTED_VALUE"""),"Wolven 13") -> Wolven 13 | B29: =IFERROR(__xludf.DUMMYFUNCTION("""COMPUTED_VALUE"""),"x") -> x | M29: =IFERROR(__xludf.DUMMYFUNCTION("""COMPUTED_VALUE"""),"Arden used Petrify, along with at least two Keeper heals, good combat, all engaged and working together.") -> Arden used Petrify, along with at least two Keeper heals, good combat, all engaged and working together.
M30: =IFERROR(__xludf.DUMMYFUNCTION("""COMPUTED_VALUE"""),"Saw eliswhich first 3 down one brought back by potion. Single combat with Waylon seeker down. Arden chased into dinner no combat. Light combat sythwan and waylon. Keer used hide in shadows. Bacherlorette 2") -> Saw eliswhich first 3 down one brought back by potion. Single combat with Waylon seeker down. Arden chased into dinner no combat. Light combat sythwan and waylon. Keer used hide in shadows. Bacherlorette 2

Sheet Clairia_Party Sheet
A1: CLAIRIA
A2: Investigating the charge against: Danny Donovan
A3: Companion: Clementine (Britt Rothauser)
A4: Keeper’s Saturday morning dream: The vision shows the carbon key and will (hopefully!) lead the party to Ember.
A5: Riddle: phoenix-bird riddle; tree straddling Summer Stream
A6: Keeper’s Sunday morning dream: Shows both the ghosts of the Morg and Honoré’s letter to Aria, both of which are faded but also have important messages for the party.
A8: Complete? | B8: Staff | C8: Time | D8: Items to give | F8: Complete? | G8: Staff | H8: Info to Give | I8: Bloc Requirements
A9: =if(Clairia_Import!B5=true,"Yes!","No") -> No | B9: Moxie | C9: Contact | D9: -- | F9: =if(Clairia_Import!B24=true,"Yes!","No") -> Yes! | G9: Honoré Valerius | H9: assigns charge, mentions letter | I9: Need | J9: =COUNTif(F9,"Yes!") -> 1
A10: =if(Clairia_Import!B6=true,"Yes!","No") -> Yes! | B10: Brimstone | C10: 2nd Friday | D10: -- | F10: =if(Clairia_Import!B25=true,"Yes!","No") -> Yes! | G10: Aria Morgan | H10: She fired Danny Donovan Thursday morning for throwing away important paperwork, Honoré gave her a letter listing all of Danny’s good points, theater burned down Thursday night. Aria has no memory of Thursday night but is sure Danny did this. | I10: Need | J10: =COUNTif(F10:F14,"Yes!") -> 3
A11: =if(Clairia_Import!B7=true,"Yes!","No") -> Yes! | B11: Pascal Valerius | C11: 3rd Friday | D11: -- | F11: =if(Clairia_Import!B26=true,"Yes!","No") -> Yes! | G11: Danny Donovon | H11: Aria fired Danny for throwing away some crumpled old papers, he woke up on tavern cot Friday morning sooty with burned clothes. He thinks he must have used White Noise again and started the fire. He can’t remember. | I11: Need
A12: =if(Clairia_Import!B8=true,"Yes!","No") -> Yes! | B12: Lenora Graves | C12: 4th Friday | D12: list of items | F12: =if(Clairia_Import!B27=true,"Yes!","No") -> No | G12: Eugenie Bright | H12: Memories of theater, including Montgomery Morgan + Aria dancing with a white paper crown | I12: Need
A13: =if(Clairia_Import!B9=true,"Yes!","No") -> Yes! | B13: Dramina | C13: 1st Saturday | D13: dragon’s egg ring | F13: =if(Clairia_Import!B28=true,"Yes!","No") -> No | G13: Ned Crochett | H13: Danny came out of his room at the tavern Friday morning sooty and smelling of smoke, no idea what happened to him | I13: Need 2 | J13: =COUNTif(F13:F15,"Yes!") -> 2
A14: =if(Clairia_Import!B10=true,"Yes!","No") -> Yes! | B14: Kyson Wayseeker | C14: 10am-4pm | D14: featherflame herb | F14: =if(Clairia_Import!B29=true,"Yes!","No") -> Yes! | G14: Aleeya Witchborn | H14: Danny came out of his room at the tavern Friday morning sooty and smelling of smoke, no idea what happened to him
A15: =if(Clairia_Import!B11=true,"Yes!","No") -> Yes! | B15: Adina Valerius | C15: 8am-2pm | D15: none until tomorrow | F15: =if(Clairia_Import!B30=true,"Yes!","No") -> Yes! | G15: Elliott Peacock | H15: Danny came out of tavern Friday morning, sooty and smelling of smoke, and stared at the theater in shock
A16: =if(Clairia_Import!B12=true,"Yes!","No") -> Yes! | B16: Natasha | C16: 12noon-8pm | D16: winterheart gem | F16: =if(Clairia_Import!B31=true,"Yes!","No") -> No | G16: Electra | H16: Danny had been clean for six months, and Aria took a risk hiring him early in his sobriety. | I16: Need 3 | J16: =COUNTif(F16:F20,"Yes!") -> 3
A17: =if(Clairia_Import!B13=true,"Yes!","No") -> Yes! | B17: Jack Johnson | C17: 11am-6pm | D17: fool’s gold | F17: =if(Clairia_Import!B32=true,"Yes!","No") -> No | G17: Stevie Peacock | H17: Danny told her last week he didn’t want to let Aria down after she gave him a chance, but maybe he went back to using or maybe he burned the theater down out of spite?
A18: =if(Clairia_Import!B14=true,"Yes!","No") -> Yes! | B18: Cal Coleman | C18: 8am-4pm | D18: gold essence | F18: =if(Clairia_Import!B33=true,"Yes!","No") -> Yes! | G18: Kovi Woundtender | H18: Danny did something very hard by giving up White Noise
A19: =if(Clairia_Import!B15=true,"Yes!","No") -> Yes! | B19: Bartleby Sprink | C19: 8-11am, 1-4pm, 6-8pm | D19: riddle for phoenix egg | F19: =if(Clairia_Import!B34=true,"Yes!","No") -> Yes! | G19: Phyllis Fieri | H19: Danny’s a nice guy and good worker but not always reliable even when he’s not using
A20: =if(Clairia_Import!B16=true,"Yes!","No") -> Yes! | B20: Ember | C20: 8am-4pm | D20: carbon key | F20: =if(Clairia_Import!B35=true,"Yes!","No") -> Yes! | G20: Huxley | H20: Danny’s a nice guy and good worker but not always reliable even when he’s not using
A21: =if(Clairia_Import!B17=true,"Yes!","No") -> Yes! | B21: Court of Mirrors | C21: 4-8pm | D21: favor | F21: =if(Clairia_Import!B36=true,"Yes!","No") -> No | G21: Dramina | H21: Theater was built by Aria’s great-grandfather and his wife and was closed for 24 years before Aria | I21: Need 2 | J21: =COUNTif(F21:F23,"Yes!") -> 1
A22: =if(Clairia_Import!B18=true,"Yes!","No") -> No | B22: Adina Valerius | C22: Penultimate: 10 am | D22: silver snowflake amulets | F22: =if(Clairia_Import!B37=true,"Yes!","No") -> No | G22: Diesel | H22: Rumors of ghosts at theater, and had a feeling of being watched
A23: =if(Clairia_Import!B19=true,"Yes!","No") -> No | B23: Staff of Ignatius | C23: 10:15 Sunday | D23: the staff! | F23: =if(Clairia_Import!B38=true,"Yes!","No") -> Yes! | G23: Celeste Wilde | H23: Theater was famous, and famously haunted by Aria’s legendary great grandparents
A24: =If(Dashboard!$M4=TRUE,"Yes!","No") -> No | B24: riddle item found? | C24: -- | D24: -- | F24: =if(Clairia_Import!B39=true,"Yes!","No") -> Yes! | G24: Pascal Valerius | H24: Overheard Aria firing Danny LOUDLY on Thursday, but Danny didn’t seem angry | I24: Need 1 | J24: =COUNTif(F24:F25,"Yes!") -> 1
F25: =if(Clairia_Import!B40=true,"Yes!","No") -> No | G25: Cary Montalvo | H25: Overheard Aria firing Danny on Thursday but Danny didn’t seem angry
A26: COMMENTS | F26: =if(Clairia_Import!B41=true,"Yes!","No") -> Yes! | G26: Samuelson | H26: Danny is druggie and lowlife, and his burning down the theater was predictable | I26: Need 1 | J26: =COUNTif(F26:F27,"Yes!") -> 1
A27: =IFERROR(__xludf.DUMMYFUNCTION("IFERROR( FILTER( FLATTEN({Clairia_Import!C5:C20; Clairia_Import!C24:C52; Clairia_Import!A55:A79}), FLATTEN({Clairia_Import!C5:C20; Clairia_Import!C24:C52; Clairia_Import!A55:A79}) <> """" ), """" )"),"Didn't talk long, but they were really nice. - ZT") -> Didn't talk long, but they were really nice. - ZT | F27: =if(Clairia_Import!B42=true,"Yes!","No") -> No | G27: Vernon Gill | H27: Danny is druggie and lowlife and burned the theater down when he got fired
A28: =IFERROR(__xludf.DUMMYFUNCTION("""COMPUTED_VALUE"""),"Very fun. They are interested in the Cary/belle story. Are a bit skittish, they avoided combat with the skeever group with ranger pathwalk, and were pretty proud of themselves") -> Very fun. They are interested in the Cary/belle story. Are a bit skittish, they avoided combat with the skeever group with ranger pathwalk, and were pretty proud of themselves | F28: =if(Clairia_Import!B43=true,"Yes!","No") -> Yes! | G28: Crabtree | H28: Danny was kind and helpful | I28: Need 1
A29: =IFERROR(__xludf.DUMMYFUNCTION("""COMPUTED_VALUE"""),"Fun group! They were very interested in the items (2 people wrote down where to find them) and they asked a lot of questions about Poppy and the portal") -> Fun group! They were very interested in the items (2 people wrote down where to find them) and they asked a lot of questions about Poppy and the portal | F29: =if(Clairia_Import!B44=true,"Yes!","No") -> No | G29: Bracken | H29: Danny was kind and helpful, wouldn’t have set the fire on purpose | J29: =COUNTif(F29:F35,"Yes!") -> 3
A30: =IFERROR(__xludf.DUMMYFUNCTION("""COMPUTED_VALUE"""),"Box checked by Rob.") -> Box checked by Rob. | F30: =if(Clairia_Import!B45=true,"Yes!","No") -> No | G30: Mick Peacock | H30: White Noise causes bloodshot eyes and headache the next day, but Danny didn’t show these Friday morning | I30: Need | J30: =COUNTif(F30,"Yes!") -> 0
A31: =IFERROR(__xludf.DUMMYFUNCTION("""COMPUTED_VALUE"""),"Great group, Medical issue with Traveler addressed. More detail in notes. (jen P)") -> Great group, Medical issue with Traveler addressed. More detail in notes. (jen P) | F31: =if(Clairia_Import!B46=true,"Yes!","No") -> Yes! | G31: Brimstone | H31: Apologizes for taking away everyone’s memories of Thursday night; spell worked on ALL LIVING CREATURES
A32: =IFERROR(__xludf.DUMMYFUNCTION("""COMPUTED_VALUE"""),"Chased them down to the tavern, but they got the heart during dinner") -> Chased them down to the tavern, but they got the heart during dinner | F32: =if(Clairia_Import!B47=true,"Yes!","No") -> Yes! | G32: Malachi | H32: Malachi hid a small stash of White Noise for Danny when he decided to go clean last winter- he checked it recently and it was all still there | I32: Need | J32: =COUNTif(F32,"Yes!") -> 1
A33: =IFERROR(__xludf.DUMMYFUNCTION("""COMPUTED_VALUE"""),"some party dynamics roughness, but they made solid progress - PSC") -> some party dynamics roughness, but they made solid progress - PSC | F33: =if(Dashboard!G4=true,"Yes!","No") -> Yes! | G33: Keeper’s Sunday Vision | H33: Vision shows both the ghosts of the Morg and Honoré’s letter to Aria, both of which are faded but have important messages for Clairia | I33: Need | J33: =COUNTif(F33,"Yes!") -> 1
A34: =IFERROR(__xludf.DUMMYFUNCTION("""COMPUTED_VALUE"""),"Oz: Tentative group at first, but warmed up quickly. Good job on observation challenge. Gave gold essence.") -> Oz: Tentative group at first, but warmed up quickly. Good job on observation challenge. Gave gold essence. | F34: =if(Clairia_Import!B49=true,"Yes!","No") -> No | G34: Mila | H34: Recognizes them from her vision; leaves to ponder | I34: Need | J34: =COUNTif(F34,"Yes!") -> 0
A35: =IFERROR(__xludf.DUMMYFUNCTION("""COMPUTED_VALUE"""),"Got it off a bridesmaid corpse. Not sure they really solved the vision but I wasn't going to be out again & it was a good fight. Recognized what it was immediately.") -> Got it off a bridesmaid corpse. Not sure they really solved the vision but I wasn't going to be out again & it was a good fight. Recognized what it was immediately. | F35: =if(Clairia_Import!B50=true,"Yes!","No") -> No | G35: Mila, Ghosts Of Montgomery Morgan, Delia Morgan, Horatio Morgan, Veena Morgan | H35: Leads party to ghosts’ reenactment of Aria’s knocking over candle and Danny saving her | I35: Need | J35: =COUNTif(F35,"Yes!") -> 0
A36: =IFERROR(__xludf.DUMMYFUNCTION("""COMPUTED_VALUE"""),"Had a great connection with them Friday night at Valerius House to prepare for delivering charge on Saturday") -> Had a great connection with them Friday night at Valerius House to prepare for delivering charge on Saturday | F36: =if(Clairia_Import!B51=true,"Yes!","No") -> No | G36: Aria Morgan | H36: Party tells Aria what they have learned from the ghosts. She is disbelieving at first but after the Spun Sugar dance reference and when she sees the soaked letter from Honore, she understands that she started the fire and Danny saved her. | I36: Need | J36: =COUNTif(F36,"Yes!") -> 0
A37: =IFERROR(__xludf.DUMMYFUNCTION("""COMPUTED_VALUE"""),"Sat 12:15pm- party approached Aria by the lake (they were looking for her), ARia told story w/Phyllis' help- told them not to trust DD, explained timeline, Baron's letter, DD isn't trustworthy. FULL party engaged, asked if they could help investigate befo"&"re lunch even started. They seem invested. DG") -> Sat 12:15pm- party approached Aria by the lake (they were looking for her), ARia told story w/Phyllis' help- told them not to trust DD, explained timeline, Baron's letter, DD isn't trustworthy. FULL party engaged, asked if they could help investigate before lunch even started. They seem invested. DG | F37: =if(Clairia_Import!B52=true,"Yes!","No") -> No | G37: Moxie | H37: Danny didn’t accidentally or purposefully set this fire; Aria’s accidental knocking over a candle did. Aria’s still alive because Danny heard her screams and ran inside to save her. “Every living soul” in World’s Edge has forgotten what happened on Thursday night, but the ghosts who haunt the Morg saw everything, and they remember. | I37: Need | J37: =COUNTif(F37,"Yes!") -> 0
A38: =IFERROR(__xludf.DUMMYFUNCTION("""COMPUTED_VALUE"""),"Gave them the full story after they brought up the fire. They were sympathetic and suggested maybe i had gone into the fire to save someone and thats why I was sooty.") -> Gave them the full story after they brought up the fire. They were sympathetic and suggested maybe i had gone into the fire to save someone and thats why I was sooty.
A39: =IFERROR(__xludf.DUMMYFUNCTION("""COMPUTED_VALUE"""),"Got to them at breakfast. Only blue haired participant was interested in speaking with me, but we talked for a good 5 minutes in detail. She said that I gave them useful information. Hopefully she shares it with the rest of them.") -> Got to them at breakfast. Only blue haired participant was interested in speaking with me, but we talked for a good 5 minutes in detail. She said that I gave them useful information. Hopefully she shares it with the rest of them.
A40: =IFERROR(__xludf.DUMMYFUNCTION("""COMPUTED_VALUE"""),"Had a great conversation with them, seemed excited about singing. Promised to teach us a song ""My Little Yeti""") -> Had a great conversation with them, seemed excited about singing. Promised to teach us a song "My Little Yeti"
A41: =IFERROR(__xludf.DUMMYFUNCTION("""COMPUTED_VALUE"""),"talked to two of them in front of the tavern. they had been going to investigate tavern but it had turned into ghost theater. Knew already that Danny had been clean for over 200 days. Interested. 4:50") -> talked to two of them in front of the tavern. they had been going to investigate tavern but it had turned into ghost theater. Knew already that Danny had been clean for over 200 days. Interested. 4:50
A42: =IFERROR(__xludf.DUMMYFUNCTION("""COMPUTED_VALUE"""),"Full party interaction with Aria Morgan, discussing the Morg and Danny Donovan's recent work there. Mentioned his history with white noise and how unreliable he was. Definitely lanfded wlll with the party.") -> Full party interaction with Aria Morgan, discussing the Morg and Danny Donovan's recent work there. Mentioned his history with white noise and how unreliable he was. Definitely lanfded wlll with the party.
A43: =IFERROR(__xludf.DUMMYFUNCTION("""COMPUTED_VALUE"""),"Talked to them at lunch about Danny. Didn't seem engaged, but at least one nodded. -EF") -> Talked to them at lunch about Danny. Didn't seem engaged, but at least one nodded. -EF
A44: =IFERROR(__xludf.DUMMYFUNCTION("""COMPUTED_VALUE"""),"Talked to them in front of tavern about how tragic it was for ghost theater to burn down before I arrived on Fri morning, and how it looked different now (Sat after 4:30pm) - EL") -> Talked to them in front of tavern about how tragic it was for ghost theater to burn down before I arrived on Fri morning, and how it looked different now (Sat after 4:30pm) - EL
A45: =IFERROR(__xludf.DUMMYFUNCTION("""COMPUTED_VALUE"""),"Interested in the charge, Think Aria kinda sucks (for firing danny)") -> Interested in the charge, Think Aria kinda sucks (for firing danny)
A46: =IFERROR(__xludf.DUMMYFUNCTION("""COMPUTED_VALUE"""),"Talked to Yara (Keeper). Told her to watch her sleeves over the candles. Don't want to pull a Danny Donnovan") -> Talked to Yara (Keeper). Told her to watch her sleeves over the candles. Don't want to pull a Danny Donnovan
A47: =IFERROR(__xludf.DUMMYFUNCTION("""COMPUTED_VALUE"""),"Sat on the way to Soul Speaking, spoke about DD helping Crabtree to bring in heavy boxes, history of pain, white noise, heart of gold. the party said that they also have the feeling that he's a kind person and does his best - MO") -> Sat on the way to Soul Speaking, spoke about DD helping Crabtree to bring in heavy boxes, history of pain, white noise, heart of gold. the party said that they also have the feeling that he's a kind person and does his best - MO
A48: =IFERROR(__xludf.DUMMYFUNCTION("""COMPUTED_VALUE"""),"Totally got it, they were literally talking to themself ""oh, maybe ghosts would know?"" - ZT") -> Totally got it, they were literally talking to themself "oh, maybe ghosts would know?" - ZT
A49: =IFERROR(__xludf.DUMMYFUNCTION("""COMPUTED_VALUE"""),"Had a wonderful conversation with them right when they came back from the ritual. They're on it!") -> Had a wonderful conversation with them right when they came back from the ritual. They're on it!
A50: =IFERROR(__xludf.DUMMYFUNCTION("""COMPUTED_VALUE"""),"accidentally told Claria my Arden clue info about SWV finding crown of St Mora… Sat. Breakfast M.O.") -> accidentally told Claria my Arden clue info about SWV finding crown of St Mora… Sat. Breakfast M.O.
A51: =IFERROR(__xludf.DUMMYFUNCTION("""COMPUTED_VALUE"""),"party photo taken -Mirin") -> party photo taken -Mirin
A52: =IFERROR(__xludf.DUMMYFUNCTION("""COMPUTED_VALUE"""),"one almost died battling skeevers - keeper used heal all wounds to save him. ") -> one almost died battling skeevers - keeper used heal all wounds to save him.
A53: =IFERROR(__xludf.DUMMYFUNCTION("""COMPUTED_VALUE"""),"Not good communication before Chitter fight. Spent 5 min planning and then Chitters were rushed by Uri Kesh. Feels like the party is still feeling each other out Sat 11am. -HA") -> Not good communication before Chitter fight. Spent 5 min planning and then Chitters were rushed by Uri Kesh. Feels like the party is still feeling each other out Sat 11am. -HA
A54: =IFERROR(__xludf.DUMMYFUNCTION("""COMPUTED_VALUE"""),"Traveler has a knee issue (pre-Otherworld) so Pascal got her a walking stick and we gave her Tylenol. She was reluctant to slow her group down. We had a good talk, she is feeling better about it. She will get a knee brace from Britt when they get to the t"&"avern. (Jen P)") -> Traveler has a knee issue (pre-Otherworld) so Pascal got her a walking stick and we gave her Tylenol. She was reluctant to slow her group down. We had a good talk, she is feeling better about it. She will get a knee brace from Britt when they get to the tavern. (Jen P)
A55: =IFERROR(__xludf.DUMMYFUNCTION("""COMPUTED_VALUE"""),"Party visit to Peacocks was split between 2 people who wanted to stay and sing forever, 2 people trying to figure shit out, and 2 people (a couple? She's the traveler) who seemed very removed and disengaged. -JF") -> Party visit to Peacocks was split between 2 people who wanted to stay and sing forever, 2 people trying to figure shit out, and 2 people (a couple? She's the traveler) who seemed very removed and disengaged. -JF
A56: =IFERROR(__xludf.DUMMYFUNCTION("""COMPUTED_VALUE"""),"Party was a bit hesitant about combat, but after sparring at the Valerius house, they are feeling much more confident. They have better communication, the caster is really blowing her whistle and projecting her spells, the keeper learned how to use her sh"&"ield and is feeling much more confident. JM") -> Party was a bit hesitant about combat, but after sparring at the Valerius house, they are feeling much more confident. They have better communication, the caster is really blowing her whistle and projecting her spells, the keeper learned how to use her shield and is feeling much more confident. JM
A57: =IFERROR(__xludf.DUMMYFUNCTION("""COMPUTED_VALUE"""),"Isaiah Cooke golden page story told to half the party") -> Isaiah Cooke golden page story told to half the party
A58: =IFERROR(__xludf.DUMMYFUNCTION("""COMPUTED_VALUE"""),"3:30 pm Sat - Claria only has three people. 1 is napping, 1 has a knee injury, one is keeping that person company. - KK (remove highlight when seen)") -> 3:30 pm Sat - Claria only has three people. 1 is napping, 1 has a knee injury, one is keeping that person company. - KK (remove highlight when seen)
A59: =IFERROR(__xludf.DUMMYFUNCTION("""COMPUTED_VALUE"""),"Post Lunch Saturday they seemed VERY invested in the Danny Donovan Charge") -> Post Lunch Saturday they seemed VERY invested in the Danny Donovan Charge
A60: =IFERROR(__xludf.DUMMYFUNCTION("""COMPUTED_VALUE"""),"5pm Sat - Claria companion returned to basement a riddle/bag that they had found. Handed to Jodi - EL") -> 5pm Sat - Claria companion returned to basement a riddle/bag that they had found. Handed to Jodi - EL

Sheet Arden_Import
A1: =IFERROR(__xludf.DUMMYFUNCTION("IMPORTRANGE(""https://docs.google.com/spreadsheets/d/1PPFix0KE5FV0_ekB8X93l4fBTTlhI3_4FnP7klgfg_Y/edit?gid=0#gid=0"", ""Arden!a1:f100"")"),"ARDEN") -> ARDEN | C1: =IFERROR(__xludf.DUMMYFUNCTION("""COMPUTED_VALUE"""),"Ari (Chelsea Hadlock)") -> Ari (Chelsea Hadlock)
E2: =IFERROR(__xludf.DUMMYFUNCTION("""COMPUTED_VALUE"""),"Caster") -> Caster | F2: =IFERROR(__xludf.DUMMYFUNCTION("""COMPUTED_VALUE"""),"Starling; flower earrings") -> Starling; flower earrings
A3: =IFERROR(__xludf.DUMMYFUNCTION("""COMPUTED_VALUE"""),"PARTY PATH") -> PARTY PATH | E3: =IFERROR(__xludf.DUMMYFUNCTION("""COMPUTED_VALUE"""),"Keeper") -> Keeper | F3: =IFERROR(__xludf.DUMMYFUNCTION("""COMPUTED_VALUE"""),"Von Haggen; black Arden cloak") -> Von Haggen; black Arden cloak
A4: =IFERROR(__xludf.DUMMYFUNCTION("""COMPUTED_VALUE"""),"Character") -> Character | B4: =IFERROR(__xludf.DUMMYFUNCTION("""COMPUTED_VALUE"""),"Gave Item/Info") -> Gave Item/Info | C4: =IFERROR(__xludf.DUMMYFUNCTION("""COMPUTED_VALUE"""),"Notes") -> Notes | E4: =IFERROR(__xludf.DUMMYFUNCTION("""COMPUTED_VALUE"""),"Maker") -> Maker | F4: =IFERROR(__xludf.DUMMYFUNCTION("""COMPUTED_VALUE"""),"Willow; black vest, green skirt") -> Willow; black vest, green skirt
A5: =IFERROR(__xludf.DUMMYFUNCTION("""COMPUTED_VALUE"""),"Aria Morgan") -> Aria Morgan | B5: =IFERROR(__xludf.DUMMYFUNCTION("""COMPUTED_VALUE"""),TRUE) -> TRUE | C5: =IFERROR(__xludf.DUMMYFUNCTION("""COMPUTED_VALUE"""),"Spoke with Birdie, Starling, & Willow- discussed Memory Lapse from last night, theater burning, and Golden Page/Nemaiah. Party was ""hesitant to trust others"" but they opened up after some conversation. Introduced to Ursula. DG") -> Spoke with Birdie, Starling, & Willow- discussed Memory Lapse from last night, theater burning, and Golden Page/Nemaiah. Party was "hesitant to trust others" but they opened up after some conversation. Introduced to Ursula. DG | E5: =IFERROR(__xludf.DUMMYFUNCTION("""COMPUTED_VALUE"""),"Ranger") -> Ranger | F5: =IFERROR(__xludf.DUMMYFUNCTION("""COMPUTED_VALUE"""),"Erebadan; brown hat, long hair") -> Erebadan; brown hat, long hair
A6: =IFERROR(__xludf.DUMMYFUNCTION("""COMPUTED_VALUE"""),"Ursula Smirch") -> Ursula Smirch | B6: =IFERROR(__xludf.DUMMYFUNCTION("""COMPUTED_VALUE"""),TRUE) -> TRUE | E6: =IFERROR(__xludf.DUMMYFUNCTION("""COMPUTED_VALUE"""),"Seeker") -> Seeker | F6: =IFERROR(__xludf.DUMMYFUNCTION("""COMPUTED_VALUE"""),"Kestra; tabard, brown sweater") -> Kestra; tabard, brown sweater
A7: =IFERROR(__xludf.DUMMYFUNCTION("""COMPUTED_VALUE"""),"Nix Valerius") -> Nix Valerius | B7: =IFERROR(__xludf.DUMMYFUNCTION("""COMPUTED_VALUE"""),FALSE) -> FALSE | E7: =IFERROR(__xludf.DUMMYFUNCTION("""COMPUTED_VALUE"""),"Traveler") -> Traveler | F7: =IFERROR(__xludf.DUMMYFUNCTION("""COMPUTED_VALUE"""),"Birdie; light green poofie shirt") -> Birdie; light green poofie shirt
A8: =IFERROR(__xludf.DUMMYFUNCTION("""COMPUTED_VALUE"""),"Isaiah Cooke") -> Isaiah Cooke | B8: =IFERROR(__xludf.DUMMYFUNCTION("""COMPUTED_VALUE"""),TRUE) -> TRUE | C8: =IFERROR(__xludf.DUMMYFUNCTION("""COMPUTED_VALUE"""),"Gave them the list Friday night (sorry, put in the wrong cell)") -> Gave them the list Friday night (sorry, put in the wrong cell)
A9: =IFERROR(__xludf.DUMMYFUNCTION("""COMPUTED_VALUE"""),"Kiko Truthspeaker") -> Kiko Truthspeaker | B9: =IFERROR(__xludf.DUMMYFUNCTION("""COMPUTED_VALUE"""),TRUE) -> TRUE | C9: =IFERROR(__xludf.DUMMYFUNCTION("""COMPUTED_VALUE"""),"Traveler had not shared the list with the group, got her to share lore, and some of the list, but fewer people heard that. 10:30.") -> Traveler had not shared the list with the group, got her to share lore, and some of the list, but fewer people heard that. 10:30.
A10: =IFERROR(__xludf.DUMMYFUNCTION("""COMPUTED_VALUE"""),"Buzzkill (Don't Give Item)") -> Buzzkill (Don't Give Item) | B10: =IFERROR(__xludf.DUMMYFUNCTION("""COMPUTED_VALUE"""),TRUE) -> TRUE | C10: =IFERROR(__xludf.DUMMYFUNCTION("""COMPUTED_VALUE"""),"Did challenge with them, will give on Sunday at the coordinator's leisure (AS)") -> Did challenge with them, will give on Sunday at the coordinator's leisure (AS)
A11: =IFERROR(__xludf.DUMMYFUNCTION("""COMPUTED_VALUE"""),"Pascal Valerius") -> Pascal Valerius | B11: =IFERROR(__xludf.DUMMYFUNCTION("""COMPUTED_VALUE"""),TRUE) -> TRUE
A12: =IFERROR(__xludf.DUMMYFUNCTION("""COMPUTED_VALUE"""),"Karmin Smirch") -> Karmin Smirch | B12: =IFERROR(__xludf.DUMMYFUNCTION("""COMPUTED_VALUE"""),TRUE) -> TRUE | C12: =IFERROR(__xludf.DUMMYFUNCTION("""COMPUTED_VALUE"""),"Finished the jingle challenge with them at 4pm on Saturday. I'm sure nothing horrible happened right as I walked away. -DaveKamin") -> Finished the jingle challenge with them at 4pm on Saturday. I'm sure nothing horrible happened right as I walked away. -DaveKamin
A13: =IFERROR(__xludf.DUMMYFUNCTION("""COMPUTED_VALUE"""),"Valentina") -> Valentina | B13: =IFERROR(__xludf.DUMMYFUNCTION("""COMPUTED_VALUE"""),TRUE) -> TRUE
A14: =IFERROR(__xludf.DUMMYFUNCTION("""COMPUTED_VALUE"""),"Charlie Peacock") -> Charlie Peacock | B14: =IFERROR(__xludf.DUMMYFUNCTION("""COMPUTED_VALUE"""),TRUE) -> TRUE | C14: =IFERROR(__xludf.DUMMYFUNCTION("""COMPUTED_VALUE"""),"Switched to pitch pipe challenge and did it in front of tavern after their ghost theater in Charlie's absence. -JF") -> Switched to pitch pipe challenge and did it in front of tavern after their ghost theater in Charlie's absence. -JF
A15: =IFERROR(__xludf.DUMMYFUNCTION("""COMPUTED_VALUE"""),"Moxie (or any Warband)") -> Moxie (or any Warband) | B15: =IFERROR(__xludf.DUMMYFUNCTION("""COMPUTED_VALUE"""),TRUE) -> TRUE | C15: =IFERROR(__xludf.DUMMYFUNCTION("""COMPUTED_VALUE"""),"Found them at 6pm. Petulantly threw the stupid riddle at them. -LN") -> Found them at 6pm. Petulantly threw the stupid riddle at them. -LN
A16: =IFERROR(__xludf.DUMMYFUNCTION("""COMPUTED_VALUE"""),"Obsidian") -> Obsidian | B16: =IFERROR(__xludf.DUMMYFUNCTION("""COMPUTED_VALUE"""),TRUE) -> TRUE
A17: =IFERROR(__xludf.DUMMYFUNCTION("""COMPUTED_VALUE"""),"Ghost Theater") -> Ghost Theater | B17: =IFERROR(__xludf.DUMMYFUNCTION("""COMPUTED_VALUE"""),TRUE) -> TRUE | C17: =IFERROR(__xludf.DUMMYFUNCTION("""COMPUTED_VALUE"""),"Did a bit of a ""who cares speedrun"" but had a good experience. -Dave Nadig") -> Did a bit of a "who cares speedrun" but had a good experience. -Dave Nadig | D17: =IFERROR(__xludf.DUMMYFUNCTION("""COMPUTED_VALUE"""),"Fri PM- Aria showed them Golden Page, and explained ""theater belongs to the ghosts now"" DG") -> Fri PM- Aria showed them Golden Page, and explained "theater belongs to the ghosts now" DG
A18: =IFERROR(__xludf.DUMMYFUNCTION("""COMPUTED_VALUE"""),"Buzzkill (Sunday)") -> Buzzkill (Sunday) | B18: =IFERROR(__xludf.DUMMYFUNCTION("""COMPUTED_VALUE"""),FALSE) -> FALSE
A19: =IFERROR(__xludf.DUMMYFUNCTION("""COMPUTED_VALUE"""),"Morgoth & Henchmen") -> Morgoth & Henchmen | B19: =IFERROR(__xludf.DUMMYFUNCTION("""COMPUTED_VALUE"""),FALSE) -> FALSE
A22: =IFERROR(__xludf.DUMMYFUNCTION("""COMPUTED_VALUE"""),"CHARGE INFO") -> CHARGE INFO | B22: =IFERROR(__xludf.DUMMYFUNCTION("""COMPUTED_VALUE"""),"(Bracken)") -> (Bracken)
A23: =IFERROR(__xludf.DUMMYFUNCTION("""COMPUTED_VALUE"""),"Character") -> Character | B23: =IFERROR(__xludf.DUMMYFUNCTION("""COMPUTED_VALUE"""),"Gave Info") -> Gave Info | C23: =IFERROR(__xludf.DUMMYFUNCTION("""COMPUTED_VALUE"""),"Notes") -> Notes
A24: =IFERROR(__xludf.DUMMYFUNCTION("""COMPUTED_VALUE"""),"Angelica Sprink") -> Angelica Sprink | B24: =IFERROR(__xludf.DUMMYFUNCTION("""COMPUTED_VALUE"""),TRUE) -> TRUE | C24: =IFERROR(__xludf.DUMMYFUNCTION("""COMPUTED_VALUE"""),"Met them in preperation to assign charge LD, assigned charge with a side of tears and teenage angst.") -> Met them in preperation to assign charge LD, assigned charge with a side of tears and teenage angst.
A25: =IFERROR(__xludf.DUMMYFUNCTION("""COMPUTED_VALUE"""),"Geneva Sprink") -> Geneva Sprink | B25: =IFERROR(__xludf.DUMMYFUNCTION("""COMPUTED_VALUE"""),TRUE) -> TRUE | C25: =IFERROR(__xludf.DUMMYFUNCTION("""COMPUTED_VALUE"""),"Did not directly approach but sat next to them at lunch and was told they already fully understood charge from overhearing Angelica and Geneva fight and not to clue hammer any more ") -> Did not directly approach but sat next to them at lunch and was told they already fully understood charge from overhearing Angelica and Geneva fight and not to clue hammer any more
A26: =IFERROR(__xludf.DUMMYFUNCTION("""COMPUTED_VALUE"""),"Bartleby Sprink") -> Bartleby Sprink | B26: =IFERROR(__xludf.DUMMYFUNCTION("""COMPUTED_VALUE"""),TRUE) -> TRUE
A27: =IFERROR(__xludf.DUMMYFUNCTION("""COMPUTED_VALUE"""),"Lenora Graves") -> Lenora Graves | B27: =IFERROR(__xludf.DUMMYFUNCTION("""COMPUTED_VALUE"""),FALSE) -> FALSE | C27: =IFERROR(__xludf.DUMMYFUNCTION("""COMPUTED_VALUE"""),"Was told they already had info they needed, not to clue hammer them") -> Was told they already had info they needed, not to clue hammer them
A28: =IFERROR(__xludf.DUMMYFUNCTION("""COMPUTED_VALUE"""),"Kyson Wayseeker") -> Kyson Wayseeker | B28: =IFERROR(__xludf.DUMMYFUNCTION("""COMPUTED_VALUE"""),FALSE) -> FALSE
A29: =IFERROR(__xludf.DUMMYFUNCTION("""COMPUTED_VALUE"""),"Samuelson") -> Samuelson | B29: =IFERROR(__xludf.DUMMYFUNCTION("""COMPUTED_VALUE"""),TRUE) -> TRUE | C29: =IFERROR(__xludf.DUMMYFUNCTION("""COMPUTED_VALUE"""),"Talked to woman in light green shirt. Two others listened.") -> Talked to woman in light green shirt. Two others listened.
A30: =IFERROR(__xludf.DUMMYFUNCTION("""COMPUTED_VALUE"""),"Pansy Golden") -> Pansy Golden | B30: =IFERROR(__xludf.DUMMYFUNCTION("""COMPUTED_VALUE"""),TRUE) -> TRUE | C30: =IFERROR(__xludf.DUMMYFUNCTION("""COMPUTED_VALUE"""),"Sat night during apple crisp. They asked about a Black Lamp secret society, I said I didn't know anything about that.") -> Sat night during apple crisp. They asked about a Black Lamp secret society, I said I didn't know anything about that.
A31: =IFERROR(__xludf.DUMMYFUNCTION("""COMPUTED_VALUE"""),"Kulinos") -> Kulinos | B31: =IFERROR(__xludf.DUMMYFUNCTION("""COMPUTED_VALUE"""),TRUE) -> TRUE
A32: =IFERROR(__xludf.DUMMYFUNCTION("""COMPUTED_VALUE"""),"Aleeya Witchborn") -> Aleeya Witchborn | B32: =IFERROR(__xludf.DUMMYFUNCTION("""COMPUTED_VALUE"""),TRUE) -> TRUE | C32: =IFERROR(__xludf.DUMMYFUNCTION("""COMPUTED_VALUE"""),"Slipped the info in as a natural aside at breakfast to two participants on the periphery just after they spoke with Samuelson about Angelica, and before Bartleby came over to them. Very interested. ") -> Slipped the info in as a natural aside at breakfast to two participants on the periphery just after they spoke with Samuelson about Angelica, and before Bartleby came over to them. Very interested.
A33: =IFERROR(__xludf.DUMMYFUNCTION("""COMPUTED_VALUE"""),"Karla Smirch") -> Karla Smirch | B33: =IFERROR(__xludf.DUMMYFUNCTION("""COMPUTED_VALUE"""),TRUE) -> TRUE | C33: =IFERROR(__xludf.DUMMYFUNCTION("""COMPUTED_VALUE"""),"3 of the party members were very focused on the info and then tried to teach Karla the magic of giving to help her better understand Bracken") -> 3 of the party members were very focused on the info and then tried to teach Karla the magic of giving to help her better understand Bracken
A34: =IFERROR(__xludf.DUMMYFUNCTION("""COMPUTED_VALUE"""),"Dusty Peacock") -> Dusty Peacock | B34: =IFERROR(__xludf.DUMMYFUNCTION("""COMPUTED_VALUE"""),FALSE) -> FALSE
A35: =IFERROR(__xludf.DUMMYFUNCTION("""COMPUTED_VALUE"""),"Phineas Smirch") -> Phineas Smirch | B35: =IFERROR(__xludf.DUMMYFUNCTION("""COMPUTED_VALUE"""),TRUE) -> TRUE | C35: =IFERROR(__xludf.DUMMYFUNCTION("""COMPUTED_VALUE"""),"Got asked about Bracken after ritual") -> Got asked about Bracken after ritual
A36: =IFERROR(__xludf.DUMMYFUNCTION("""COMPUTED_VALUE"""),"Equinoxious") -> Equinoxious | B36: =IFERROR(__xludf.DUMMYFUNCTION("""COMPUTED_VALUE"""),FALSE) -> FALSE
A37: =IFERROR(__xludf.DUMMYFUNCTION("""COMPUTED_VALUE"""),"Isaiah Cooke") -> Isaiah Cooke | B37: =IFERROR(__xludf.DUMMYFUNCTION("""COMPUTED_VALUE"""),TRUE) -> TRUE | C37: =IFERROR(__xludf.DUMMYFUNCTION("""COMPUTED_VALUE"""),"Gave them the location spell listing and they wrote all the ppl on it. They crushed the illiterate challenge. Invested in all parts of Otherworld already. Seemed like a great crew. Update, gave them charge info at 12:15") -> Gave them the location spell listing and they wrote all the ppl on it. They crushed the illiterate challenge. Invested in all parts of Otherworld already. Seemed like a great crew. Update, gave them charge info at 12:15
A38: =IFERROR(__xludf.DUMMYFUNCTION("""COMPUTED_VALUE"""),"Crabtree") -> Crabtree | B38: =IFERROR(__xludf.DUMMYFUNCTION("""COMPUTED_VALUE"""),TRUE) -> TRUE | C38: =IFERROR(__xludf.DUMMYFUNCTION("""COMPUTED_VALUE"""),"Gave clue info re: St Mora crown & SWV's return to Mistal; they were interested & wrote a few things down; Saturday late morning - MO") -> Gave clue info re: St Mora crown & SWV's return to Mistal; they were interested & wrote a few things down; Saturday late morning - MO
A39: =IFERROR(__xludf.DUMMYFUNCTION("""COMPUTED_VALUE"""),"Aesthetika") -> Aesthetika | B39: =IFERROR(__xludf.DUMMYFUNCTION("""COMPUTED_VALUE"""),TRUE) -> TRUE | C39: =IFERROR(__xludf.DUMMYFUNCTION("""COMPUTED_VALUE"""),"I told one woman who seemed to be listening intently. (before lunch) -TO'") -> I told one woman who seemed to be listening intently. (before lunch) -TO'
A40: =IFERROR(__xludf.DUMMYFUNCTION("""COMPUTED_VALUE"""),"Santiago Valerius") -> Santiago Valerius | B40: =IFERROR(__xludf.DUMMYFUNCTION("""COMPUTED_VALUE"""),TRUE) -> TRUE | C40: =IFERROR(__xludf.DUMMYFUNCTION("""COMPUTED_VALUE"""),"Gave the charge information to the Traveler. She asked proactively after the Crown and has been tracking Bracken and Angelica") -> Gave the charge information to the Traveler. She asked proactively after the Crown and has been tracking Bracken and Angelica
A41: =IFERROR(__xludf.DUMMYFUNCTION("""COMPUTED_VALUE"""),"Dimitri") -> Dimitri | B41: =IFERROR(__xludf.DUMMYFUNCTION("""COMPUTED_VALUE"""),TRUE) -> TRUE | C41: =IFERROR(__xludf.DUMMYFUNCTION("""COMPUTED_VALUE"""),"Seemed to know about St. Mora and be putting together with other clues. RCY. ") -> Seemed to know about St. Mora and be putting together with other clues. RCY.
A42: =IFERROR(__xludf.DUMMYFUNCTION("""COMPUTED_VALUE"""),"Fenwick Michaels") -> Fenwick Michaels | B42: =IFERROR(__xludf.DUMMYFUNCTION("""COMPUTED_VALUE"""),FALSE) -> FALSE
A43: =IFERROR(__xludf.DUMMYFUNCTION("""COMPUTED_VALUE"""),"Bracken") -> Bracken | B43: =IFERROR(__xludf.DUMMYFUNCTION("""COMPUTED_VALUE"""),TRUE) -> TRUE | C43: =IFERROR(__xludf.DUMMYFUNCTION("""COMPUTED_VALUE"""),"At least a few seem to be hard committed to helping Angelica and involved, but as far as I can tell no real knowledge of the charge or what it might mean --RS") -> At least a few seem to be hard committed to helping Angelica and involved, but as far as I can tell no real knowledge of the charge or what it might mean --RS
A44: =IFERROR(__xludf.DUMMYFUNCTION("""COMPUTED_VALUE"""),"Pearl Bryce") -> Pearl Bryce | B44: =IFERROR(__xludf.DUMMYFUNCTION("""COMPUTED_VALUE"""),TRUE) -> TRUE | C44: =IFERROR(__xludf.DUMMYFUNCTION("""COMPUTED_VALUE"""),"Told 2 memebers about the dragon seemed interested right after lunch -TB") -> Told 2 memebers about the dragon seemed interested right after lunch -TB
A45: =IFERROR(__xludf.DUMMYFUNCTION("""COMPUTED_VALUE"""),"Kora Peacekeeper") -> Kora Peacekeeper | B45: =IFERROR(__xludf.DUMMYFUNCTION("""COMPUTED_VALUE"""),TRUE) -> TRUE | C45: =IFERROR(__xludf.DUMMYFUNCTION("""COMPUTED_VALUE"""),"Two paying attention, no initial recognition of Brackens name, seemed to know at the end of the interaction. CL 10:30am") -> Two paying attention, no initial recognition of Brackens name, seemed to know at the end of the interaction. CL 10:30am
A46: =IFERROR(__xludf.DUMMYFUNCTION("""COMPUTED_VALUE"""),"Tinker Bill") -> Tinker Bill | B46: =IFERROR(__xludf.DUMMYFUNCTION("""COMPUTED_VALUE"""),TRUE) -> TRUE | C46: =IFERROR(__xludf.DUMMYFUNCTION("""COMPUTED_VALUE"""),"Coasters delivered. Made sure seveal heard my little speech. They did look to try and see the printing..") -> Coasters delivered. Made sure seveal heard my little speech. They did look to try and see the printing..
A47: =IFERROR(__xludf.DUMMYFUNCTION("""COMPUTED_VALUE"""),"Kyli Talespinner") -> Kyli Talespinner | B47: =IFERROR(__xludf.DUMMYFUNCTION("""COMPUTED_VALUE"""),TRUE) -> TRUE | C47: =IFERROR(__xludf.DUMMYFUNCTION("""COMPUTED_VALUE"""),"Gave paper in Tavern before they went to Soul Speaking. Party is very interested in helping Bracken and started trying to read the black paper under a flashlight almost right away. MG") -> Gave paper in Tavern before they went to Soul Speaking. Party is very interested in helping Bracken and started trying to read the black paper under a flashlight almost right away. MG
A48: =IFERROR(__xludf.DUMMYFUNCTION("""COMPUTED_VALUE"""),"Revelations") -> Revelations
A49: =IFERROR(__xludf.DUMMYFUNCTION("""COMPUTED_VALUE"""),"Angelica Sprink") -> Angelica Sprink | B49: =IFERROR(__xludf.DUMMYFUNCTION("""COMPUTED_VALUE"""),FALSE) -> FALSE
A50: =IFERROR(__xludf.DUMMYFUNCTION("""COMPUTED_VALUE"""),"Bracken") -> Bracken | B50: =IFERROR(__xludf.DUMMYFUNCTION("""COMPUTED_VALUE"""),FALSE) -> FALSE
A51: =IFERROR(__xludf.DUMMYFUNCTION("""COMPUTED_VALUE"""),"Karmin Smirch") -> Karmin Smirch | B51: =IFERROR(__xludf.DUMMYFUNCTION("""COMPUTED_VALUE"""),FALSE) -> FALSE
A52: =IFERROR(__xludf.DUMMYFUNCTION("""COMPUTED_VALUE"""),"Adina Valerius") -> Adina Valerius | B52: =IFERROR(__xludf.DUMMYFUNCTION("""COMPUTED_VALUE"""),FALSE) -> FALSE
A54: =IFERROR(__xludf.DUMMYFUNCTION("""COMPUTED_VALUE"""),"GENERAL NOTES") -> GENERAL NOTES
A55: =IFERROR(__xludf.DUMMYFUNCTION("""COMPUTED_VALUE"""),"party photo taken -Mirin") -> party photo taken -Mirin
A56: =IFERROR(__xludf.DUMMYFUNCTION("""COMPUTED_VALUE"""),"1 almost died battling skeevers, keeper used heal all hits pray") -> 1 almost died battling skeevers, keeper used heal all hits pray
A57: =IFERROR(__xludf.DUMMYFUNCTION("""COMPUTED_VALUE"""),"Told Arden about Golden Letter for Samuelson. -Mike S.") -> Told Arden about Golden Letter for Samuelson. -Mike S.
A58: =IFERROR(__xludf.DUMMYFUNCTION("""COMPUTED_VALUE"""),"They mentioned they hadn't found a chest yet and wanted to, I gave them some advice on where to find them. - ZT") -> They mentioned they hadn't found a chest yet and wanted to, I gave them some advice on where to find them. - ZT
A59: =IFERROR(__xludf.DUMMYFUNCTION("""COMPUTED_VALUE"""),"Kim told me (Ariel) that Arden found the basket of Wolven slaying (but Lance says it wont be a problem)") -> Kim told me (Ariel) that Arden found the basket of Wolven slaying (but Lance says it wont be a problem)
A60: =IFERROR(__xludf.DUMMYFUNCTION("""COMPUTED_VALUE"""),"The woman with the short blond hair is collecting leaves and other examples of the local fauna to bring back to Arden for study. She gave me (Baroness Adina) a leaf from Arden to remind me of my home. She is awesome!") -> The woman with the short blond hair is collecting leaves and other examples of the local fauna to bring back to Arden for study. She gave me (Baroness Adina) a leaf from Arden to remind me of my home. She is awesome!
A61: =IFERROR(__xludf.DUMMYFUNCTION("""COMPUTED_VALUE"""),"very good fighters, good coordination ") -> very good fighters, good coordination
A62: =IFERROR(__xludf.DUMMYFUNCTION("""COMPUTED_VALUE"""),"Maker is a really strong individual fighter; overall group combat is strong - Neal D. 1pm Sat") -> Maker is a really strong individual fighter; overall group combat is strong - Neal D. 1pm Sat
A63: =IFERROR(__xludf.DUMMYFUNCTION("""COMPUTED_VALUE"""),"Backing off trial drama, companion told Rowan who told me (Lane) that they are completly trial locked in and not to item focused. 1:44 pm") -> Backing off trial drama, companion told Rowan who told me (Lane) that they are completly trial locked in and not to item focused. 1:44 pm
A64: =IFERROR(__xludf.DUMMYFUNCTION("""COMPUTED_VALUE"""),"Have golden page info re: Obsidian-Abigail") -> Have golden page info re: Obsidian-Abigail

Sheet Clairia_Import
A1: =IFERROR(__xludf.DUMMYFUNCTION("IMPORTRANGE(""https://docs.google.com/spreadsheets/d/1PPFix0KE5FV0_ekB8X93l4fBTTlhI3_4FnP7klgfg_Y/edit?gid=0#gid=0"", ""Clairia!a1:f100"")"),"CLAIRIA") -> CLAIRIA | C1: =IFERROR(__xludf.DUMMYFUNCTION("""COMPUTED_VALUE"""),"Clementine (Britt Rothauser)") -> Clementine (Britt Rothauser)
E2: =IFERROR(__xludf.DUMMYFUNCTION("""COMPUTED_VALUE"""),"Caster") -> Caster | F2: =IFERROR(__xludf.DUMMYFUNCTION("""COMPUTED_VALUE"""),"Bedelia Schnee; white tabard, blue cloak") -> Bedelia Schnee; white tabard, blue cloak
A3: =IFERROR(__xludf.DUMMYFUNCTION("""COMPUTED_VALUE"""),"PARTY PATH") -> PARTY PATH | E3: =IFERROR(__xludf.DUMMYFUNCTION("""COMPUTED_VALUE"""),"Keeper") -> Keeper | F3: =IFERROR(__xludf.DUMMYFUNCTION("""COMPUTED_VALUE"""),"Yara; fur collar") -> Yara; fur collar
A4: =IFERROR(__xludf.DUMMYFUNCTION("""COMPUTED_VALUE"""),"Character") -> Character | B4: =IFERROR(__xludf.DUMMYFUNCTION("""COMPUTED_VALUE"""),"Gave Item/Info") -> Gave Item/Info | C4: =IFERROR(__xludf.DUMMYFUNCTION("""COMPUTED_VALUE"""),"Notes") -> Notes | E4: =IFERROR(__xludf.DUMMYFUNCTION("""COMPUTED_VALUE"""),"Maker") -> Maker | F4: =IFERROR(__xludf.DUMMYFUNCTION("""COMPUTED_VALUE"""),"Tearsay; white dress") -> Tearsay; white dress
A5: =IFERROR(__xludf.DUMMYFUNCTION("""COMPUTED_VALUE"""),"Moxie") -> Moxie | B5: =IFERROR(__xludf.DUMMYFUNCTION("""COMPUTED_VALUE"""),FALSE) -> FALSE | E5: =IFERROR(__xludf.DUMMYFUNCTION("""COMPUTED_VALUE"""),"Ranger") -> Ranger | F5: =IFERROR(__xludf.DUMMYFUNCTION("""COMPUTED_VALUE"""),"Feist") -> Feist
A6: =IFERROR(__xludf.DUMMYFUNCTION("""COMPUTED_VALUE"""),"Brimstone") -> Brimstone | B6: =IFERROR(__xludf.DUMMYFUNCTION("""COMPUTED_VALUE"""),TRUE) -> TRUE | C6: =IFERROR(__xludf.DUMMYFUNCTION("""COMPUTED_VALUE"""),"Didn't talk long, but they were really nice. - ZT") -> Didn't talk long, but they were really nice. - ZT | E6: =IFERROR(__xludf.DUMMYFUNCTION("""COMPUTED_VALUE"""),"Seeker") -> Seeker | F6: =IFERROR(__xludf.DUMMYFUNCTION("""COMPUTED_VALUE"""),"Trefor; white doublet puffy sleeve") -> Trefor; white doublet puffy sleeve
A7: =IFERROR(__xludf.DUMMYFUNCTION("""COMPUTED_VALUE"""),"Pascal Valerius") -> Pascal Valerius | B7: =IFERROR(__xludf.DUMMYFUNCTION("""COMPUTED_VALUE"""),TRUE) -> TRUE | C7: =IFERROR(__xludf.DUMMYFUNCTION("""COMPUTED_VALUE"""),"Very fun. They are interested in the Cary/belle story. Are a bit skittish, they avoided combat with the skeever group with ranger pathwalk, and were pretty proud of themselves") -> Very fun. They are interested in the Cary/belle story. Are a bit skittish, they avoided combat with the skeever group with ranger pathwalk, and were pretty proud of themselves | E7: =IFERROR(__xludf.DUMMYFUNCTION("""COMPUTED_VALUE"""),"Traveler") -> Traveler | F7: =IFERROR(__xludf.DUMMYFUNCTION("""COMPUTED_VALUE"""),"Oscura; white & silver queen sleeves gown") -> Oscura; white & silver queen sleeves gown
A8: =IFERROR(__xludf.DUMMYFUNCTION("""COMPUTED_VALUE"""),"Lenora Graves") -> Lenora Graves | B8: =IFERROR(__xludf.DUMMYFUNCTION("""COMPUTED_VALUE"""),TRUE) -> TRUE | C8: =IFERROR(__xludf.DUMMYFUNCTION("""COMPUTED_VALUE"""),"Fun group! They were very interested in the items (2 people wrote down where to find them) and they asked a lot of questions about Poppy and the portal") -> Fun group! They were very interested in the items (2 people wrote down where to find them) and they asked a lot of questions about Poppy and the portal
A9: =IFERROR(__xludf.DUMMYFUNCTION("""COMPUTED_VALUE"""),"Dramina") -> Dramina | B9: =IFERROR(__xludf.DUMMYFUNCTION("""COMPUTED_VALUE"""),TRUE) -> TRUE
A10: =IFERROR(__xludf.DUMMYFUNCTION("""COMPUTED_VALUE"""),"Kyson Wayseeker") -> Kyson Wayseeker | B10: =IFERROR(__xludf.DUMMYFUNCTION("""COMPUTED_VALUE"""),TRUE) -> TRUE | C10: =IFERROR(__xludf.DUMMYFUNCTION("""COMPUTED_VALUE"""),"Box checked by Rob.") -> Box checked by Rob.
A11: =IFERROR(__xludf.DUMMYFUNCTION("""COMPUTED_VALUE"""),"Adina Valerius (Don't Give Item)") -> Adina Valerius (Don't Give Item) | B11: =IFERROR(__xludf.DUMMYFUNCTION("""COMPUTED_VALUE"""),TRUE) -> TRUE | C11: =IFERROR(__xludf.DUMMYFUNCTION("""COMPUTED_VALUE"""),"Great group, Medical issue with Traveler addressed. More detail in notes. (jen P)") -> Great group, Medical issue with Traveler addressed. More detail in notes. (jen P)
A12: =IFERROR(__xludf.DUMMYFUNCTION("""COMPUTED_VALUE"""),"Natasha") -> Natasha | B12: =IFERROR(__xludf.DUMMYFUNCTION("""COMPUTED_VALUE"""),TRUE) -> TRUE | C12: =IFERROR(__xludf.DUMMYFUNCTION("""COMPUTED_VALUE"""),"Chased them down to the tavern, but they got the heart during dinner") -> Chased them down to the tavern, but they got the heart during dinner
A13: =IFERROR(__xludf.DUMMYFUNCTION("""COMPUTED_VALUE"""),"Jack Johnson") -> Jack Johnson | B13: =IFERROR(__xludf.DUMMYFUNCTION("""COMPUTED_VALUE"""),TRUE) -> TRUE | C13: =IFERROR(__xludf.DUMMYFUNCTION("""COMPUTED_VALUE"""),"some party dynamics roughness, but they made solid progress - PSC") -> some party dynamics roughness, but they made solid progress - PSC
A14: =IFERROR(__xludf.DUMMYFUNCTION("""COMPUTED_VALUE"""),"Cal Coleman") -> Cal Coleman | B14: =IFERROR(__xludf.DUMMYFUNCTION("""COMPUTED_VALUE"""),TRUE) -> TRUE | C14: =IFERROR(__xludf.DUMMYFUNCTION("""COMPUTED_VALUE"""),"Oz: Tentative group at first, but warmed up quickly. Good job on observation challenge. Gave gold essence.") -> Oz: Tentative group at first, but warmed up quickly. Good job on observation challenge. Gave gold essence.
A15: =IFERROR(__xludf.DUMMYFUNCTION("""COMPUTED_VALUE"""),"Bartleby Sprink") -> Bartleby Sprink | B15: =IFERROR(__xludf.DUMMYFUNCTION("""COMPUTED_VALUE"""),TRUE) -> TRUE
A16: =IFERROR(__xludf.DUMMYFUNCTION("""COMPUTED_VALUE"""),"Ember") -> Ember | B16: =IFERROR(__xludf.DUMMYFUNCTION("""COMPUTED_VALUE"""),TRUE) -> TRUE | C16: =IFERROR(__xludf.DUMMYFUNCTION("""COMPUTED_VALUE"""),"Got it off a bridesmaid corpse. Not sure they really solved the vision but I wasn't going to be out again & it was a good fight. Recognized what it was immediately.") -> Got it off a bridesmaid corpse. Not sure they really solved the vision but I wasn't going to be out again & it was a good fight. Recognized what it was immediately.
A17: =IFERROR(__xludf.DUMMYFUNCTION("""COMPUTED_VALUE"""),"Court of Mirrors") -> Court of Mirrors | B17: =IFERROR(__xludf.DUMMYFUNCTION("""COMPUTED_VALUE"""),TRUE) -> TRUE
A18: =IFERROR(__xludf.DUMMYFUNCTION("""COMPUTED_VALUE"""),"Adina Valerius (Sunday)") -> Adina Valerius (Sunday) | B18: =IFERROR(__xludf.DUMMYFUNCTION("""COMPUTED_VALUE"""),FALSE) -> FALSE
A19: =IFERROR(__xludf.DUMMYFUNCTION("""COMPUTED_VALUE"""),"Staff of Ignatius") -> Staff of Ignatius | B19: =IFERROR(__xludf.DUMMYFUNCTION("""COMPUTED_VALUE"""),FALSE) -> FALSE
A22: =IFERROR(__xludf.DUMMYFUNCTION("""COMPUTED_VALUE"""),"CHARGE INFO") -> CHARGE INFO | B22: =IFERROR(__xludf.DUMMYFUNCTION("""COMPUTED_VALUE"""),"(Danny Donovan)") -> (Danny Donovan)
A23: =IFERROR(__xludf.DUMMYFUNCTION("""COMPUTED_VALUE"""),"Character") -> Character | B23: =IFERROR(__xludf.DUMMYFUNCTION("""COMPUTED_VALUE"""),"Gave Info") -> Gave Info | C23: =IFERROR(__xludf.DUMMYFUNCTION("""COMPUTED_VALUE"""),"Notes") -> Notes
A24: =IFERROR(__xludf.DUMMYFUNCTION("""COMPUTED_VALUE"""),"Honoré Valerius") -> Honoré Valerius | B24: =IFERROR(__xludf.DUMMYFUNCTION("""COMPUTED_VALUE"""),TRUE) -> TRUE | C24: =IFERROR(__xludf.DUMMYFUNCTION("""COMPUTED_VALUE"""),"Had a great connection with them Friday night at Valerius House to prepare for delivering charge on Saturday") -> Had a great connection with them Friday night at Valerius House to prepare for delivering charge on Saturday
A25: =IFERROR(__xludf.DUMMYFUNCTION("""COMPUTED_VALUE"""),"Aria Morgan") -> Aria Morgan | B25: =IFERROR(__xludf.DUMMYFUNCTION("""COMPUTED_VALUE"""),TRUE) -> TRUE | C25: =IFERROR(__xludf.DUMMYFUNCTION("""COMPUTED_VALUE"""),"Sat 12:15pm- party approached Aria by the lake (they were looking for her), ARia told story w/Phyllis' help- told them not to trust DD, explained timeline, Baron's letter, DD isn't trustworthy. FULL party engaged, asked if they could help investigate befo"&"re lunch even started. They seem invested. DG") -> Sat 12:15pm- party approached Aria by the lake (they were looking for her), ARia told story w/Phyllis' help- told them not to trust DD, explained timeline, Baron's letter, DD isn't trustworthy. FULL party engaged, asked if they could help investigate before lunch even started. They seem invested. DG
A26: =IFERROR(__xludf.DUMMYFUNCTION("""COMPUTED_VALUE"""),"Danny Donovon") -> Danny Donovon | B26: =IFERROR(__xludf.DUMMYFUNCTION("""COMPUTED_VALUE"""),TRUE) -> TRUE | C26: =IFERROR(__xludf.DUMMYFUNCTION("""COMPUTED_VALUE"""),"Gave them the full story after they brought up the fire. They were sympathetic and suggested maybe i had gone into the fire to save someone and thats why I was sooty.") -> Gave them the full story after they brought up the fire. They were sympathetic and suggested maybe i had gone into the fire to save someone and thats why I was sooty.
A27: =IFERROR(__xludf.DUMMYFUNCTION("""COMPUTED_VALUE"""),"Eugenie Bright") -> Eugenie Bright | B27: =IFERROR(__xludf.DUMMYFUNCTION("""COMPUTED_VALUE"""),FALSE) -> FALSE
A28: =IFERROR(__xludf.DUMMYFUNCTION("""COMPUTED_VALUE"""),"Ned Crochett") -> Ned Crochett | B28: =IFERROR(__xludf.DUMMYFUNCTION("""COMPUTED_VALUE"""),FALSE) -> FALSE
A29: =IFERROR(__xludf.DUMMYFUNCTION("""COMPUTED_VALUE"""),"Aleeya Witchborn") -> Aleeya Witchborn | B29: =IFERROR(__xludf.DUMMYFUNCTION("""COMPUTED_VALUE"""),TRUE) -> TRUE | C29: =IFERROR(__xludf.DUMMYFUNCTION("""COMPUTED_VALUE"""),"Got to them at breakfast. Only blue haired participant was interested in speaking with me, but we talked for a good 5 minutes in detail. She said that I gave them useful information. Hopefully she shares it with the rest of them.") -> Got to them at breakfast. Only blue haired participant was interested in speaking with me, but we talked for a good 5 minutes in detail. She said that I gave them useful information. Hopefully she shares it with the rest of them.
A30: =IFERROR(__xludf.DUMMYFUNCTION("""COMPUTED_VALUE"""),"Elliott Peacock") -> Elliott Peacock | B30: =IFERROR(__xludf.DUMMYFUNCTION("""COMPUTED_VALUE"""),TRUE) -> TRUE | C30: =IFERROR(__xludf.DUMMYFUNCTION("""COMPUTED_VALUE"""),"Had a great conversation with them, seemed excited about singing. Promised to teach us a song ""My Little Yeti""") -> Had a great conversation with them, seemed excited about singing. Promised to teach us a song "My Little Yeti"
A31: =IFERROR(__xludf.DUMMYFUNCTION("""COMPUTED_VALUE"""),"Electra") -> Electra | B31: =IFERROR(__xludf.DUMMYFUNCTION("""COMPUTED_VALUE"""),FALSE) -> FALSE
A32: =IFERROR(__xludf.DUMMYFUNCTION("""COMPUTED_VALUE"""),"Stevie Peacock") -> Stevie Peacock | B32: =IFERROR(__xludf.DUMMYFUNCTION("""COMPUTED_VALUE"""),FALSE) -> FALSE
A33: =IFERROR(__xludf.DUMMYFUNCTION("""COMPUTED_VALUE"""),"Kovi Woundtender") -> Kovi Woundtender | B33: =IFERROR(__xludf.DUMMYFUNCTION("""COMPUTED_VALUE"""),TRUE) -> TRUE | C33: =IFERROR(__xludf.DUMMYFUNCTION("""COMPUTED_VALUE"""),"talked to two of them in front of the tavern. they had been going to investigate tavern but it had turned into ghost theater. Knew already that Danny had been clean for over 200 days. Interested. 4:50") -> talked to two of them in front of the tavern. they had been going to investigate tavern but it had turned into ghost theater. Knew already that Danny had been clean for over 200 days. Interested. 4:50
A34: =IFERROR(__xludf.DUMMYFUNCTION("""COMPUTED_VALUE"""),"Phyllis Fieri") -> Phyllis Fieri | B34: =IFERROR(__xludf.DUMMYFUNCTION("""COMPUTED_VALUE"""),TRUE) -> TRUE | C34: =IFERROR(__xludf.DUMMYFUNCTION("""COMPUTED_VALUE"""),"Full party interaction with Aria Morgan, discussing the Morg and Danny Donovan's recent work there. Mentioned his history with white noise and how unreliable he was. Definitely lanfded wlll with the party.") -> Full party interaction with Aria Morgan, discussing the Morg and Danny Donovan's recent work there. Mentioned his history with white noise and how unreliable he was. Definitely lanfded wlll with the party.
A35: =IFERROR(__xludf.DUMMYFUNCTION("""COMPUTED_VALUE"""),"Huxley") -> Huxley | B35: =IFERROR(__xludf.DUMMYFUNCTION("""COMPUTED_VALUE"""),TRUE) -> TRUE | C35: =IFERROR(__xludf.DUMMYFUNCTION("""COMPUTED_VALUE"""),"Talked to them at lunch about Danny. Didn't seem engaged, but at least one nodded. -EF") -> Talked to them at lunch about Danny. Didn't seem engaged, but at least one nodded. -EF
A36: =IFERROR(__xludf.DUMMYFUNCTION("""COMPUTED_VALUE"""),"Dramina") -> Dramina | B36: =IFERROR(__xludf.DUMMYFUNCTION("""COMPUTED_VALUE"""),FALSE) -> FALSE
A37: =IFERROR(__xludf.DUMMYFUNCTION("""COMPUTED_VALUE"""),"Diesel") -> Diesel | B37: =IFERROR(__xludf.DUMMYFUNCTION("""COMPUTED_VALUE"""),FALSE) -> FALSE
A38: =IFERROR(__xludf.DUMMYFUNCTION("""COMPUTED_VALUE"""),"Celeste Wilde") -> Celeste Wilde | B38: =IFERROR(__xludf.DUMMYFUNCTION("""COMPUTED_VALUE"""),TRUE) -> TRUE | C38: =IFERROR(__xludf.DUMMYFUNCTION("""COMPUTED_VALUE"""),"Talked to them in front of tavern about how tragic it was for ghost theater to burn down before I arrived on Fri morning, and how it looked different now (Sat after 4:30pm) - EL") -> Talked to them in front of tavern about how tragic it was for ghost theater to burn down before I arrived on Fri morning, and how it looked different now (Sat after 4:30pm) - EL
A39: =IFERROR(__xludf.DUMMYFUNCTION("""COMPUTED_VALUE"""),"Pascal Valerius") -> Pascal Valerius | B39: =IFERROR(__xludf.DUMMYFUNCTION("""COMPUTED_VALUE"""),TRUE) -> TRUE | C39: =IFERROR(__xludf.DUMMYFUNCTION("""COMPUTED_VALUE"""),"Interested in the charge, Think Aria kinda sucks (for firing danny)") -> Interested in the charge, Think Aria kinda sucks (for firing danny)
A40: =IFERROR(__xludf.DUMMYFUNCTION("""COMPUTED_VALUE"""),"Cary Montalvo") -> Cary Montalvo | B40: =IFERROR(__xludf.DUMMYFUNCTION("""COMPUTED_VALUE"""),FALSE) -> FALSE
A41: =IFERROR(__xludf.DUMMYFUNCTION("""COMPUTED_VALUE"""),"Samuelson") -> Samuelson | B41: =IFERROR(__xludf.DUMMYFUNCTION("""COMPUTED_VALUE"""),TRUE) -> TRUE | C41: =IFERROR(__xludf.DUMMYFUNCTION("""COMPUTED_VALUE"""),"Talked to Yara (Keeper). Told her to watch her sleeves over the candles. Don't want to pull a Danny Donnovan") -> Talked to Yara (Keeper). Told her to watch her sleeves over the candles. Don't want to pull a Danny Donnovan
A42: =IFERROR(__xludf.DUMMYFUNCTION("""COMPUTED_VALUE"""),"Vernon Gill") -> Vernon Gill | B42: =IFERROR(__xludf.DUMMYFUNCTION("""COMPUTED_VALUE"""),FALSE) -> FALSE
A43: =IFERROR(__xludf.DUMMYFUNCTION("""COMPUTED_VALUE"""),"Crabtree") -> Crabtree | B43: =IFERROR(__xludf.DUMMYFUNCTION("""COMPUTED_VALUE"""),TRUE) -> TRUE | C43: =IFERROR(__xludf.DUMMYFUNCTION("""COMPUTED_VALUE"""),"Sat on the way to Soul Speaking, spoke about DD helping Crabtree to bring in heavy boxes, history of pain, white noise, heart of gold. the party said that they also have the feeling that he's a kind person and does his best - MO") -> Sat on the way to Soul Speaking, spoke about DD helping Crabtree to bring in heavy boxes, history of pain, white noise, heart of gold. the party said that they also have the feeling that he's a kind person and does his best - MO
A44: =IFERROR(__xludf.DUMMYFUNCTION("""COMPUTED_VALUE"""),"Bracken") -> Bracken | B44: =IFERROR(__xludf.DUMMYFUNCTION("""COMPUTED_VALUE"""),FALSE) -> FALSE
A45: =IFERROR(__xludf.DUMMYFUNCTION("""COMPUTED_VALUE"""),"Mick Peacock") -> Mick Peacock | B45: =IFERROR(__xludf.DUMMYFUNCTION("""COMPUTED_VALUE"""),FALSE) -> FALSE
A46: =IFERROR(__xludf.DUMMYFUNCTION("""COMPUTED_VALUE"""),"Brimstone") -> Brimstone | B46: =IFERROR(__xludf.DUMMYFUNCTION("""COMPUTED_VALUE"""),TRUE) -> TRUE | C46: =IFERROR(__xludf.DUMMYFUNCTION("""COMPUTED_VALUE"""),"Totally got it, they were literally talking to themself ""oh, maybe ghosts would know?"" - ZT") -> Totally got it, they were literally talking to themself "oh, maybe ghosts would know?" - ZT
A47: =IFERROR(__xludf.DUMMYFUNCTION("""COMPUTED_VALUE"""),"Malachi") -> Malachi | B47: =IFERROR(__xludf.DUMMYFUNCTION("""COMPUTED_VALUE"""),TRUE) -> TRUE | C47: =IFERROR(__xludf.DUMMYFUNCTION("""COMPUTED_VALUE"""),"Had a wonderful conversation with them right when they came back from the ritual. They're on it!") -> Had a wonderful conversation with them right when they came back from the ritual. They're on it!
A48: =IFERROR(__xludf.DUMMYFUNCTION("""COMPUTED_VALUE"""),"Revelations") -> Revelations
A49: =IFERROR(__xludf.DUMMYFUNCTION("""COMPUTED_VALUE"""),"Mila") -> Mila | B49: =IFERROR(__xludf.DUMMYFUNCTION("""COMPUTED_VALUE"""),FALSE) -> FALSE
A50: =IFERROR(__xludf.DUMMYFUNCTION("""COMPUTED_VALUE"""),"Ghosts of the Morgans") -> Ghosts of the Morgans | B50: =IFERROR(__xludf.DUMMYFUNCTION("""COMPUTED_VALUE"""),FALSE) -> FALSE
A51: =IFERROR(__xludf.DUMMYFUNCTION("""COMPUTED_VALUE"""),"Aria Morgan") -> Aria Morgan | B51: =IFERROR(__xludf.DUMMYFUNCTION("""COMPUTED_VALUE"""),FALSE) -> FALSE
A52: =IFERROR(__xludf.DUMMYFUNCTION("""COMPUTED_VALUE"""),"Moxie") -> Moxie | B52: =IFERROR(__xludf.DUMMYFUNCTION("""COMPUTED_VALUE"""),FALSE) -> FALSE
A54: =IFERROR(__xludf.DUMMYFUNCTION("""COMPUTED_VALUE"""),"GENERAL NOTES") -> GENERAL NOTES
A55: =IFERROR(__xludf.DUMMYFUNCTION("""COMPUTED_VALUE"""),"accidentally told Claria my Arden clue info about SWV finding crown of St Mora… Sat. Breakfast M.O.") -> accidentally told Claria my Arden clue info about SWV finding crown of St Mora… Sat. Breakfast M.O.
A56: =IFERROR(__xludf.DUMMYFUNCTION("""COMPUTED_VALUE"""),"party photo taken -Mirin") -> party photo taken -Mirin
A57: =IFERROR(__xludf.DUMMYFUNCTION("""COMPUTED_VALUE"""),"one almost died battling skeevers - keeper used heal all wounds to save him. ") -> one almost died battling skeevers - keeper used heal all wounds to save him.
A58: =IFERROR(__xludf.DUMMYFUNCTION("""COMPUTED_VALUE"""),"Not good communication before Chitter fight. Spent 5 min planning and then Chitters were rushed by Uri Kesh. Feels like the party is still feeling each other out Sat 11am. -HA") -> Not good communication before Chitter fight. Spent 5 min planning and then Chitters were rushed by Uri Kesh. Feels like the party is still feeling each other out Sat 11am. -HA
A59: =IFERROR(__xludf.DUMMYFUNCTION("""COMPUTED_VALUE"""),"Traveler has a knee issue (pre-Otherworld) so Pascal got her a walking stick and we gave her Tylenol. She was reluctant to slow her group down. We had a good talk, she is feeling better about it. She will get a knee brace from Britt when they get to the t"&"avern. (Jen P)") -> Traveler has a knee issue (pre-Otherworld) so Pascal got her a walking stick and we gave her Tylenol. She was reluctant to slow her group down. We had a good talk, she is feeling better about it. She will get a knee brace from Britt when they get to the tavern. (Jen P)
A60: =IFERROR(__xludf.DUMMYFUNCTION("""COMPUTED_VALUE"""),"Party visit to Peacocks was split between 2 people who wanted to stay and sing forever, 2 people trying to figure shit out, and 2 people (a couple? She's the traveler) who seemed very removed and disengaged. -JF") -> Party visit to Peacocks was split between 2 people who wanted to stay and sing forever, 2 people trying to figure shit out, and 2 people (a couple? She's the traveler) who seemed very removed and disengaged. -JF
A61: =IFERROR(__xludf.DUMMYFUNCTION("""COMPUTED_VALUE"""),"Party was a bit hesitant about combat, but after sparring at the Valerius house, they are feeling much more confident. They have better communication, the caster is really blowing her whistle and projecting her spells, the keeper learned how to use her sh"&"ield and is feeling much more confident. JM") -> Party was a bit hesitant about combat, but after sparring at the Valerius house, they are feeling much more confident. They have better communication, the caster is really blowing her whistle and projecting her spells, the keeper learned how to use her shield and is feeling much more confident. JM
A62: =IFERROR(__xludf.DUMMYFUNCTION("""COMPUTED_VALUE"""),"Isaiah Cooke golden page story told to half the party") -> Isaiah Cooke golden page story told to half the party
A63: =IFERROR(__xludf.DUMMYFUNCTION("""COMPUTED_VALUE"""),"3:30 pm Sat - Claria only has three people. 1 is napping, 1 has a knee injury, one is keeping that person company. - KK (remove highlight when seen)") -> 3:30 pm Sat - Claria only has three people. 1 is napping, 1 has a knee injury, one is keeping that person company. - KK (remove highlight when seen)
A64: =IFERROR(__xludf.DUMMYFUNCTION("""COMPUTED_VALUE"""),"Post Lunch Saturday they seemed VERY invested in the Danny Donovan Charge") -> Post Lunch Saturday they seemed VERY invested in the Danny Donovan Charge
A65: =IFERROR(__xludf.DUMMYFUNCTION("""COMPUTED_VALUE"""),"5pm Sat - Claria companion returned to basement a riddle/bag that they had found. Handed to Jodi - EL") -> 5pm Sat - Claria companion returned to basement a riddle/bag that they had found. Handed to Jodi - EL

Sheet Doloron_Party Sheet
A1: DOLORÓN
A2: Investigating the charge against: Katherine Carmichael
A3: Companion: Dodi (Maisie Sturtevant)
A4: Keeper’s Saturday morning dream: The vision shows the gemwing butterfly and will (hopefully!) lead the party to Eugenie Bright.
A5: Riddle: Large Rock, fallen over, along Big Bow Trail halfway between Peaceful Crossing Bridge and entrance to Forsaken Forest
A6: Keeper’s Sunday morning dream: Shows Vernon Gill and suggests both that his injury is feigned and also that he’s motivated by greed.
A8: Complete? | B8: Staff | C8: Time | D8: Items to give | F8: Complete? | G8: Staff | H8: Info to Give | I8: Bloc Requirements
A9: =if('Dolorón_Import'!B5=true,"Yes!","No") -> Yes! | B9: Mick Peacock | C9: Contact | D9: -- | F9: =if('Dolorón_Import'!B24=true,"Yes!","No") -> Yes! | G9: Pearl Bryce | H9: assigns charge | I9: Need | J9: =COUNTif(F9,"Yes!") -> 1
A10: =if('Dolorón_Import'!B6=true,"Yes!","No") -> No | B10: Lexia | C10: 2nd Friday | D10: -- | F10: =if('Dolorón_Import'!B25=true,"Yes!","No") -> No | G10: Mila | H10: Vernon was a soldier until K shot him ten years ago, and wants restitution. K admits she did it. | I10: Need 2 | J10: =COUNTif(F10:F12,"Yes!") -> 0
A11: =if('Dolorón_Import'!B7=true,"Yes!","No") -> Yes! | B11: JPeg | C11: 3rd Friday | D11: -- | F11: =if('Dolorón_Import'!B26=true,"Yes!","No") -> No | G11: Melados | H11: Vernon was a soldier until K shot him ten years ago, and wants restitution. K admits she did it.
A12: =if('Dolorón_Import'!B8=true,"Yes!","No") -> Yes! | B12: Phyllis Fieri | C12: 4th Friday | D12: list of items | F12: =if('Dolorón_Import'!B27=true,"Yes!","No") -> No | G12: Jack Johnson | H12: Vernon was a soldier until K shot him ten years ago, and wants restitution. K admits she did it.
A13: =if('Dolorón_Import'!B9=true,"Yes!","No") -> Yes! | B13: Crabtree | C13: 1st Saturday | D13: snake-eye talisman | F13: =if('Dolorón_Import'!B28=true,"Yes!","No") -> Yes! | G13: Kyli Talespinner | H13: K shot Vernon ten years ago after he mouthed off. Afterwards, she reclaimed the crossbow bolts. | I13: Need 1 | J13: =COUNTif(F13:F14,"Yes!") -> 1
A14: =if('Dolorón_Import'!B10=true,"Yes!","No") -> Yes! | B14: Isaiah Cooke | C14: 8am-2pm | D14: riddle leading to silver incense burner | F14: =if('Dolorón_Import'!B29=true,"Yes!","No") -> No | G14: Moxie | H14: K shot Vernon ten years ago after he mouthed off. Afterwards, she reclaimed the crossbow bolts.
A15: =if('Dolorón_Import'!B11=true,"Yes!","No") -> Yes! | B15: Malachi (PEN Saturday) | C15: 8am-2pm, 4-8pm | D15: none until tomorrow | F15: =if('Dolorón_Import'!B30=true,"Yes!","No") -> Yes! | G15: Vernon Gill | H15: Is unpleasant/K shot him and reclaimed the crossbow bolts. | I15: Need | J15: =COUNTif(F15,"Yes!") -> 1
A16: =if('Dolorón_Import'!B12=true,"Yes!","No") -> Yes! | B16: Kora Peacekeeper | C16: 9am-4pm | D16: whiteleaf sage | F16: =if('Dolorón_Import'!B31=true,"Yes!","No") -> Yes! | G16: Katherine Carmichael | H16: Is competent and likable/doesn’t want to talk about Vernon Gill. | I16: Need | J16: =COUNTif(F16,"Yes!") -> 1
A17: =if('Dolorón_Import'!B13=true,"Yes!","No") -> No | B17: Pansy Golden | C17: 8am-3pm | D17: seafoam sphere | F17: =if('Dolorón_Import'!B32=true,"Yes!","No") -> Yes! | G17: Nix Valerius | H17: K really IS Kit Carson. The books are inspiring. The books’ physical description of Kit matches K. | I17: Need 4 | J17: =COUNTif(F17:F22,"Yes!") -> 6
A18: =if('Dolorón_Import'!B14=true,"Yes!","No") -> Yes! | B18: Stevie Peacock | C18: 8-11am, 3-8pm | D18: signalstone ring | F18: =if('Dolorón_Import'!B33=true,"Yes!","No") -> Yes! | G18: Angelica Sprink | H18: K really IS Kit Carson. The books are inspiring.
A19: =if('Dolorón_Import'!B15=true,"Yes!","No") -> Yes! | B19: Eugenie Bright | C19: 10am-4pm | D19: gemwing butterfly | F19: =if('Dolorón_Import'!B34=true,"Yes!","No") -> Yes! | G19: Aria Morgan | H19: K really IS Kit Carson. The books are inspiring.
A20: =if('Dolorón_Import'!B16=true,"Yes!","No") -> Yes! | B20: Bracken | C20: 8-11am, 1-4pm | D20: water from River Sigh | F20: =if('Dolorón_Import'!B35=true,"Yes!","No") -> Yes! | G20: Belle Bishop | H20: K really IS Kit Carson. The books are inspiring.
A21: =if('Dolorón_Import'!B17=true,"Yes!","No") -> Yes! | B21: Ghost Theater | C21: 4-8pm | D21: limelight | F21: =if('Dolorón_Import'!B36=true,"Yes!","No") -> Yes! | G21: Donna Peacock | H21: K really IS Kit Carson. The books are inspiring.
A22: =if('Dolorón_Import'!B18=true,"Yes!","No") -> No | B22: Malachi | C22: PEN 9:45am | D22: merula-fruit cordial | F22: =if('Dolorón_Import'!B37=true,"Yes!","No") -> Yes! | G22: Lexia | H22: K really IS Kit Carson. The books are inspiring.
A23: =if('Dolorón_Import'!B19=true,"Yes!","No") -> No | B23: Pixies | C23: 0.41666667 | D23: pixie dust | F23: =if('Dolorón_Import'!B38=true,"Yes!","No") -> Yes! | G23: Lincroft Spence | H23: K really IS Kit Carson. The books are great, but many people have a dismissive attitude towards her books. | I23: Need 3 | J23: =COUNTif(F23:F27,"Yes!") -> 3
A24: =If(Dashboard!$M5=TRUE,"Yes!","No") -> No | B24: riddle item found? | C24: -- | D24: -- | F24: =if('Dolorón_Import'!B39=true,"Yes!","No") -> Yes! | G24: Karmin Smirch | H24: K really IS Kit Carson. Karmin has a dismissive attitude towards her books.
F25: =if('Dolorón_Import'!B40=true,"Yes!","No") -> No | G25: Bartleby Sprink | H25: K really IS Kit Carson. Bartleby has a dismissive attitude towards her books, which encourage young girls to behave badly.
A26: COMMENTS | F26: =if('Dolorón_Import'!B41=true,"Yes!","No") -> No | G26: Carmina Bordeaux | H26: K really IS Kit Carson. Carmina has a dismissive attitude towards her books, which encourage children to behave badly.
A27: =IFERROR(__xludf.DUMMYFUNCTION("IFERROR( FILTER( FLATTEN({'Dolorón_Import'!C5:C20; 'Dolorón_Import'!C24:C52; 'Dolorón_Import'!A53:A79}), FLATTEN({'Dolorón_Import'!C5:C20; 'Dolorón_Import'!C24:C52; 'Dolorón_Import'!A53:A79}) <> """" ), """" )"),"4th Friday - gave them letter w list of items. Great teamwork on challenge. Excellent group dynamics! ") -> 4th Friday - gave them letter w list of items. Great teamwork on challenge. Excellent group dynamics! | F27: =if('Dolorón_Import'!B42=true,"Yes!","No") -> Yes! | G27: Edwin Davies | H27: K really IS Kit Carson. Edwin has a dismissive attitude towards her books, which encourage children to behave badly.
A28: =IFERROR(__xludf.DUMMYFUNCTION("""COMPUTED_VALUE"""),"1st Sat - gave them snake eye talisman (Maker is wearing as a necklace); traveler was distracted by writing his notes, not paying attention to ""bucket challenge"", but participated when I addressed him specifically; caster renewed the whirlwind spell; Tr"&"aveler seems to be trying to be in charge & direct the rest of the team's behavior, everyone was attending politely to him, but I could imagine that being a stress point .") -> 1st Sat - gave them snake eye talisman (Maker is wearing as a necklace); traveler was distracted by writing his notes, not paying attention to "bucket challenge", but participated when I addressed him specifically; caster renewed the whirlwind spell; Traveler seems to be trying to be in charge & direct the rest of the team's behavior, everyone was attending politely to him, but I could imagine that being a stress point . | F28: =if('Dolorón_Import'!B43=true,"Yes!","No") -> Yes! | G28: Bonnie Stillwater | H28: Electra had nosebleed. K was faint at sight of blood. | I28: Need 1 | J28: =COUNTif(F28:F29,"Yes!") -> 1
A29: =IFERROR(__xludf.DUMMYFUNCTION("""COMPUTED_VALUE"""),"They were fantastic! Super invested and had a convo and combat! Love them") -> They were fantastic! Super invested and had a convo and combat! Love them | F29: =if('Dolorón_Import'!B44=true,"Yes!","No") -> No | G29: Electra | H29: Electra had nosebleed. K was faint at sight of blood.
A30: =IFERROR(__xludf.DUMMYFUNCTION("""COMPUTED_VALUE"""),"Update - Lunch: I spoke to Doloron at their table. They asked about the Merula Fruit Cordial. I told them to find me at the Roamer Camp and play Managers and Peons if they would like to get the Cordial. After they've done that, I'd be happy to meet them a"&"t 10:00am on Sunday. Sat AM: I have not seen Doloron yet, and am concerned because it is nearing the end of my morning face part.") -> Update - Lunch: I spoke to Doloron at their table. They asked about the Merula Fruit Cordial. I told them to find me at the Roamer Camp and play Managers and Peons if they would like to get the Cordial. After they've done that, I'd be happy to meet them at 10:00am on Sunday. Sat AM: I have not seen Doloron yet, and am concerned because it is nearing the end of my morning face part. | F30: =if('Dolorón_Import'!B45=true,"Yes!","No") -> No | G30: Katherine Carmichael | H30: Gets shaky and tells party she doesn’t want to talk about it. [Does Sunday 10am scene if they press her.]
A31: =IFERROR(__xludf.DUMMYFUNCTION("""COMPUTED_VALUE"""),"At breakfast, made a deal that they will cheer Ned up and I will give them the sphere. Planned for lunch Sat --HA Talked to Bracken about this after lunch, didn't find Ned and trying to ask people to see what he likes -- RS") -> At breakfast, made a deal that they will cheer Ned up and I will give them the sphere. Planned for lunch Sat --HA Talked to Bracken about this after lunch, didn't find Ned and trying to ask people to see what he likes -- RS | F31: =if('Dolorón_Import'!B46=true,"Yes!","No") -> Yes! | G31: Cameron Light-Astor | H31: Vernon didn’t know a marching song that every soldier should know. | I31: Need | J31: =COUNTif(F31,"Yes!") -> 1
A32: =IFERROR(__xludf.DUMMYFUNCTION("""COMPUTED_VALUE"""),"Overheard conversartion on needing gemwing butterfly.") -> Overheard conversartion on needing gemwing butterfly. | F32: =if(Dashboard!G5=true,"Yes!","No") -> Yes! | G32: Keeper’s Sunday Vision | H32: This vision shows Vernon Gill and suggests both that his injury is feigned and also that he’s motivated by greed. | I32: Need | J32: =COUNTif(F32,"Yes!") -> 1
A33: =IFERROR(__xludf.DUMMYFUNCTION("""COMPUTED_VALUE"""),"Had a good story and really considerate about taking something that was from my grandfather, all around went well! -- RS") -> Had a good story and really considerate about taking something that was from my grandfather, all around went well! -- RS | F33: =if('Dolorón_Import'!B48=true,"Yes!","No") -> No | G33: Katherine Carmichael | H33: She didn’t shoot Gill. She’s not Kit Carnage. But she doesn’t want to let down her fans, so is pleading guilty. | J33: =COUNTif(F33,"Yes!") -> 0
A34: =IFERROR(__xludf.DUMMYFUNCTION("""COMPUTED_VALUE"""),"Very engaged, however the taller gentleman did a fake face-first into the sand ""Fainting"" that we treated seriously. FFS. Dave") -> Very engaged, however the taller gentleman did a fake face-first into the sand "Fainting" that we treated seriously. FFS. Dave | F34: =if('Dolorón_Import'!B49=true,"Yes!","No") -> No | G34: Pearl Bryce, Nix Valerius, Joni Peacock, Donna Peacock, Nina Bliss | H34: They cannot let K go to jail; they love the books so much. When party tells them the truth: K is so brave!! | I34: Need | J34: =COUNTif(F34,"Yes!") -> 0
A35: =IFERROR(__xludf.DUMMYFUNCTION("""COMPUTED_VALUE"""),"Seem to at least like pearl! HOORAY. Ask her to help them investigate pixies, she said sure after she finishes the Katherine Carmicheal article (Friday Night)-TB Charge given, maker seems invested and doesn't like Verrin. Some other party members skeptica"&"l of Katherine. They are asking who would benefit from besmirching Katherine (saturyday 1:45)-TB") -> Seem to at least like pearl! HOORAY. Ask her to help them investigate pixies, she said sure after she finishes the Katherine Carmicheal article (Friday Night)-TB Charge given, maker seems invested and doesn't like Verrin. Some other party members skeptical of Katherine. They are asking who would benefit from besmirching Katherine (saturyday 1:45)-TB | F35: =if('Dolorón_Import'!B50=true,"Yes!","No") -> No | G35: Diesel | H35: • Vernon Gill lied about everything; Katherine never shot him and he isn’t actually injured. • Katherine was willing to take the fall for this crime because she believes her readers will be disillusioned if they learn she’s not actually courageous like her heroine Kit Carnage. • In actuality, the true story of Katherine being willing to sacrifice herself for others is even more inspiring. | I35: Need 2 | J35: =COUNTif(F35:F37,"Yes!") -> 0
A36: =IFERROR(__xludf.DUMMYFUNCTION("""COMPUTED_VALUE"""),"Talked to party Sat 7:30pm in Tavern. Whole party was engaged but maybe not yet fully interested in the charge. MG") -> Talked to party Sat 7:30pm in Tavern. Whole party was engaged but maybe not yet fully interested in the charge. MG
A37: =IFERROR(__xludf.DUMMYFUNCTION("""COMPUTED_VALUE"""),"Fri 10:30pm-Keeperwantedto heal my arm, I briefly explained the attack and that it was exhibit 1 for Sunday's trial.") -> Fri 10:30pm-Keeperwantedto heal my arm, I briefly explained the attack and that it was exhibit 1 for Sunday's trial.
A38: =IFERROR(__xludf.DUMMYFUNCTION("""COMPUTED_VALUE"""),"spoke briefly with a couple members at breakfast; just pleasantries; Lincroft came over as well (to gush, of course) ") -> spoke briefly with a couple members at breakfast; just pleasantries; Lincroft came over as well (to gush, of course)
A39: =IFERROR(__xludf.DUMMYFUNCTION("""COMPUTED_VALUE"""),"Most were engaged, understand that Vernon Gill sucks and Katherine Carmichael is awesome") -> Most were engaged, understand that Vernon Gill sucks and Katherine Carmichael is awesome
A40: =IFERROR(__xludf.DUMMYFUNCTION("""COMPUTED_VALUE"""),"Got info to three members, got the message I was inspired 1:45 ") -> Got info to three members, got the message I was inspired 1:45
A41: =IFERROR(__xludf.DUMMYFUNCTION("""COMPUTED_VALUE"""),"Joined for breakfast, Pearl and Aria retold scene from Across the Prairie, party was very invested in how popular KC's books are, and how cool it is she has a crossbow just like Kit Carnage. 4/5 members were actively listening and engaged. DG") -> Joined for breakfast, Pearl and Aria retold scene from Across the Prairie, party was very invested in how popular KC's books are, and how cool it is she has a crossbow just like Kit Carnage. 4/5 members were actively listening and engaged. DG
A42: =IFERROR(__xludf.DUMMYFUNCTION("""COMPUTED_VALUE"""),"Talked with them at lunch and they were interested in Katherine Carmichael's story - asked why she had come to town") -> Talked with them at lunch and they were interested in Katherine Carmichael's story - asked why she had come to town
A43: =IFERROR(__xludf.DUMMYFUNCTION("""COMPUTED_VALUE"""),"Had a good chat sitting with two women in the party during lunch. -LBD") -> Had a good chat sitting with two women in the party during lunch. -LBD
A44: =IFERROR(__xludf.DUMMYFUNCTION("""COMPUTED_VALUE"""),"Chatted with Katherine Carmichael at breakfact and reinforced ""based on her life"", which thet had clearly already taken in") -> Chatted with Katherine Carmichael at breakfact and reinforced "based on her life", which thet had clearly already taken in
A45: =IFERROR(__xludf.DUMMYFUNCTION("""COMPUTED_VALUE"""),"Chatted with them around 7pm Sat. Deliveried the info. They floated a potential framing.") -> Chatted with them around 7pm Sat. Deliveried the info. They floated a potential framing.
A46: =IFERROR(__xludf.DUMMYFUNCTION("""COMPUTED_VALUE"""),"Told one member of the party how KC's charge wasn't surprising, as a natural consequence of allowing the drivel/so-called-""literature"" she writes to influence the minds of youth in Lyrian society.") -> Told one member of the party how KC's charge wasn't surprising, as a natural consequence of allowing the drivel/so-called-"literature" she writes to influence the minds of youth in Lyrian society.
A47: =IFERROR(__xludf.DUMMYFUNCTION("""COMPUTED_VALUE"""),"Talked to at least 2 participants about KC's faintness at the sight of blood. They asked how could that be if she's an epic hunter and adventurer jag") -> Talked to at least 2 participants about KC's faintness at the sight of blood. They asked how could that be if she's an epic hunter and adventurer jag
A48: =IFERROR(__xludf.DUMMYFUNCTION("""COMPUTED_VALUE"""),"Told 3-4 participants about Sgt Gill not knowing the song, and leaving him sad. They seemed entirely focused on the fact that he was sad and how to comfort him and not at all about the lack of knowledge of military songs. - RP") -> Told 3-4 participants about Sgt Gill not knowing the song, and leaving him sad. They seemed entirely focused on the fact that he was sad and how to comfort him and not at all about the lack of knowledge of military songs. - RP
A49: =IFERROR(__xludf.DUMMYFUNCTION("""COMPUTED_VALUE"""),"JV-Fri-11pm-they were reviewing resourceslike spells and forming general strategies.") -> JV-Fri-11pm-they were reviewing resourceslike spells and forming general strategies.
A50: =IFERROR(__xludf.DUMMYFUNCTION("""COMPUTED_VALUE"""),"AM - On Friday evening when they told us they were headed to FireWaterEarthAirBnb we (Cary and Belle) had a hilarious exchange with them in which we both apologized for my father and described him as ""a lot."" We told them about the mix-up and they were "&"HIGHLY entertained. When we saw them later that night we asked how they were doing and how things went, and they said it was great, that they loved both of our parents, ""apart from the flatulence issue."" They they proceeded to tell us that they thought "&"there might be some romantic energy between the two of them, which we found both preposterous and ""gross."" GREAT conversation. ") -> AM - On Friday evening when they told us they were headed to FireWaterEarthAirBnb we (Cary and Belle) had a hilarious exchange with them in which we both apologized for my father and described him as "a lot." We told them about the mix-up and they were HIGHLY entertained. When we saw them later that night we asked how they were doing and how things went, and they said it was great, that they loved both of our parents, "apart from the flatulence issue." They they proceeded to tell us that they thought there might be some romantic energy between the two of them, which we found both preposterous and "gross." GREAT conversation.
A51: =IFERROR(__xludf.DUMMYFUNCTION("""COMPUTED_VALUE"""),"Did not pay for breakfast (Sat AM), was told they accidentally left their money in the cabin. Seemed pretty worried about having enough money to pay for things, they shared their chitter combat winnings with Arden this morning. Bonnie was tough on them bu"&"t told them they needed to pay what was owed at lunch. DG") -> Did not pay for breakfast (Sat AM), was told they accidentally left their money in the cabin. Seemed pretty worried about having enough money to pay for things, they shared their chitter combat winnings with Arden this morning. Bonnie was tough on them but told them they needed to pay what was owed at lunch. DG
A52: =IFERROR(__xludf.DUMMYFUNCTION("""COMPUTED_VALUE"""),"party photo taken -Mirin") -> party photo taken -Mirin
A53: =IFERROR(__xludf.DUMMYFUNCTION("""COMPUTED_VALUE"""),"Caster used Gust of Wind spell against skeevers. ") -> Caster used Gust of Wind spell against skeevers.
A54: =IFERROR(__xludf.DUMMYFUNCTION("""COMPUTED_VALUE"""),"Shared general info that Belle is effusive and sometimes forgets that Cari doesn't want attention called to him, e.g. at his birthday party; I hope she remembers that at the wedding. Saturday 10am. M.O.") -> Shared general info that Belle is effusive and sometimes forgets that Cari doesn't want attention called to him, e.g. at his birthday party; I hope she remembers that at the wedding. Saturday 10am. M.O.
A55: =IFERROR(__xludf.DUMMYFUNCTION("""COMPUTED_VALUE"""),"Golden page great convo for Isaiah") -> Golden page great convo for Isaiah
A56: =IFERROR(__xludf.DUMMYFUNCTION("""COMPUTED_VALUE"""),"Seemed worried about Wolven, but had a lovely Cup of Insight. - Kira") -> Seemed worried about Wolven, but had a lovely Cup of Insight. - Kira
A57: =IFERROR(__xludf.DUMMYFUNCTION("""COMPUTED_VALUE"""),"Caster has a strong fairness drive - showed up in combat practice at Valerius house in strong views about how combat practice should be structured. Traveler is less mobile and did not participate in combat training and appears to be some tension between "&"the caster and the traveler as a result. Caster was pushing to say traveler should be getting into combat. - Neal, 1:30pm Sat") -> Caster has a strong fairness drive - showed up in combat practice at Valerius house in strong views about how combat practice should be structured. Traveler is less mobile and did not participate in combat training and appears to be some tension between the caster and the traveler as a result. Caster was pushing to say traveler should be getting into combat. - Neal, 1:30pm Sat
A58: =IFERROR(__xludf.DUMMYFUNCTION("""COMPUTED_VALUE"""),"Have golden page info re: Obsidian-Abigail") -> Have golden page info re: Obsidian-Abigail
A59: =IFERROR(__xludf.DUMMYFUNCTION("""COMPUTED_VALUE"""),"6:30 Saturday SM -Gave them a great (if brief) Wolven fight at the bottom of Shepherd's Pass. Their Caster did an illusion that the participants all had wings and the Wolven were all standing on 6"" square pillars over a hundred foot drop. They made sho"&"rt work of us and seemed to feel heroically clever.") -> 6:30 Saturday SM -Gave them a great (if brief) Wolven fight at the bottom of Shepherd's Pass. Their Caster did an illusion that the participants all had wings and the Wolven were all standing on 6" square pillars over a hundred foot drop. They made short work of us and seemed to feel heroically clever.
A60: =IFERROR(__xludf.DUMMYFUNCTION("""COMPUTED_VALUE"""),"Party snuck past mad lib ander wolven party, then came back and declared single combat to save the ""kidnapped"" ander") -> Party snuck past mad lib ander wolven party, then came back and declared single combat to save the "kidnapped" ander

Sheet Elsewhich_Party Sheet
A1: ELSEWHICH
A2: Investigating the charge against: Evelyn
A3: Companion: Elvie (Christine Huebbe)
A4: Keeper’s Saturday morning dream: Shows the gold laceleaf pendant and (hopefully!) leads the party to Belle Bishop
A5: Riddle: Heliotrope Candle, ~120 paces beyond the entrance to the Forsaken Forest, left side of the path are two joined trees with their roots spreading over a grey rock. Candle hidden behind the trees (that is, away from the path.)
A6: Keeper’s Sunday morning dream: Suggests that Kira is the one who has magical ability but doesn't know it, and that she is thus the one who can successfully do the ritual with the magic cup.
A8: Complete? | B8: Staff | C8: Time | D8: Items to give | F8: Complete? | G8: Staff | H8: Info to Give | I8: Bloc Requirements
A9: Yes! | B9: Electra | C9: Contact | D9: -- | F9: =if(Elsewhich_Import!B24=true,"Yes!","No") -> Yes! | G9: Ember And Karmin Smirch | H9: The party is brought to Ember as their party path second encounter and she is hanging out with Karmin. (sets charge context ) | I9: Need | J9: =COUNTif(F9,"Yes!") -> 1
A10: =if(Elsewhich_Import!B6=true,"Yes!","No") -> Yes! | B10: Ember | C10: 2nd Friday | D10: -- | F10: =if(Elsewhich_Import!B25=true,"Yes!","No") -> No | G10: Teknos | H10: Nice to meet the party before his Sunday prototype.
A11: =if(Elsewhich_Import!B7=true,"Yes!","No") -> Yes! | B11: Kira | C11: 3rd Friday | D11: -- | F11: =if(Elsewhich_Import!B26=true,"Yes!","No") -> No | G11: Buzzkill | H11: assigns charge | I11: Need 2 | J11: =COUNTif(F11:F15,"Yes!") -> 2
A12: =if(Elsewhich_Import!B8=true,"Yes!","No") -> Yes! | B12: Kerrick Dealbinder | C12: 4th Friday | D12: list of items | F12: =if(Elsewhich_Import!B27=true,"Yes!","No") -> No | G12: Obsidian | H12: Evelyn threatened to put Ursula out of business after Ursula spoke of a machine that could replace Crabtree. Doesn’t sound like Evelyn
A13: =if(Elsewhich_Import!B9=true,"Yes!","No") -> Yes! | B13: Mila | C13: 1st Saturday | D13: amethyst sphere | F13: =if(Elsewhich_Import!B28=true,"Yes!","No") -> Yes! | G13: Poppy Golden | H13: Evelyn threatened to put Ursula out of business after Ursula spoke of a machine that could replace Crabtree Doesn’t sound like Evelyn
A14: =if(Elsewhich_Import!B10=true,"Yes!","No") -> Yes! | B14: Danny Donovan | C14: 10am - 4pm | D14: crummy magic chalice | F14: =if(Elsewhich_Import!B29=true,"Yes!","No") -> No | G14: Moxie | H14: Evelyn threatened to put Ursula out of business after Ursula spoke of a machine that could replace Crabtree Doesn’t sound like Evelyn
A15: =if(Elsewhich_Import!B11=true,"Yes!","No") -> Yes! | B15: Teknos | C15: 10am - 3pm | D15: none until tomorrow | F15: =if(Elsewhich_Import!B30=true,"Yes!","No") -> Yes! | G15: Evelyn | H15: Evelyn threatened to put Ursula out of business after Ursula spoke of a machine that could replace Crabtree (and Evelyn claims she isn’t guilty of the charge)
A16: =if(Elsewhich_Import!B12=true,"Yes!","No") -> Yes! | B16: Belle Bishop | C16: 8am - 2pm | D16: gold laceleaf pendant | F16: =if(Elsewhich_Import!B31=true,"Yes!","No") -> Yes! | G16: Karmin Smirch | H16: Merchandise has been knocked off of Smirch shelves (probably Evelyn) | I16: Need 7 | J16: =COUNTif(F16:F26,"Yes!") -> 7
A17: =if(Elsewhich_Import!B13=true,"Yes!","No") -> Yes! | B17: Donna Peacock | C17: 12noon - 8pm | D17: cat’s-eye jewelbox | F17: =if(Elsewhich_Import!B32=true,"Yes!","No") -> Yes! | G17: Nina Bliss | H17: Merchandise has been knocked off of Smirch shelves
A18: =if(Elsewhich_Import!B14=true,"Yes!","No") -> Yes! | B18: Fenwick Michaels | C18: 8am - 2pm, 6-8pm | D18: gospel weed | F18: =if(Elsewhich_Import!B33=true,"Yes!","No") -> Yes! | G18: Phineas Smirch | H18: Smirch shipping containers have been crushed. Evelyn must have climbed on top of them
A19: =if(Elsewhich_Import!B15=true,"Yes!","No") -> Yes! | B19: Pearl Bryce | C19: 10am - 4pm | D19: riddle to heliotrope candle | F19: =if(Elsewhich_Import!B34=true,"Yes!","No") -> Yes! | G19: Dramina | H19: Smirch shipping containers have been crushed Phineas says Evelyn climbed on top of the boxes
A20: =if(Elsewhich_Import!B16=true,"Yes!","No") -> Yes! | B20: Samuelson | C20: 8am - 2pm, 6-8pm | D20: doveroot seeds | F20: =if(Elsewhich_Import!B35=true,"Yes!","No") -> Yes! | G20: Ursula Smirch | H20: Bloody animal carcasses are being left by the Smirch shop (probably by Evelyn)
A21: =if(Elsewhich_Import!B17=true,"Yes!","No") -> Yes! | B21: (mad) Lincroft Spence | C21: 4 - 8pm | D21: folly dust | F21: =if(Elsewhich_Import!B36=true,"Yes!","No") -> No | G21: Pascal Valerius | H21: Bloody animal carcasses are being left by the Smirch shop
A22: =if(Elsewhich_Import!B18=true,"Yes!","No") -> Yes! | B22: Teknos | C22: PEN: 9:45am Sunday | D22: Elsewhichian wine | F22: =if(Elsewhich_Import!B37=true,"Yes!","No") -> No | G22: Natasha | H22: Bloody animal carcasses are being left by the Smirch shop
A23: =if(Elsewhich_Import!B19=true,"Yes!","No") -> No | B23: Kira | C23: 10am Sunday | D23: magical cup from ritual | F23: =if(Elsewhich_Import!B38=true,"Yes!","No") -> Yes! | G23: Karla Smirch | H23: Someone is leaving gobs of wet hair on the Smirches’ floor (probably Evelyn)
A24: =If(Dashboard!$M6=TRUE,"Yes!","No") -> Yes! | B24: riddle item found? | C24: -- | D24: -- | F24: =if(Elsewhich_Import!B39=true,"Yes!","No") -> No | G24: Milton Peacock | H24: Stepped in gobs of wet slime/lint on the Smirches’ floor
F25: =if(Elsewhich_Import!B40=true,"Yes!","No") -> No | G25: Kerrick Dealbinder | H25: There is an odor of urine around the Smirch shop
A26: COMMENTS | F26: =if(Elsewhich_Import!B41=true,"Yes!","No") -> Yes! | G26: Floria | H26: There is an odor of urine around the Smirch shop
A27: =IFERROR(__xludf.DUMMYFUNCTION("IFERROR( FILTER( FLATTEN({Elsewhich_Import!C5:C20; Elsewhich_Import!C24:C52; Elsewhich_Import!A61:A90}), FLATTEN({Elsewhich_Import!C5:C20; Elsewhich_Import!C24:C52; Elsewhich_Import!A61:A90}) <> """" ), """" )"),"Very engaged in overall plot (knows about memory gap, trial, wedding, etc). Had to remind them to ask me about the cup after 2 other concentrations so may be a little unfocused or just overwhelmed by tavern. Definitely approaching in a larp-like capacity "&"(but not necessarily in a bad way) -Mirin") -> Very engaged in overall plot (knows about memory gap, trial, wedding, etc). Had to remind them to ask me about the cup after 2 other concentrations so may be a little unfocused or just overwhelmed by tavern. Definitely approaching in a larp-like capacity (but not necessarily in a bad way) -Mirin | F27: =if(Elsewhich_Import!B42=true,"Yes!","No") -> No | G27: Tanya Peacock | H27: Ember is authentic, but hard to get to know (and Tanya adores her) | I27: Need 3 | J27: =COUNTif(F27:F31,"Yes!") -> 3
A28: =IFERROR(__xludf.DUMMYFUNCTION("""COMPUTED_VALUE"""),"Super into the Elsewich lore they concocted together in a really fun way. They're super friendly, invited Kira to visit Elsewich already, funny. They didn't immediately associate hex with Kira, so that's a win - only asked one follow up question about his"&"tory of hex in Macai, so Kira will emphasize curiosity about hex during Dreadwright ritual to give them another point of reference. - Kels") -> Super into the Elsewich lore they concocted together in a really fun way. They're super friendly, invited Kira to visit Elsewich already, funny. They didn't immediately associate hex with Kira, so that's a win - only asked one follow up question about history of hex in Macai, so Kira will emphasize curiosity about hex during Dreadwright ritual to give them another point of reference. - Kels | F28: =if(Elsewhich_Import!B43=true,"Yes!","No") -> Yes! | G28: Dorito | H28: Ember is authentic, but hard to get to know. She is also stylish and relatable.
A29: =IFERROR(__xludf.DUMMYFUNCTION("""COMPUTED_VALUE"""),"Very engaged group. Both in terms of being deep and insightful for the Cup ritual, but also with levity and ""buying into the bit""") -> Very engaged group. Both in terms of being deep and insightful for the Cup ritual, but also with levity and "buying into the bit" | F29: =if(Elsewhich_Import!B44=true,"Yes!","No") -> No | G29: Bartelby Sprink | H29: Ember is stylish.
A30: =IFERROR(__xludf.DUMMYFUNCTION("""COMPUTED_VALUE"""),"very engaged, were making plans together") -> very engaged, were making plans together | F30: =if(Elsewhich_Import!B45=true,"Yes!","No") -> Yes! | G30: Umberto Dunn | H30: Ember is famous for being famous and doesn’t care what people think.
A31: =IFERROR(__xludf.DUMMYFUNCTION("""COMPUTED_VALUE"""),"they have done the chaloenge (while Dannty was not there) but he has not seen them to give them the cup. Cup delivered (Jen P)") -> they have done the chaloenge (while Dannty was not there) but he has not seen them to give them the cup. Cup delivered (Jen P) | F31: =if(Elsewhich_Import!B46=true,"Yes!","No") -> Yes! | G31: Aleeya Witchborn | H31: Ember has clearly defined boundaries, a healthy sense of self, and practices aspiration self care.
A32: =IFERROR(__xludf.DUMMYFUNCTION("""COMPUTED_VALUE"""),"After lunch I did ""What Kind of Tree Are You?"" Challenge with them, and they provided thoughtful, empathetic answers in both rounds - What kind of tree? and What month of the year? Gave them gold laceleaf pendant. ") -> After lunch I did "What Kind of Tree Are You?" Challenge with them, and they provided thoughtful, empathetic answers in both rounds - What kind of tree? and What month of the year? Gave them gold laceleaf pendant. | F32: =if(Elsewhich_Import!B47=true,"Yes!","No") -> No | G32: Joni Peacock | H32: Ember is cool, but she doesn’t know why Ember hangs out with Karmin Smirch. | I32: Need 1 | J32: =COUNTif(F32:F33,"Yes!") -> 0
A33: =IFERROR(__xludf.DUMMYFUNCTION("""COMPUTED_VALUE"""),"Really good party, had lots of fun and laughter during Perfect Square. - Eli") -> Really good party, had lots of fun and laughter during Perfect Square. - Eli | F33: =if(Elsewhich_Import!B48=true,"Yes!","No") -> No | G33: Miscellania | H33: Ember is stylish; her image is curated but seems effortless. Ember hangs out with Karmin Smirch.
A34: =IFERROR(__xludf.DUMMYFUNCTION("""COMPUTED_VALUE"""),"Given around 11:30Am already starting to solve connect bow with the path on the first read.*") -> Given around 11:30Am already starting to solve connect bow with the path on the first read.* | F34: =if(Elsewhich_Import!B49=true,"Yes!","No") -> Yes! | G34: Bailey | H34: Ember likes Bailey. “She likes me, I know it” | I34: Need | J34: =COUNTif(F34,"Yes!") -> 1
A35: =IFERROR(__xludf.DUMMYFUNCTION("""COMPUTED_VALUE"""),"Asked about Doveroot Friday night at 10:30 pm. Told them I would have it with me tomorrow. Surprised me at dinner Saturday by declaring it to be my King's Day, and gave me a card and a back of candy as well as 3 commands. I asked for a reference with the"&"ir Duke/Duchess, for them to do a random act of propriety, and a random act of kindness.") -> Asked about Doveroot Friday night at 10:30 pm. Told them I would have it with me tomorrow. Surprised me at dinner Saturday by declaring it to be my King's Day, and gave me a card and a back of candy as well as 3 commands. I asked for a reference with their Duke/Duchess, for them to do a random act of propriety, and a random act of kindness. | F35: =if(Elsewhich_Import!B50=true,"Yes!","No") -> Yes! | G35: Quinoa | H35: Ember is high maintenance and cries until she gets food. | I35: Need 2 | J35: =COUNTif(F35:F37,"Yes!") -> 2
A36: =IFERROR(__xludf.DUMMYFUNCTION("""COMPUTED_VALUE"""),"approached MoaM very much like 4 people and 2 people. Even after we probed, they pretty much didn't get it. (""Grapes are better in a bunch... but then you kinda just need to go it alone."" Ah well (KLH)") -> approached MoaM very much like 4 people and 2 people. Even after we probed, they pretty much didn't get it. ("Grapes are better in a bunch... but then you kinda just need to go it alone." Ah well (KLH) | F36: =if(Elsewhich_Import!B51=true,"Yes!","No") -> No | G36: Isaiah Cooke | H36: Ember is popular but he finds her rude. Repeatedly, she had him open the door and then she immediately left again.
A37: =IFERROR(__xludf.DUMMYFUNCTION("""COMPUTED_VALUE"""),"They are very pro Ember as of Fri night -Mirin") -> They are very pro Ember as of Fri night -Mirin | F37: =if(Elsewhich_Import!B52=true,"Yes!","No") -> Yes! | G37: Orion Wilde | H37: Ember tried to get his attention at the bar by ‘accidentally’ nudging his drink. He greeted her, but she ignored him and nudged the drink again. When he didn’t respond, she kept going until she pushed his drink off the bar into his lap.
A38: =IFERROR(__xludf.DUMMYFUNCTION("""COMPUTED_VALUE"""),"Buzzkill introduced Elsewhich to me and said they would be investigating my charge. I told them I didn't do it.. They are thinking it was an animal.") -> Buzzkill introduced Elsewhich to me and said they would be investigating my charge. I told them I didn't do it.. They are thinking it was an animal. | F38: =if(Dashboard!G6=true,"Yes!","No") -> Yes! | G38: Keeper’s Sunday Vision | I38: Need | J38: =COUNTif(F38,"Yes!") -> 1
A39: =IFERROR(__xludf.DUMMYFUNCTION("""COMPUTED_VALUE"""),"I told them about the knocked-ver merchandise in the same conversation in which Karla mentioned the ""gross mess of hair.""") -> I told them about the knocked-ver merchandise in the same conversation in which Karla mentioned the "gross mess of hair." | F39: =if(Elsewhich_Import!B54=true,"Yes!","No") -> No | G39: Bailey (Again) | H39: Ember *is like* Bailey, not Ember likes Bailey. | I39: Need | J39: =COUNTif(F39,"Yes!") -> 0
A40: =IFERROR(__xludf.DUMMYFUNCTION("""COMPUTED_VALUE"""),"Already suspect it's an animal of some kind - Sat noon") -> Already suspect it's an animal of some kind - Sat noon | F40: =if(Elsewhich_Import!B55=true,"Yes!","No") -> No | G40: Teknos | H40: Teknos mentions he has something he would like to show the party | I40: Need | J40: =COUNTif(F40,"Yes!") -> 0
A41: =IFERROR(__xludf.DUMMYFUNCTION("""COMPUTED_VALUE"""),"Phineas and Karmin gave full blast to one engaged oarty menber") -> Phineas and Karmin gave full blast to one engaged oarty menber | F41: =if(Elsewhich_Import!B56=true,"Yes!","No") -> No | G41: Teknos (And Ember) | H41: Teknos unpacks his new targeting wand (laser pointer) from a crate. Ember shows interest in the light and may even crawl into the crate lid. The party learns: Ember used to be a cat She left “presents” at the shop for Karmin She plays there knocking things off shelves and sleeping on boxes She doesn’t care about the charges against Evelyn Teknos should remind the party about laser safety if he loans them the wand. | I41: Need | J41: =COUNTif(F41,"Yes!") -> 0
A42: =IFERROR(__xludf.DUMMYFUNCTION("""COMPUTED_VALUE"""),"Talked with four of them and they have already started to think about it being a large cat BT 9:30am sat") -> Talked with four of them and they have already started to think about it being a large cat BT 9:30am sat | F42: =if(Elsewhich_Import!B57=true,"Yes!","No") -> No | G42: Buzzkill | H42: Evelyn hasn't done anything to the Smirches’ shop. Everything that’s happened - merchandise pushed off shelves, foul globs of hair on the floor, animal carcasses left by the door - is intended not to sabotage the shop’s business, but because visiting influencer Ember has been hanging out with Karmin Smirch. And unbeknownst to World’s Edge, Ember used to be - and still essentially is - a cat. | I42: Need | J42: =COUNTif(F42,"Yes!") -> 0
A43: =IFERROR(__xludf.DUMMYFUNCTION("""COMPUTED_VALUE"""),"Entire party at breakfast very engaged with Karla when she was talking about the mean lady and the ball of hair") -> Entire party at breakfast very engaged with Karla when she was talking about the mean lady and the ball of hair
A44: =IFERROR(__xludf.DUMMYFUNCTION("""COMPUTED_VALUE"""),"Talked to three of them, they were interested, they were very sweet. They mentioned other info they had heard about the Smirches. -MFL") -> Talked to three of them, they were interested, they were very sweet. They mentioned other info they had heard about the Smirches. -MFL
A45: =IFERROR(__xludf.DUMMYFUNCTION("""COMPUTED_VALUE"""),"ember is cool - they think so too. Talked up how leather and fur look good on her, esp fur ER") -> ember is cool - they think so too. Talked up how leather and fur look good on her, esp fur ER
A46: =IFERROR(__xludf.DUMMYFUNCTION("""COMPUTED_VALUE"""),"They are super into Ember and very engaged. Already gelled as a party and great fun Fri night. - BW") -> They are super into Ember and very engaged. Already gelled as a party and great fun Fri night. - BW
A47: =IFERROR(__xludf.DUMMYFUNCTION("""COMPUTED_VALUE"""),"Asked me if I knew any cats. Seemed too much of a cluehammer to mention Ember. Saw them again, they straight up asked me if Ember was like me, I said ""she likes me""") -> Asked me if I knew any cats. Seemed too much of a cluehammer to mention Ember. Saw them again, they straight up asked me if Ember was like me, I said "she likes me"
A48: =IFERROR(__xludf.DUMMYFUNCTION("""COMPUTED_VALUE"""),"Gave the info to one party member. They seemed very interested, and Elvie confirmed that they're suspicious of Ember so it probably landed.") -> Gave the info to one party member. They seemed very interested, and Elvie confirmed that they're suspicious of Ember so it probably landed.
A49: =IFERROR(__xludf.DUMMYFUNCTION("""COMPUTED_VALUE"""),"They seem pretty clear on this being Ember ... not 100% ""she's a cat"" but close. -TR Sat. 11pm") -> They seem pretty clear on this being Ember ... not 100% "she's a cat" but close. -TR Sat. 11pm
A50: =IFERROR(__xludf.DUMMYFUNCTION("""COMPUTED_VALUE"""),"Read runes re: Lorelei sword with Kemma: lightning, mountain, candle (EC)") -> Read runes re: Lorelei sword with Kemma: lightning, mountain, candle (EC)
A51: =IFERROR(__xludf.DUMMYFUNCTION("""COMPUTED_VALUE"""),"Very friendly, said they would shout ""Kora"" and run up the hill if they were attacked (CL)") -> Very friendly, said they would shout "Kora" and run up the hill if they were attacked (CL)
A52: =IFERROR(__xludf.DUMMYFUNCTION("""COMPUTED_VALUE"""),"They gave Kira nickname ""Shadeslinger."" Kerrick was away and after talking to the traveler, I said ""oh, Kerrick is like a traveler, just really cool!"" (referring to his crown) Hilariously offended, nickname was born. (Kels)") -> They gave Kira nickname "Shadeslinger." Kerrick was away and after talking to the traveler, I said "oh, Kerrick is like a traveler, just really cool!" (referring to his crown) Hilariously offended, nickname was born. (Kels)
A53: =IFERROR(__xludf.DUMMYFUNCTION("""COMPUTED_VALUE"""),"Told full party about Golden Note for Samuelson. - Mike S") -> Told full party about Golden Note for Samuelson. - Mike S
A54: =IFERROR(__xludf.DUMMYFUNCTION("""COMPUTED_VALUE"""),".Ander #2 restored 2 free hits. Party in good spirits.") -> .Ander #2 restored 2 free hits. Party in good spirits.
A55: =IFERROR(__xludf.DUMMYFUNCTION("""COMPUTED_VALUE"""),"Party photo taken -Mirin") -> Party photo taken -Mirin
A56: =IFERROR(__xludf.DUMMYFUNCTION("""COMPUTED_VALUE"""),"They think Ember and Shadow might be a thing? -Mirin") -> They think Ember and Shadow might be a thing? -Mirin
A57: =IFERROR(__xludf.DUMMYFUNCTION("""COMPUTED_VALUE"""),"They have a beautiful woodblock card print of a drunk sheep, and they write down personal notes or information for us on the back. Very talkative group as a whole. --TR") -> They have a beautiful woodblock card print of a drunk sheep, and they write down personal notes or information for us on the back. Very talkative group as a whole. --TR
A58: =IFERROR(__xludf.DUMMYFUNCTION("""COMPUTED_VALUE"""),"They wrote down their story from Tinker Bill's challenge and left us a beautiful card with it all! - DN") -> They wrote down their story from Tinker Bill's challenge and left us a beautiful card with it all! - DN
A59: =IFERROR(__xludf.DUMMYFUNCTION("""COMPUTED_VALUE"""),"Had combat training at Valerius house and did well. Party was having fun. - Neal, 1pm Sat") -> Had combat training at Valerius house and did well. Party was having fun. - Neal, 1pm Sat
A60: =IFERROR(__xludf.DUMMYFUNCTION("""COMPUTED_VALUE"""),"Scheduled meeting for 9:45 with reporter from elsewhich - Mike Dion, 2pm Sat") -> Scheduled meeting for 9:45 with reporter from elsewhich - Mike Dion, 2pm Sat
A61: =IFERROR(__xludf.DUMMYFUNCTION("""COMPUTED_VALUE"""),"Pretty sure it's a cat, think maybe it's Buzzkill's. -Ab, Sat lunch") -> Pretty sure it's a cat, think maybe it's Buzzkill's. -Ab, Sat lunch
A62: =IFERROR(__xludf.DUMMYFUNCTION("""COMPUTED_VALUE"""),"Didn't really ""get it"" when we challenged them to think about their stated value for ""grapes are better as a bunch"" but did a lot of individualism in Mind of a Mad Man. - Kels") -> Didn't really "get it" when we challenged them to think about their stated value for "grapes are better as a bunch" but did a lot of individualism in Mind of a Mad Man. - Kels
A63: =IFERROR(__xludf.DUMMYFUNCTION("""COMPUTED_VALUE"""),"Before soul speaking last night the maker said ""Guys do you think Ember is a cat in the same way Bailey is dog?""-TB") -> Before soul speaking last night the maker said "Guys do you think Ember is a cat in the same way Bailey is dog?"-TB

Sheet Dolorón_Import
A1: =IFERROR(__xludf.DUMMYFUNCTION("IMPORTRANGE(""https://docs.google.com/spreadsheets/d/1PPFix0KE5FV0_ekB8X93l4fBTTlhI3_4FnP7klgfg_Y/edit?gid=0#gid=0"", ""Dolorón!a1:f100"")"),"DOLORÓN") -> DOLORÓN | C1: =IFERROR(__xludf.DUMMYFUNCTION("""COMPUTED_VALUE"""),"Dodi (Maisie Sturtevant)") -> Dodi (Maisie Sturtevant)
E2: =IFERROR(__xludf.DUMMYFUNCTION("""COMPUTED_VALUE"""),"Caster") -> Caster | F2: =IFERROR(__xludf.DUMMYFUNCTION("""COMPUTED_VALUE"""),"Ambien Yawn; Doloron champion belt") -> Ambien Yawn; Doloron champion belt
A3: =IFERROR(__xludf.DUMMYFUNCTION("""COMPUTED_VALUE"""),"PARTY PATH") -> PARTY PATH | E3: =IFERROR(__xludf.DUMMYFUNCTION("""COMPUTED_VALUE"""),"Keeper") -> Keeper | F3: =IFERROR(__xludf.DUMMYFUNCTION("""COMPUTED_VALUE"""),"Isabel; glasses, rose jacket") -> Isabel; glasses, rose jacket
A4: =IFERROR(__xludf.DUMMYFUNCTION("""COMPUTED_VALUE"""),"Character") -> Character | B4: =IFERROR(__xludf.DUMMYFUNCTION("""COMPUTED_VALUE"""),"Gave Item/Info") -> Gave Item/Info | C4: =IFERROR(__xludf.DUMMYFUNCTION("""COMPUTED_VALUE"""),"Notes") -> Notes | E4: =IFERROR(__xludf.DUMMYFUNCTION("""COMPUTED_VALUE"""),"Maker") -> Maker | F4: =IFERROR(__xludf.DUMMYFUNCTION("""COMPUTED_VALUE"""),"Gaius; leather bracers w/pewter studs") -> Gaius; leather bracers w/pewter studs
A5: =IFERROR(__xludf.DUMMYFUNCTION("""COMPUTED_VALUE"""),"Mick Peacock") -> Mick Peacock | B5: =IFERROR(__xludf.DUMMYFUNCTION("""COMPUTED_VALUE"""),TRUE) -> TRUE | E5: =IFERROR(__xludf.DUMMYFUNCTION("""COMPUTED_VALUE"""),"Ranger") -> Ranger | F5: =IFERROR(__xludf.DUMMYFUNCTION("""COMPUTED_VALUE"""),"Arcadia; long curly red/blonde hair, glasses") -> Arcadia; long curly red/blonde hair, glasses
A6: =IFERROR(__xludf.DUMMYFUNCTION("""COMPUTED_VALUE"""),"Lexia") -> Lexia | B6: =IFERROR(__xludf.DUMMYFUNCTION("""COMPUTED_VALUE"""),FALSE) -> FALSE | E6: =IFERROR(__xludf.DUMMYFUNCTION("""COMPUTED_VALUE"""),"Seeker") -> Seeker | F6: =IFERROR(__xludf.DUMMYFUNCTION("""COMPUTED_VALUE"""),"Gwendyl; rose tabard, backward cap") -> Gwendyl; rose tabard, backward cap
A7: =IFERROR(__xludf.DUMMYFUNCTION("""COMPUTED_VALUE"""),"Jpeg") -> Jpeg | B7: =IFERROR(__xludf.DUMMYFUNCTION("""COMPUTED_VALUE"""),TRUE) -> TRUE | E7: =IFERROR(__xludf.DUMMYFUNCTION("""COMPUTED_VALUE"""),"Traveler") -> Traveler | F7: =IFERROR(__xludf.DUMMYFUNCTION("""COMPUTED_VALUE"""),"Otter; green tabard, grey beard") -> Otter; green tabard, grey beard
A8: =IFERROR(__xludf.DUMMYFUNCTION("""COMPUTED_VALUE"""),"Phyllis Fieri") -> Phyllis Fieri | B8: =IFERROR(__xludf.DUMMYFUNCTION("""COMPUTED_VALUE"""),TRUE) -> TRUE | C8: =IFERROR(__xludf.DUMMYFUNCTION("""COMPUTED_VALUE"""),"4th Friday - gave them letter w list of items. Great teamwork on challenge. Excellent group dynamics! ") -> 4th Friday - gave them letter w list of items. Great teamwork on challenge. Excellent group dynamics!
A9: =IFERROR(__xludf.DUMMYFUNCTION("""COMPUTED_VALUE"""),"Crabtree") -> Crabtree | B9: =IFERROR(__xludf.DUMMYFUNCTION("""COMPUTED_VALUE"""),TRUE) -> TRUE | C9: =IFERROR(__xludf.DUMMYFUNCTION("""COMPUTED_VALUE"""),"1st Sat - gave them snake eye talisman (Maker is wearing as a necklace); traveler was distracted by writing his notes, not paying attention to ""bucket challenge"", but participated when I addressed him specifically; caster renewed the whirlwind spell; Tr"&"aveler seems to be trying to be in charge & direct the rest of the team's behavior, everyone was attending politely to him, but I could imagine that being a stress point .") -> 1st Sat - gave them snake eye talisman (Maker is wearing as a necklace); traveler was distracted by writing his notes, not paying attention to "bucket challenge", but participated when I addressed him specifically; caster renewed the whirlwind spell; Traveler seems to be trying to be in charge & direct the rest of the team's behavior, everyone was attending politely to him, but I could imagine that being a stress point .
A10: =IFERROR(__xludf.DUMMYFUNCTION("""COMPUTED_VALUE"""),"Isaiah Cooke") -> Isaiah Cooke | B10: =IFERROR(__xludf.DUMMYFUNCTION("""COMPUTED_VALUE"""),TRUE) -> TRUE | C10: =IFERROR(__xludf.DUMMYFUNCTION("""COMPUTED_VALUE"""),"They were fantastic! Super invested and had a convo and combat! Love them") -> They were fantastic! Super invested and had a convo and combat! Love them
A11: =IFERROR(__xludf.DUMMYFUNCTION("""COMPUTED_VALUE"""),"Malachi (Don't Give Item)") -> Malachi (Don't Give Item) | B11: =IFERROR(__xludf.DUMMYFUNCTION("""COMPUTED_VALUE"""),TRUE) -> TRUE | C11: =IFERROR(__xludf.DUMMYFUNCTION("""COMPUTED_VALUE"""),"Update - Lunch: I spoke to Doloron at their table. They asked about the Merula Fruit Cordial. I told them to find me at the Roamer Camp and play Managers and Peons if they would like to get the Cordial. After they've done that, I'd be happy to meet them a"&"t 10:00am on Sunday. Sat AM: I have not seen Doloron yet, and am concerned because it is nearing the end of my morning face part.") -> Update - Lunch: I spoke to Doloron at their table. They asked about the Merula Fruit Cordial. I told them to find me at the Roamer Camp and play Managers and Peons if they would like to get the Cordial. After they've done that, I'd be happy to meet them at 10:00am on Sunday. Sat AM: I have not seen Doloron yet, and am concerned because it is nearing the end of my morning face part.
A12: =IFERROR(__xludf.DUMMYFUNCTION("""COMPUTED_VALUE"""),"Kora Peacekeeper") -> Kora Peacekeeper | B12: =IFERROR(__xludf.DUMMYFUNCTION("""COMPUTED_VALUE"""),TRUE) -> TRUE
A13: =IFERROR(__xludf.DUMMYFUNCTION("""COMPUTED_VALUE"""),"Pansy Golden") -> Pansy Golden | B13: =IFERROR(__xludf.DUMMYFUNCTION("""COMPUTED_VALUE"""),FALSE) -> FALSE | C13: =IFERROR(__xludf.DUMMYFUNCTION("""COMPUTED_VALUE"""),"At breakfast, made a deal that they will cheer Ned up and I will give them the sphere. Planned for lunch Sat --HA Talked to Bracken about this after lunch, didn't find Ned and trying to ask people to see what he likes -- RS") -> At breakfast, made a deal that they will cheer Ned up and I will give them the sphere. Planned for lunch Sat --HA Talked to Bracken about this after lunch, didn't find Ned and trying to ask people to see what he likes -- RS
A14: =IFERROR(__xludf.DUMMYFUNCTION("""COMPUTED_VALUE"""),"Stevie Peacock") -> Stevie Peacock | B14: =IFERROR(__xludf.DUMMYFUNCTION("""COMPUTED_VALUE"""),TRUE) -> TRUE
A15: =IFERROR(__xludf.DUMMYFUNCTION("""COMPUTED_VALUE"""),"Eugenie Bright") -> Eugenie Bright | B15: =IFERROR(__xludf.DUMMYFUNCTION("""COMPUTED_VALUE"""),TRUE) -> TRUE | C15: =IFERROR(__xludf.DUMMYFUNCTION("""COMPUTED_VALUE"""),"Overheard conversartion on needing gemwing butterfly.") -> Overheard conversartion on needing gemwing butterfly.
A16: =IFERROR(__xludf.DUMMYFUNCTION("""COMPUTED_VALUE"""),"Bracken") -> Bracken | B16: =IFERROR(__xludf.DUMMYFUNCTION("""COMPUTED_VALUE"""),TRUE) -> TRUE | C16: =IFERROR(__xludf.DUMMYFUNCTION("""COMPUTED_VALUE"""),"Had a good story and really considerate about taking something that was from my grandfather, all around went well! -- RS") -> Had a good story and really considerate about taking something that was from my grandfather, all around went well! -- RS
A17: =IFERROR(__xludf.DUMMYFUNCTION("""COMPUTED_VALUE"""),"Ghost Theater") -> Ghost Theater | B17: =IFERROR(__xludf.DUMMYFUNCTION("""COMPUTED_VALUE"""),TRUE) -> TRUE | C17: =IFERROR(__xludf.DUMMYFUNCTION("""COMPUTED_VALUE"""),"Very engaged, however the taller gentleman did a fake face-first into the sand ""Fainting"" that we treated seriously. FFS. Dave") -> Very engaged, however the taller gentleman did a fake face-first into the sand "Fainting" that we treated seriously. FFS. Dave | D17: =IFERROR(__xludf.DUMMYFUNCTION("""COMPUTED_VALUE"""),"Sat AM- Aria showed them Golden Page, and explained ""theater belongs to the ghosts now"" DG") -> Sat AM- Aria showed them Golden Page, and explained "theater belongs to the ghosts now" DG
A18: =IFERROR(__xludf.DUMMYFUNCTION("""COMPUTED_VALUE"""),"Malachi (Sunday)") -> Malachi (Sunday) | B18: =IFERROR(__xludf.DUMMYFUNCTION("""COMPUTED_VALUE"""),FALSE) -> FALSE
A19: =IFERROR(__xludf.DUMMYFUNCTION("""COMPUTED_VALUE"""),"Pixies") -> Pixies | B19: =IFERROR(__xludf.DUMMYFUNCTION("""COMPUTED_VALUE"""),FALSE) -> FALSE
A22: =IFERROR(__xludf.DUMMYFUNCTION("""COMPUTED_VALUE"""),"CHARGE INFO") -> CHARGE INFO | B22: =IFERROR(__xludf.DUMMYFUNCTION("""COMPUTED_VALUE"""),"(Katherine Carmichael)") -> (Katherine Carmichael)
A23: =IFERROR(__xludf.DUMMYFUNCTION("""COMPUTED_VALUE"""),"Character") -> Character | B23: =IFERROR(__xludf.DUMMYFUNCTION("""COMPUTED_VALUE"""),"Gave Info") -> Gave Info | C23: =IFERROR(__xludf.DUMMYFUNCTION("""COMPUTED_VALUE"""),"Notes") -> Notes
A24: =IFERROR(__xludf.DUMMYFUNCTION("""COMPUTED_VALUE"""),"Pearl Bryce") -> Pearl Bryce | B24: =IFERROR(__xludf.DUMMYFUNCTION("""COMPUTED_VALUE"""),TRUE) -> TRUE | C24: =IFERROR(__xludf.DUMMYFUNCTION("""COMPUTED_VALUE"""),"Seem to at least like pearl! HOORAY. Ask her to help them investigate pixies, she said sure after she finishes the Katherine Carmicheal article (Friday Night)-TB Charge given, maker seems invested and doesn't like Verrin. Some other party members skeptica"&"l of Katherine. They are asking who would benefit from besmirching Katherine (saturyday 1:45)-TB") -> Seem to at least like pearl! HOORAY. Ask her to help them investigate pixies, she said sure after she finishes the Katherine Carmicheal article (Friday Night)-TB Charge given, maker seems invested and doesn't like Verrin. Some other party members skeptical of Katherine. They are asking who would benefit from besmirching Katherine (saturyday 1:45)-TB
A25: =IFERROR(__xludf.DUMMYFUNCTION("""COMPUTED_VALUE"""),"Mila") -> Mila | B25: =IFERROR(__xludf.DUMMYFUNCTION("""COMPUTED_VALUE"""),FALSE) -> FALSE
A26: =IFERROR(__xludf.DUMMYFUNCTION("""COMPUTED_VALUE"""),"Melados") -> Melados | B26: =IFERROR(__xludf.DUMMYFUNCTION("""COMPUTED_VALUE"""),FALSE) -> FALSE
A27: =IFERROR(__xludf.DUMMYFUNCTION("""COMPUTED_VALUE"""),"Jack Johnson") -> Jack Johnson | B27: =IFERROR(__xludf.DUMMYFUNCTION("""COMPUTED_VALUE"""),FALSE) -> FALSE
